Workbook

Sheet combined_protein_level
A1: precursor_protein | B1: mismatch_precursor_id_number | C1: mismatch_evidence_peptides_scans | D1: mismatch_n_noncontained_le9 | E1: matched_precursor_id_number | F1: matched_evidence_peptides_scans | G1: matched_n_noncontained_le9 | H1: evidence_peptides_scans | I1: combined_n_noncontained_le9 | J1: In_2.1.22-only
A2: O60330 | B2: 28 | C2: [('GQVICFIQGNLPFK', 2375, 'lost_3_aa_Nterm', True, 'Missed'), ('GQVICFIQGNLPFK', 2374, 'lost_3_aa_Nterm', True, 'Missed'), ('GQVICFIQGNLPFK', 2379, 'lost_3_aa_Nterm', True, 'Missed'), ('GQVICFIQGNLPFK', 2377, 'lost_3_aa_Nterm', True, 'Missed'), ('GQVICFIQGNLPFK', 2378, 'lost_3_aa_Nterm', True, 'Missed'), ('GQVICFIQGNLPFK', 2376, 'lost_3_aa_Nterm', True, 'Missed'), ('NGQVICFIQGNLPFK', 2397, 'lost_3_aa_Nterm', False, 'Missed'), ('NGQVICFIQGNLPFK', 2398, 'lost_3_aa_Nterm', False, 'Missed'), ('NGQVICFIQGNLPFK', 2395, 'lost_3_aa_Nterm', False, 'Missed'), ('NGQVICFIQGNLPFK', 2396, 'lost_3_aa_Nterm', False, 'Missed'), ('TQIRYSVPEELEKG', 2412, 'IDENTIFIED', True, 'Missed'), ('YVDDKAAQVF', 2423, 'HLA1', True, 'Missed'), ('IVQNGADGSKY', 2322, 'IDENTIFIED', True, 'Missed'), ('NGQVICFIQGNLPFK', 2399, 'lost_3_aa_Nterm', False, 'Missed'), ('IVQNGADGSKY', 2323, 'IDENTIFIED', True, 'Missed'), ('SSFDYEQFRDLQVK', 2307, 'IDENTIFIED', True, 'Missed'), ('IVQNGADGSKY', 2324, 'IDENTIFIED', True, 'Missed'), ('LLQASGGGLTGAPASHFVGVDGVQAFLQTYSHEVSLTTDSR', 2334, 'peptide_length_>_40', True, 'Missed'), ('LLQASGGGLTGAPASHFVGVDGVQAFLQTYSHEVSLTTDSR', 2330, 'peptide_length_>_40', True, 'Missed'), ('AQPEYRASVPENLALG', 2318, 'IDENTIFIED', True, 'Missed'), ('LLQASGGGLTGAPASHFVGVDGVQAFLQTYSHEVSLTTDSR', 2337, 'peptide_length_>_40', True, 'Missed'), ('LLQASGGGLTGAPASHFVGVDGVQAFLQTYSHEVSLTTDSR', 2331, 'peptide_length_>_40', True, 'Missed'), ('LLQASGGGLTGAPASHFVGVDGVQAFLQTYSHEVSLTTDSR', 2338, 'peptide_length_>_40', True, 'Missed'), ('LLQASGGGLTGAPASHFVGVDGVQAFLQTYSHEVSLTTDSR', 2336, 'peptide_length_>_40', True, 'Missed'), ('LLQASGGGLTGAPASHFVGVDGVQAFLQTYSHEVSLTTDSR', 2333, 'peptide_length_>_40', True, 'Missed'), ('LLQASGGGLTGAPASHFVGVDGVQAFLQTYSHEVSLTTDSR', 2335, 'peptide_length_>_40', True, 'Missed'), ('LLQASGGGLTGAPASHFVGVDGVQAFLQTYSHEVSLTTDSR', 2332, 'peptide_length_>_40', True, 'Missed'), ('LLQASGGGLTGAPASHFVGVDGVQAFLQTYSHEVSLTTDSR', 2339, 'peptide_length_>_40', True, 'Missed')] | D2: 7 | E2: 98 | F2: [('VMVLDANDNAPAFAQPEYR', 2345, nan, True, 'Matched'), ('ALSSFDYEQFRDLQ', 2380, nan, False, 'Matched'), ('ALSSFDYEQFRDLQ', 2382, nan, False, 'Matched'), ('LSSFDYEQFRDLQV', 2394, nan, False, 'Matched'), ('ALSSFDYEQFRDLQ', 2383, nan, False, 'Matched'), ('IVQNGADGSKY', 2325, nan, True, 'Matched'), ('SSFDYEQFRDLQVK', 2303, nan, False, 'Matched'), ('ALSSFDYEQFRDLQ', 2381, nan, False, 'Matched'), ('LSSFDYEQFRDLQ', 2349, nan, True, 'Matched'), ('LSSFDYEQFRDLQV', 2391, nan, False, 'Matched'), ('LSSFDYEQFRDLQV', 2392, nan, False, 'Matched'), ('LSSFDYEQFRDLQ', 2346, nan, True, 'Matched'), ('IVQNGADGSKY', 2326, nan, True, 'Matched'), ('LSSFDYEQFRDLQ', 2348, nan, True, 'Matched'), ('IVQNGADGSKY', 2327, nan, True, 'Matched'), ('LSSFDYEQFRDLQV', 2390, nan, False, 'Matched'), ('DYEQFRDLQVK', 2419, nan, True, 'Matched'), ('LSSFDYEQFRDLQ', 2350, nan, True, 'Matched'), ('IVQNGADGSKY', 2329, nan, True, 'Matched'), ('SYGNYYSLVTDIVLDR', 2401, nan, True, 'Matched'), ('SSFDYEQFRDLQVK', 2301, nan, False, 'Matched'), ('LSSFDYEQFRDLQ', 2347, nan, True, 'Matched'), ('SSFDYEQFRDLQVK', 2299, nan, False, 'Matched'), ('SYGNYYSLVTDIVLDR', 2402, nan, True, 'Matched'), ('SYGNYYSLVTDIVLDR', 2400, nan, True, 'Matched'), ('SSFDYEQFRDLQVK', 2302, nan, False, 'Matched'), ('NSLQSYELSPNTHFSLIVQNGADGSK', 2420, nan, True, 'Matched'), ('TQIRYSVPEELEKG', 2410, nan, True, 'Matched'), ('SEPLLLSGDSVFSK', 2369, nan, True, 'Matched'), ('YSFRYVDDKAAQVFK', 2422, nan, True, 'Matched'), ('YALSSFDYEQFRDLQVK', 2359, nan, False, 'Matched'), ('TQIRYSVPEELEKG', 2409, nan, True, 'Matched'), ('DSHGLIEQAPPNTDWR', 2366, nan, True, 'Matched'), ('LSSFDYEQFRDLQV', 2393, nan, False, 'Matched'), ('DSHGLIEQAPPNTDWR', 2364, nan, True, 'Matched'), ('YALSSFDYEQFRDLQVK', 2355, nan, False, 'Matched'), ('YALSSFDYEQFRDLQVK', 2357, nan, False, 'Matched'), ('YALSSFDYEQFRDLQVK', 2358, nan, False, 'Matched'), ('FPLPHAWDPDIGK', 2368, nan, True, 'Matched'), ('SEPLLLSGDSVFSK', 2372, nan, True, 'Matched'), ('YALSSFDYEQFRDLQVK', 2356, nan, False, 'Matched'), ('DSHGLIEQAPPNTDWR', 2363, nan, True, 'Matched'), ('ALSSFDYEQFRDLQ', 2384, nan, False, 'Matched'), ('SYGNYYSLVTDIVLDR', 2403, nan, True, 'Matched'), ('FPLPHAWDPDIGK', 2367, nan, True, 'Matched'), ('SEPLLLSGDSVFSK', 2370, nan, True, 'Matched'), ('LSSFDYEQFRDLQ', 2353, nan, True, 'Matched'), ('SHLIFPQPNYADMLVSQESFEK', 2298, nan, True, 'Matched'), ('AAHHLVLTASDGGDPVR', 2404, nan, True, 'Matched'), ('SSFDYEQFRDLQVK', 2308, nan, False, 'Matched'), ('SSFDYEQFRDLQVK', 2300, nan, False, 'Matched'), ('SSFDYEQFRDLQVK', 2309, nan, False, 'Matched'), ('YALSSFDYEQFRDLQVK', 2360, nan, False, 'Matched'), ('SSFDYEQFRDLQVK', 2306, nan, False, 'Matched'), ('IDREELCMGAIK', 2413, nan, True, 'Matched'), ('YALSSFDYEQFRDLQVK', 2361, nan, False, 'Matched'), ('LSSFDYEQFRDLQ', 2351, nan, True, 'Matched'), ('CQLNLDILMEDK', 2418, nan, True, 'Matched'), ('LEIKISENAATEMR', 2415, nan, True, 'Matched'), ('VMVLDANDNAPAFAQPEYR', 2342, nan, True, 'Matched'), ('VMVLDANDNAPAFAQPEYR', 2341, nan, True, 'Matched'), ('SSFDYEQFRDLQVK', 2305, nan, False, 'Matched'), ('LSSFDYEQFRDLQ', 2352, nan, True, 'Matched'), ('LEIKISENAATEMRFP', 2417, nan, False, 'Matched'), ('IVQNGADGSKY', 2321, nan, True, 'Matched'), ('IVQNGADGSKY', 2320, nan, True, 'Matched'), ('SSFDYEQFRDLQVK', 2304, nan, False, 'Matched'), ('LEIKISENAATEMR', 2414, nan, True, 'Matched'), ('SEPLLLSGDSVFSK', 2371, nan, True, 'Matched'), ('LSSFDYEQFRDLQ', 2354, nan, True, 'Matched'), ('LEIKISENAATEMRFP', 2416, nan, False, 'Matched'), ('TQIRYSVPEELEKG', 2411, nan, True, 'Matched'), ('FAQPEYRASVPENLALG', 2387, nan, False, 'Matched'), ('AQPEYRASVPENLAL', 2405, nan, True, 'Matched'), ('SEPLLLSGDSVFSK', 2373, nan, True, 'Matched'), ('VMVLDANDNAPAFAQPEYR', 2343, nan, True, 'Matched'), ('VMVLDANDNAPAFAQPEYR', 2340, nan, True, 'Matched'), ('VDGVQAFLQTYSHEVSLTTDSR', 2421, nan, True, 'Matched'), ('AQPEYRASVPENLALG', 2310, nan, False, 'Matched'), ('FAQPEYRASVPENLALG', 2389, nan, False, 'Matched'), ('IVQNGADGSKY', 2328, nan, True, 'Matched'), ('AQPEYRASVPENLALG', 2312, nan, False, 'Matched'), ('AQPEYRASVPENLALG', 2311, nan, False, 'Matched'), ('AQPEYRASVPENLAL', 2407, nan, True, 'Matched'), ('DSHGLIEQAPPNTDWR', 2365, nan, True, 'Matched'), ('AQPEYRASVPENLALG', 2314, nan, False, 'Matched'), ('AQPEYRASVPENLALG', 2313, nan, False, 'Matched'), ('VMVLDANDNAPAFAQPEYR', 2344, nan, True, 'Matched'), ('AQPEYRASVPENLALG', 2315, nan, False, 'Matched'), ('AQPEYRASVPENLALG', 2317, nan, False, 'Matched'), ('YALSSFDYEQFRDLQVK', 2362, nan, False, 'Matched'), ('AQPEYRASVPENLAL', 2408, nan, True, 'Matched'), ('AQPEYRASVPENLALG', 2319, nan, False, 'Matched'), ('FAQPEYRASVPENLALG', 2388, nan, False, 'Matched'), ('AQPEYRASVPENLAL', 2406, nan, True, 'Matched'), ('AQPEYRASVPENLALG', 2316, nan, False, 'Matched'), ('FAQPEYRASVPENLALG', 2385, nan, False, 'Matched'), ('FAQPEYRASVPENLALG', 2386, nan, False, 'Matched')] | G2: 18 | H2: [('GQVICFIQGNLPFK', 2375, 'lost_3_aa_Nterm', True, 'Missed'), ('GQVICFIQGNLPFK', 2374, 'lost_3_aa_Nterm', True, 'Missed'), ('GQVICFIQGNLPFK', 2379, 'lost_3_aa_Nterm', True, 'Missed'), ('GQVICFIQGNLPFK', 2377, 'lost_3_aa_Nterm', True, 'Missed'), ('GQVICFIQGNLPFK', 2378, 'lost_3_aa_Nterm', True, 'Missed'), ('GQVICFIQGNLPFK', 2376, 'lost_3_aa_Nterm', True, 'Missed'), ('NGQVICFIQGNLPFK', 2397, 'lost_3_aa_Nterm', False, 'Missed'), ('NGQVICFIQGNLPFK', 2398, 'lost_3_aa_Nterm', False, 'Missed'), ('NGQVICFIQGNLPFK', 2395, 'lost_3_aa_Nterm', False, 'Missed'), ('NGQVICFIQGNLPFK', 2396, 'lost_3_aa_Nterm', False, 'Missed'), ('TQIRYSVPEELEKG', 2412, 'IDENTIFIED', True, 'Missed'), ('YVDDKAAQVF', 2423, 'HLA1', True, 'Missed'), ('IVQNGADGSKY', 2322, 'IDENTIFIED', True, 'Missed'), ('NGQVICFIQGNLPFK', 2399, 'lost_3_aa_Nterm', False, 'Missed'), ('IVQNGADGSKY', 2323, 'IDENTIFIED', True, 'Missed'), ('SSFDYEQFRDLQVK', 2307, 'IDENTIFIED', False, 'Missed'), ('IVQNGADGSKY', 2324, 'IDENTIFIED', True, 'Missed'), ('LLQASGGGLTGAPASHFVGVDGVQAFLQTYSHEVSLTTDSR', 2334, 'peptide_length_>_40', False, 'Missed'), ('LLQASGGGLTGAPASHFVGVDGVQAFLQTYSHEVSLTTDSR', 2330, 'peptide_length_>_40', False, 'Missed'), ('AQPEYRASVPENLALG', 2318, 'IDENTIFIED', False, 'Missed'), ('LLQASGGGLTGAPASHFVGVDGVQAFLQTYSHEVSLTTDSR', 2337, 'peptide_length_>_40', False, 'Missed'), ('LLQASGGGLTGAPASHFVGVDGVQAFLQTYSHEVSLTTDSR', 2331, 'peptide_length_>_40', False, 'Missed'), ('LLQASGGGLTGAPASHFVGVDGVQAFLQTYSHEVSLTTDSR', 2338, 'peptide_length_>_40', False, 'Missed'), ('LLQASGGGLTGAPASHFVGVDGVQAFLQTYSHEVSLTTDSR', 2336, 'peptide_length_>_40', False, 'Missed'), ('LLQASGGGLTGAPASHFVGVDGVQAFLQTYSHEVSLTTDSR', 2333, 'peptide_length_>_40', False, 'Missed'), ('LLQASGGGLTGAPASHFVGVDGVQAFLQTYSHEVSLTTDSR', 2335, 'peptide_length_>_40', False, 'Missed'), ('LLQASGGGLTGAPASHFVGVDGVQAFLQTYSHEVSLTTDSR', 2332, 'peptide_length_>_40', False, 'Missed'), ('LLQASGGGLTGAPASHFVGVDGVQAFLQTYSHEVSLTTDSR', 2339, 'peptide_length_>_40', False, 'Missed'), ('VMVLDANDNAPAFAQPEYR', 2345, nan, True, 'Matched'), ('ALSSFDYEQFRDLQ', 2380, nan, False, 'Matched'), ('ALSSFDYEQFRDLQ', 2382, nan, False, 'Matched'), ('LSSFDYEQFRDLQV', 2394, nan, False, 'Matched'), ('ALSSFDYEQFRDLQ', 2383, nan, False, 'Matched'), ('IVQNGADGSKY', 2325, nan, True, 'Matched'), ('SSFDYEQFRDLQVK', 2303, nan, False, 'Matched'), ('ALSSFDYEQFRDLQ', 2381, nan, False, 'Matched'), ('LSSFDYEQFRDLQ', 2349, nan, True, 'Matched'), ('LSSFDYEQFRDLQV', 2391, nan, False, 'Matched'), ('LSSFDYEQFRDLQV', 2392, nan, False, 'Matched'), ('LSSFDYEQFRDLQ', 2346, nan, True, 'Matched'), ('IVQNGADGSKY', 2326, nan, True, 'Matched'), ('LSSFDYEQFRDLQ', 2348, nan, True, 'Matched'), ('IVQNGADGSKY', 2327, nan, True, 'Matched'), ('LSSFDYEQFRDLQV', 2390, nan, False, 'Matched'), ('DYEQFRDLQVK', 2419, nan, True, 'Matched'), ('LSSFDYEQFRDLQ', 2350, nan, True, 'Matched'), ('IVQNGADGSKY', 2329, nan, True, 'Matched'), ('SYGNYYSLVTDIVLDR', 2401, nan, True, 'Matched'), ('SSFDYEQFRDLQVK', 2301, nan, False, 'Matched'), ('LSSFDYEQFRDLQ', 2347, nan, True, 'Matched'), ('SSFDYEQFRDLQVK', 2299, nan, False, 'Matched'), ('SYGNYYSLVTDIVLDR', 2402, nan, True, 'Matched'), ('SYGNYYSLVTDIVLDR', 2400, nan, True, 'Matched'), ('SSFDYEQFRDLQVK', 2302, nan, False, 'Matched'), ('NSLQSYELSPNTHFSLIVQNGADGSK', 2420, nan, True, 'Matched'), ('TQIRYSVPEELEKG', 2410, nan, True, 'Matched'), ('SEPLLLSGDSVFSK', 2369, nan, True, 'Matched'), ('YSFRYVDDKAAQVFK', 2422, nan, False, 'Matched'), ('YALSSFDYEQFRDLQVK', 2359, nan, False, 'Matched'), ('TQIRYSVPEELEKG', 2409, nan, True, 'Matched'), ('DSHGLIEQAPPNTDWR', 2366, nan, True, 'Matched'), ('LSSFDYEQFRDLQV', 2393, nan, False, 'Matched'), ('DSHGLIEQAPPNTDWR', 2364, nan, True, 'Matched'), ('YALSSFDYEQFRDLQVK', 2355, nan, False, 'Matched'), ('YALSSFDYEQFRDLQVK', 2357, nan, False, 'Matched'), ('YALSSFDYEQFRDLQVK', 2358, nan, False, 'Matched'), ('FPLPHAWDPDIGK', 2368, nan, True, 'Matched'), ('SEPLLLSGDSVFSK', 2372, nan, True, 'Matched'), ('YALSSFDYEQFRDLQVK', 2356, nan, False, 'Matched'), ('DSHGLIEQAPPNTDWR', 2363, nan, True, 'Matched'), ('ALSSFDYEQFRDLQ', 2384, nan, False, 'Matched'), ('SYGNYYSLVTDIVLDR', 2403, nan, True, 'Matched'), ('FPLPHAWDPDIGK', 2367, nan, True, 'Matched'), ('SEPLLLSGDSVFSK', 2370, nan, True, 'Matched'), ('LSSFDYEQFRDLQ', 2353, nan, True, 'Matched'), ('SHLIFPQPNYADMLVSQESFEK', 2298, nan, True, 'Matched'), ('AAHHLVLTASDGGDPVR', 2404, nan, True, 'Matched'), ('SSFDYEQFRDLQVK', 2308, nan, False, 'Matched'), ('SSFDYEQFRDLQVK', 2300, nan, False, 'Matched'), ('SSFDYEQFRDLQVK', 2309, nan, False, 'Matched'), ('YALSSFDYEQFRDLQVK', 2360, nan, False, 'Matched'), ('SSFDYEQFRDLQVK', 2306, nan, False, 'Matched'), ('IDREELCMGAIK', 2413, nan, True, 'Matched'), ('YALSSFDYEQFRDLQVK', 2361, nan, False, 'Matched'), ('LSSFDYEQFRDLQ', 2351, nan, True, 'Matched'), ('CQLNLDILMEDK', 2418, nan, True, 'Matched'), ('LEIKISENAATEMR', 2415, nan, True, 'Matched'), ('VMVLDANDNAPAFAQPEYR', 2342, nan, True, 'Matched'), ('VMVLDANDNAPAFAQPEYR', 2341, nan, True, 'Matched'), ('SSFDYEQFRDLQVK', 2305, nan, False, 'Matched'), ('LSSFDYEQFRDLQ', 2352, nan, True, 'Matched'), ('LEIKISENAATEMRFP', 2417, nan, False, 'Matched'), ('IVQNGADGSKY', 2321, nan, True, 'Matched'), ('IVQNGADGSKY', 2320, nan, True, 'Matched'), ('SSFDYEQFRDLQVK', 2304, nan, False, 'Matched'), ('LEIKISENAATEMR', 2414, nan, True, 'Matched'), ('SEPLLLSGDSVFSK', 2371, nan, True, 'Matched'), ('LSSFDYEQFRDLQ', 2354, nan, True, 'Matched'), ('LEIKISENAATEMRFP', 2416, nan, False, 'Matched'), ('TQIRYSVPEELEKG', 2411, nan, True, 'Matched'), ('FAQPEYRASVPENLALG', 2387, nan, False, 'Matched'), ('AQPEYRASVPENLAL', 2405, nan, True, 'Matched'), ('SEPLLLSGDSVFSK', 2373, nan, True, 'Matched'), ('VMVLDANDNAPAFAQPEYR', 2343, nan, True, 'Matched'), ('VMVLDANDNAPAFAQPEYR', 2340, nan, True, 'Matched'), ('VDGVQAFLQTYSHEVSLTTDSR', 2421, nan, True, 'Matched'), ('AQPEYRASVPENLALG', 2310, nan, False, 'Matched'), ('FAQPEYRASVPENLALG', 2389, nan, False, 'Matched'), ('IVQNGADGSKY', 2328, nan, True, 'Matched'), ('AQPEYRASVPENLALG', 2312, nan, False, 'Matched'), ('AQPEYRASVPENLALG', 2311, nan, False, 'Matched'), ('AQPEYRASVPENLAL', 2407, nan, True, 'Matched'), ('DSHGLIEQAPPNTDWR', 2365, nan, True, 'Matched'), ('AQPEYRASVPENLALG', 2314, nan, False, 'Matched'), ('AQPEYRASVPENLALG', 2313, nan, False, 'Matched'), ('VMVLDANDNAPAFAQPEYR', 2344, nan, True, 'Matched'), ('AQPEYRASVPENLALG', 2315, nan, False, 'Matched'), ('AQPEYRASVPENLALG', 2317, nan, False, 'Matched'), ('YALSSFDYEQFRDLQVK', 2362, nan, False, 'Matched'), ('AQPEYRASVPENLAL', 2408, nan, True, 'Matched'), ('AQPEYRASVPENLALG', 2319, nan, False, 'Matched'), ('FAQPEYRASVPENLALG', 2388, nan, False, 'Matched'), ('AQPEYRASVPENLAL', 2406, nan, True, 'Matched'), ('AQPEYRASVPENLALG', 2316, nan, False, 'Matched'), ('FAQPEYRASVPENLALG', 2385, nan, False, 'Matched'), ('FAQPEYRASVPENLALG', 2386, nan, False, 'Matched')] | I2: 19 | J2: =IFERROR(VLOOKUP(A2,dbg_proteins!$A$2:$A$20161,1,FALSE)," ---") -> O60330
A3: Q15413 | B3: 11 | C3: [('QFIFDVVNEGGEQEK', 15578, 'non_standard_modification', True, 'Missed'), ('LLENSSVGLASPSMR', 15585, 'lost_3_aa_Nterm', True, 'Missed'), ('TVQEEEQLKADGK', 15569, 'non_standard_modification', True, 'Missed'), ('QFIFDVVNEGGEQEK', 15579, 'non_standard_modification', True, 'Missed'), ('ISENPALDLPSQGYK', 15564, 'non_standard_modification', True, 'Missed'), ('HGPEVGLGDLSEIIGKDEPPTLESTVQK', 15577, 'non_standard_modification', True, 'Missed'), ('RQFIFDVVNEGGEQEK', 15568, 'non_standard_modification', False, 'Missed'), ('HGPEVGLGDLSEIIGKDEPPTLESTVQK', 15576, 'non_standard_modification', True, 'Missed'), ('QFIFDVVNEGGEQEK', 15580, 'non_standard_modification', True, 'Missed'), ('AEGGEGGEDEIQFLR', 15571, 'regular_tryptic', True, 'Missed'), ('AEGGEGGEDEIQFLR', 15570, 'regular_tryptic', True, 'Missed')] | D3: 6 | E3: 14 | F3: [('ISAAVFHLEQVEQPLR', 15563, nan, True, 'Matched'), ('AEGGEGGEDEIQFLR', 15573, nan, True, 'Matched'), ('LNVYNSVAHFAGIAR', 15586, nan, True, 'Matched'), ('AEVMEPGITTELVHFIK', 15574, nan, True, 'Matched'), ('VEKPEAFTANFFK', 15589, nan, True, 'Matched'), ('AFFENAAEDLEK', 15562, nan, True, 'Matched'), ('ILGDMPDPTQFGIHDDTMEAER', 15584, nan, True, 'Matched'), ('DHPHIEVMR', 15575, nan, True, 'Matched'), ('DLYAFYPMLIR', 15581, nan, True, 'Matched'), ('FLQLLCEGHNSDFQNFLR', 15582, nan, True, 'Matched'), ('QILLLIDPSVFGEHSAGTEEGAEKEEVTQVEEK', 15588, nan, True, 'Matched'), ('GDTDIMSDLFGLHPK', 15565, nan, True, 'Matched'), ('FYTMCGLQEGFEPFAVNMNR', 15583, nan, True, 'Matched'), ('YVDSAQEFIAHLEAIVSSGK', 15590, nan, True, 'Matched')] | G3: 14 | H3: [('QFIFDVVNEGGEQEK', 15578, 'non_standard_modification', True, 'Missed'), ('LLENSSVGLASPSMR', 15585, 'lost_3_aa_Nterm', True, 'Missed'), ('TVQEEEQLKADGK', 15569, 'non_standard_modification', True, 'Missed'), ('QFIFDVVNEGGEQEK', 15579, 'non_standard_modification', True, 'Missed'), ('ISENPALDLPSQGYK', 15564, 'non_standard_modification', True, 'Missed'), ('HGPEVGLGDLSEIIGKDEPPTLESTVQK', 15577, 'non_standard_modification', True, 'Missed'), ('RQFIFDVVNEGGEQEK', 15568, 'non_standard_modification', False, 'Missed'), ('HGPEVGLGDLSEIIGKDEPPTLESTVQK', 15576, 'non_standard_modification', True, 'Missed'), ('QFIFDVVNEGGEQEK', 15580, 'non_standard_modification', True, 'Missed'), ('AEGGEGGEDEIQFLR', 15571, 'regular_tryptic', True, 'Missed'), ('AEGGEGGEDEIQFLR', 15570, 'regular_tryptic', True, 'Missed'), ('ISAAVFHLEQVEQPLR', 15563, nan, True, 'Matched'), ('AEGGEGGEDEIQFLR', 15573, nan, True, 'Matched'), ('LNVYNSVAHFAGIAR', 15586, nan, True, 'Matched'), ('AEVMEPGITTELVHFIK', 15574, nan, True, 'Matched'), ('VEKPEAFTANFFK', 15589, nan, True, 'Matched'), ('AFFENAAEDLEK', 15562, nan, True, 'Matched'), ('ILGDMPDPTQFGIHDDTMEAER', 15584, nan, True, 'Matched'), ('DHPHIEVMR', 15575, nan, True, 'Matched'), ('DLYAFYPMLIR', 15581, nan, True, 'Matched'), ('FLQLLCEGHNSDFQNFLR', 15582, nan, True, 'Matched'), ('QILLLIDPSVFGEHSAGTEEGAEKEEVTQVEEK', 15588, nan, True, 'Matched'), ('GDTDIMSDLFGLHPK', 15565, nan, True, 'Matched'), ('FYTMCGLQEGFEPFAVNMNR', 15583, nan, True, 'Matched'), ('YVDSAQEFIAHLEAIVSSGK', 15590, nan, True, 'Matched')] | I3: 19 | J3: =IFERROR(VLOOKUP(A3,dbg_proteins!$A$2:$A$20161,1,FALSE)," ---") -> Q15413
A4: Q9BYT1 | B4: 30 | C4: [('RSSMPICTV', 21941, 'non_standard_modification', True, 'Missed'), ('RSSMPICTV', 21942, 'non_standard_modification', True, 'Missed'), ('TFNHSGISV', 21622, 'HLA1', True, 'Missed'), ('LSDHLINQGY', 21735, 'IDENTIFIED', True, 'Missed'), ('VYFPALTSL', 21758, 'IDENTIFIED', True, 'Missed'), ('VYFPALTSL', 21739, 'IDENTIFIED', True, 'Missed'), ('LSDHLINQGY', 21721, 'IDENTIFIED', True, 'Missed'), ('LSDHLINQGY', 21737, 'IDENTIFIED', True, 'Missed'), ('KVRESERAF', 21963, 'IDENTIFIED', True, 'Missed'), ('TPLLAHLSSAHLAF', 21966, 'IDENTIFIED', False, 'Missed'), ('VYFPALTSL', 21793, 'IDENTIFIED', True, 'Missed'), ('FPALTSLLSQKVR', 21974, 'lost_3_aa_Nterm', True, 'Missed'), ('TPLLAHLSSAHLA', 21816, 'IDENTIFIED', True, 'Missed'), ('VTPLLAHLSSAHLA', 21898, 'IDENTIFIED', False, 'Missed'), ('YLLSEKDLILA', 21922, 'HLA1', True, 'Missed'), ('LSDHLINQGY', 21700, 'IDENTIFIED', True, 'Missed'), ('YLLSEKDLILA', 21921, 'HLA1', True, 'Missed'), ('VTPLLAHLSSAHLA', 21892, 'IDENTIFIED', False, 'Missed'), ('FRKPAVWAA', 21905, 'IDENTIFIED', True, 'Missed'), ('LSDHLINQGY', 21678, 'IDENTIFIED', True, 'Missed'), ('YLLSEKDLILA', 21924, 'HLA1', True, 'Missed'), ('VTPLLAHLSSAHLAF', 21975, 'HLA2', False, 'Missed'), ('TPLLAHLSSAHLAF', 21968, 'IDENTIFIED', False, 'Missed'), ('YLLSEKDLILA', 21925, 'HLA1', True, 'Missed'), ('KPAVWAAVVSQLSAA', 21947, 'IDENTIFIED', True, 'Missed'), ('YLLSEKDLILA', 21923, 'HLA1', True, 'Missed'), ('YLLSEKDLILA', 21929, 'HLA1', True, 'Missed'), ('YLLSEKDLILA', 21926, 'HLA1', True, 'Missed'), ('YLLSEKDLILA', 21927, 'HLA1', True, 'Missed'), ('YLLSEKDLILA', 21928, 'HLA1', True, 'Missed')] | D4: 10 | E4: 361 | F4: [('TPLLAHLSSAHLA', 21811, nan, True, 'Matched'), ('LSDHLINQGY', 21679, nan, True, 'Matched'), ('TPLLAHLSSAHLA', 21812, nan, True, 'Matched'), ('LSDHLINQGY', 21686, nan, True, 'Matched'), ('LSDHLINQGY', 21684, nan, True, 'Matched'), ('VYFPALTSL', 21770, nan, True, 'Matched'), ('TPLLAHLSSAHLA', 21806, nan, True, 'Matched'), ('LSDHLINQGY', 21706, nan, True, 'Matched'), ('LSDHLINQGY', 21705, nan, True, 'Matched'), ('VDLSSTHEDL', 21951, nan, True, 'Matched'), ('VYFPALTSL', 21771, nan, True, 'Matched'), ('TYSIVGAGSQF', 21933, nan, True, 'Matched'), ('FPALTSLLSQKVRESE', 21838, nan, True, 'Matched'), ('TPLLAHLSSAHLA', 21804, nan, True, 'Matched'), ('VYFPALTSL', 21762, nan, True, 'Matched'), ('FPALTSLLSQKVRESE', 21827, nan, True, 'Matched'), ('TPLLAHLSSAHLA', 21799, nan, True, 'Matched'), ('TPLLAHLSSAHLA', 21805, nan, True, 'Matched'), ('TPLLAHLSSAHLA', 21809, nan, True, 'Matched'), ('MSQDFGWNK', 21953, nan, True, 'Matched'), ('SAHLAFMTF', 21863, nan, True, 'Matched'), ('TYSIVGAGSQF', 21934, nan, True, 'Matched'), ('TYSIVGAGSQF', 21931, nan, True, 'Matched'), ('TYSIVGAGSQF', 21930, nan, True, 'Matched'), ('VYFPALTSL', 21763, nan, True, 'Matched'), ('FPALTSLLSQKVRESE', 21829, nan, True, 'Matched'), ('FPALTSLLSQKVRESE', 21826, nan, True, 'Matched'), ('LSDHLINQGY', 21712, nan, True, 'Matched'), ('LSDHLINQGY', 21711, nan, True, 'Matched'), ('SAHLAFMTF', 21849, nan, True, 'Matched'), ('FPALTSLLSQKVRESE', 21835, nan, True, 'Matched'), ('FPALTSLLSQKVRESE', 21833, nan, True, 'Matched'), ('VYFPALTSL', 21764, nan, True, 'Matched'), ('LSDHLINQGY', 21708, nan, True, 'Matched'), ('LSDHLINQGY', 21707, nan, True, 'Matched'), ('TPLLAHLSSAHLA', 21808, nan, True, 'Matched'), ('FPALTSLLSQKVRESE', 21840, nan, True, 'Matched'), ('VYFPALTSL', 21772, nan, True, 'Matched'), ('TPLLAHLSSAHLA', 21800, nan, True, 'Matched'), ('SAHLAFMTF', 21851, nan, True, 'Matched'), ('NHSGISVNI', 21871, nan, True, 'Matched'), ('TPLLAHLSSAHLA', 21810, nan, True, 'Matched'), ('TYSIVGAGSQF', 21935, nan, True, 'Matched'), ('FPALTSLLSQKVRESE', 21831, nan, True, 'Matched'), ('LSDHLINQGY', 21704, nan, True, 'Matched'), ('LSDHLINQGY', 21703, nan, True, 'Matched'), ('TPLLAHLSSAHLA', 21802, nan, True, 'Matched'), ('LSDHLINQGY', 21691, nan, True, 'Matched'), ('VYFPALTSL', 21761, nan, True, 'Matched'), ('SAHLAFMTF', 21853, nan, True, 'Matched'), ('FPALTSLLSQKVRESE', 21832, nan, True, 'Matched'), ('VYFPALTSL', 21765, nan, True, 'Matched'), ('VYFPALTSL', 21760, nan, True, 'Matched'), ('VYFPALTSL', 21759, nan, True, 'Matched'), ('SAHLAFMTF', 21850, nan, True, 'Matched'), ('FPALTSLLSQKVRESE', 21836, nan, True, 'Matched'), ('SAHLAFMTF', 21852, nan, True, 'Matched'), ('VYFPALTSL', 21766, nan, True, 'Matched'), ('FPALTSLLSQKVRESE', 21848, nan, True, 'Matched'), ('LSDHLINQGY', 21710, nan, True, 'Matched'), ('LSDHLINQGY', 21709, nan, True, 'Matched'), ('NHSGISVNI', 21877, nan, True, 'Matched'), ('NHSGISVNI', 21874, nan, True, 'Matched'), ('NHSGISVNI', 21876, nan, True, 'Matched'), ('NHSGISVNI', 21885, nan, True, 'Matched'), ('TPLLAHLSSAHLA', 21801, nan, True, 'Matched'), ('VYFPALTSL', 21767, nan, True, 'Matched'), ('VYFPALTSL', 21769, nan, True, 'Matched'), ('NHSGISVNI', 21880, nan, True, 'Matched'), ('NHSGISVNI', 21879, nan, True, 'Matched'), ('FPALTSLLSQKVRESE', 21834, nan, True, 'Matched'), ('TYSIVGAGSQF', 21932, nan, True, 'Matched'), ('SAHLAFMTF', 21854, nan, True, 'Matched'), ('VYFPALTSL', 21777, nan, True, 'Matched'), ('NHSGISVNI', 21881, nan, True, 'Matched'), ('NHSGISVNI', 21887, nan, True, 'Matched'), ('VYFPALTSL', 21773, nan, True, 'Matched'), ('FPALTSLLSQKVRESE', 21825, nan, True, 'Matched'), ('MSQDFGWNK', 21955, nan, True, 'Matched'), ('YFPALTSLLSQKVRESE', 21972, nan, False, 'Matched'), ('SAHLAFMTF', 21855, nan, True, 'Matched'), ('NHSGISVNI', 21882, nan, True, 'Matched'), ('MSQDFGWNK', 21956, nan, True, 'Matched'), ('SAHLAFMTF', 21856, nan, True, 'Matched'), ('TFNHSGISV', 21675, nan, True, 'Matched'), ('VYFPALTSL', 21775, nan, True, 'Matched'), ('NHSGISVNI', 21875, nan, True, 'Matched'), ('LSDHLINQGY', 21702, nan, True, 'Matched'), ('LSDHLINQGY', 21701, nan, True, 'Matched'), ('NHSGISVNI', 21886, nan, True, 'Matched'), ('TFNHSGISV', 21586, nan, True, 'Matched'), ('NHSGISVNI', 21888, nan, True, 'Matched'), ('SAHLAFMTF', 21861, nan, True, 'Matched'), ('TFNHSGISV', 21674, nan, True, 'Matched'), ('NHSGISVNI', 21883, nan, True, 'Matched'), ('SAHLAFMTF', 21862, nan, True, 'Matched'), ('SLFSGFLSDHLINQGYR', 21971, nan, False, 'Matched'), ('SAHLAFMTF', 21869, nan, True, 'Matched'), ('LSDHLINQGY', 21713, nan, True, 'Matched'), ('TFNHSGISV', 21595, nan, True, 'Matched'), ('NHSGISVNI', 21872, nan, True, 'Matched'), ('LSDHLINQGY', 21689, nan, True, 'Matched'), ('TFNHSGISV', 21611, nan, True, 'Matched'), ('VYFPALTSL', 21776, nan, True, 'Matched'), ('TPLLAHLSSAHLA', 21813, nan, True, 'Matched'), ('FPALTSLLSQKVRESE', 21846, nan, True, 'Matched'), ('LSDHLINQGY', 21725, nan, True, 'Matched'), ('SAHLAFMTF', 21868, nan, True, 'Matched'), ('SAHLAFMTF', 21866, nan, True, 'Matched'), ('TFNHSGISV', 21663, nan, True, 'Matched'), ('TFNHSGISV', 21642, nan, True, 'Matched'), ('ITAVTPLLAHLSSAH', 21969, nan, True, 'Matched'), ('VYFPALTSL', 21768, nan, True, 'Matched'), ('TFNHSGISV', 21672, nan, True, 'Matched'), ('FPALTSLLSQKVRESE', 21828, nan, True, 'Matched'), ('FPALTSLLSQKVRESE', 21841, nan, True, 'Matched'), ('TFNHSGISV', 21592, nan, True, 'Matched'), ('TFNHSGISV', 21598, nan, True, 'Matched'), ('TFNHSGISV', 21645, nan, True, 'Matched'), ('NHSGISVNI', 21873, nan, True, 'Matched'), ('TFNHSGISV', 21603, nan, True, 'Matched'), ('YFPALTSLLSQKVRESE', 21973, nan, False, 'Matched'), ('SAHLAFMTF', 21858, nan, True, 'Matched'), ('TFNHSGISV', 21617, nan, True, 'Matched'), ('SAHLAFMTF', 21859, nan, True, 'Matched'), ('TFNHSGISV', 21606, nan, True, 'Matched'), ('TYSIVGAGSQF', 21936, nan, True, 'Matched'), ('LSDHLINQGY', 21688, nan, True, 'Matched'), ('LSDHLINQGY', 21738, nan, True, 'Matched'), ('TFNHSGISV', 21671, nan, True, 'Matched'), ('TFNHSGISV', 21659, nan, True, 'Matched'), ('TFNHSGISV', 21585, nan, True, 'Matched'), ('TFNHSGISV', 21667, nan, True, 'Matched'), ('TFNHSGISV', 21643, nan, True, 'Matched'), ('TPLLAHLSSAHLA', 21807, nan, True, 'Matched'), ('TFNHSGISV', 21621, nan, True, 'Matched'), ('TFNHSGISV', 21616, nan, True, 'Matched'), ('TFNHSGISV', 21624, nan, True, 'Matched'), ('LSDHLINQGY', 21685, nan, True, 'Matched'), ('TFNHSGISV', 21591, nan, True, 'Matched'), ('TFNHSGISV', 21656, nan, True, 'Matched'), ('TPLLAHLSSAHLA', 21803, nan, True, 'Matched'), ('TFNHSGISV', 21618, nan, True, 'Matched'), ('HLSSAHLAF', 21912, nan, True, 'Matched'), ('TFNHSGISV', 21669, nan, True, 'Matched'), ('TFNHSGISV', 21590, nan, True, 'Matched'), ('TFNHSGISV', 21604, nan, True, 'Matched'), ('TFNHSGISV', 21650, nan, True, 'Matched'), ('TFNHSGISV', 21589, nan, True, 'Matched'), ('TFNHSGISV', 21649, nan, True, 'Matched'), ('TFNHSGISV', 21605, nan, True, 'Matched'), ('TFNHSGISV', 21583, nan, True, 'Matched'), ('TFNHSGISV', 21600, nan, True, 'Matched'), ('NHSGISVNI', 21884, nan, True, 'Matched'), ('TFNHSGISV', 21596, nan, True, 'Matched'), ('TFNHSGISV', 21638, nan, True, 'Matched'), ('TFNHSGISV', 21612, nan, True, 'Matched'), ('ITAVTPLLAHLSSAH', 21970, nan, True, 'Matched'), ('TFNHSGISV', 21601, nan, True, 'Matched'), ('TFNHSGISV', 21593, nan, True, 'Matched'), ('TFNHSGISV', 21660, nan, True, 'Matched'), ('FPDAKGWIF', 21960, nan, True, 'Matched'), ('TFNHSGISV', 21628, nan, True, 'Matched'), ('TFNHSGISV', 21608, nan, True, 'Matched'), ('TFNHSGISV', 21673, nan, True, 'Matched'), ('TFNHSGISV', 21602, nan, True, 'Matched'), ('TFNHSGISV', 21623, nan, True, 'Matched'), ('TFNHSGISV', 21633, nan, True, 'Matched'), ('TFNHSGISV', 21635, nan, True, 'Matched'), ('NHSGISVNI', 21889, nan, True, 'Matched'), ('TFNHSGISV', 21629, nan, True, 'Matched'), ('TFNHSGISV', 21614, nan, True, 'Matched'), ('SAHLAFMTF', 21864, nan, True, 'Matched'), ('HLSSAHLAF', 21918, nan, True, 'Matched'), ('TFNHSGISV', 21652, nan, True, 'Matched'), ('TFNHSGISV', 21607, nan, True, 'Matched'), ('TFNHSGISV', 21626, nan, True, 'Matched'), ('TFNHSGISV', 21655, nan, True, 'Matched'), ('TFNHSGISV', 21637, nan, True, 'Matched'), ('TFNHSGISV', 21619, nan, True, 'Matched'), ('TFNHSGISV', 21588, nan, True, 'Matched'), ('LSDHLINQGY', 21714, nan, True, 'Matched'), ('TPLLAHLSSAHLA', 21818, nan, True, 'Matched'), ('TFNHSGISV', 21658, nan, True, 'Matched'), ('TFNHSGISV', 21631, nan, True, 'Matched'), ('HLSSAHLAF', 21919, nan, True, 'Matched'), ('TFNHSGISV', 21653, nan, True, 'Matched'), ('TFNHSGISV', 21640, nan, True, 'Matched'), ('HLSSAHLAF', 21920, nan, True, 'Matched'), ('TFNHSGISV', 21647, nan, True, 'Matched'), ('TFNHSGISV', 21634, nan, True, 'Matched'), ('VYFPALTSL', 21774, nan, True, 'Matched'), ('TFNHSGISV', 21582, nan, True, 'Matched'), ('LSDHLINQGY', 21726, nan, True, 'Matched'), ('TFNHSGISV', 21627, nan, True, 'Matched'), ('SAHLAFMTF', 21857, nan, True, 'Matched'), ('TFNHSGISV', 21632, nan, True, 'Matched'), ('FPALTSLLSQKVRESE', 21847, nan, True, 'Matched'), ('TFNHSGISV', 21662, nan, True, 'Matched'), ('HLSSAHLAF', 21917, nan, True, 'Matched'), ('TFNHSGISV', 21597, nan, True, 'Matched'), ('HLSSAHLAF', 21914, nan, True, 'Matched'), ('TFNHSGISV', 21630, nan, True, 'Matched'), ('HLSSAHLAF', 21916, nan, True, 'Matched'), ('TFNHSGISV', 21609, nan, True, 'Matched'), ('TFNHSGISV', 21654, nan, True, 'Matched'), ('TFNHSGISV', 21594, nan, True, 'Matched'), ('TFNHSGISV', 21615, nan, True, 'Matched'), ('TFNHSGISV', 21664, nan, True, 'Matched'), ('TFNHSGISV', 21584, nan, True, 'Matched'), ('TFNHSGISV', 21599, nan, True, 'Matched'), ('LSDHLINQGY', 21728, nan, True, 'Matched'), ('TPLLAHLSSAHLA', 21820, nan, True, 'Matched'), ('FPDAKGWIF', 21961, nan, True, 'Matched'), ('TFNHSGISV', 21651, nan, True, 'Matched'), ('LSDHLINQGY', 21681, nan, True, 'Matched'), ('FPALTSLLSQKVRESE', 21839, nan, True, 'Matched'), ('TFNHSGISV', 21620, nan, True, 'Matched'), ('TFNHSGISV', 21610, nan, True, 'Matched'), ('TFNHSGISV', 21587, nan, True, 'Matched'), ('TFNHSGISV', 21670, nan, True, 'Matched'), ('SAHLAFMTF', 21870, nan, True, 'Matched'), ('HLSSAHLAF', 21913, nan, True, 'Matched'), ('TFNHSGISV', 21613, nan, True, 'Matched'), ('TPLLAHLSSAHLA', 21821, nan, True, 'Matched'), ('NHSGISVNI', 21878, nan, True, 'Matched'), ('FPALTSLLSQKVRESE', 21843, nan, True, 'Matched'), ('TFNHSGISV', 21636, nan, True, 'Matched'), ('LSDHLINQGY', 21694, nan, True, 'Matched'), ('LSDHLINQGY', 21693, nan, True, 'Matched'), ('LSDHLINQGY', 21729, nan, True, 'Matched'), ('LSDHLINQGY', 21718, nan, True, 'Matched'), ('LSDHLINQGY', 21683, nan, True, 'Matched'), ('LSDHLINQGY', 21722, nan, True, 'Matched'), ('LSDHLINQGY', 21724, nan, True, 'Matched'), ('FPALTSLLSQKVRESE', 21837, nan, True, 'Matched'), ('LSDHLINQGY', 21687, nan, True, 'Matched'), ('LSDHLINQGY', 21720, nan, True, 'Matched'), ('HLSSAHLAF', 21915, nan, True, 'Matched'), ('LSDHLINQGY', 21692, nan, True, 'Matched'), ('TFNHSGISV', 21661, nan, True, 'Matched'), ('LSDHLINQGY', 21723, nan, True, 'Matched'), ('TFNHSGISV', 21668, nan, True, 'Matched'), ('VDLSSTHEDL', 21949, nan, True, 'Matched'), ('TFNHSGISV', 21644, nan, True, 'Matched'), ('FPDAKGWIF', 21962, nan, True, 'Matched'), ('TFNHSGISV', 21639, nan, True, 'Matched'), ('LSDHLINQGY', 21696, nan, True, 'Matched'), ('LSDHLINQGY', 21695, nan, True, 'Matched'), ('VDLSSTHEDL', 21948, nan, True, 'Matched'), ('TFNHSGISV', 21666, nan, True, 'Matched'), ('TFNHSGISV', 21665, nan, True, 'Matched'), ('LSDHLINQGY', 21719, nan, True, 'Matched'), ('VTPLLAHLSSAHLA', 21899, nan, False, 'Matched'), ('SAHLAFMTF', 21865, nan, True, 'Matched'), ('TFNHSGISV', 21641, nan, True, 'Matched'), ('VTPLLAHLSSAHLA', 21895, nan, False, 'Matched'), ('TFNHSGISV', 21648, nan, True, 'Matched'), ('ETFPDAKGWIF', 21958, nan, False, 'Matched'), ('TPLLAHLSSAHLA', 21822, nan, True, 'Matched'), ('LSDHLINQGY', 21682, nan, True, 'Matched'), ('SAHLAFMTF', 21860, nan, True, 'Matched'), ('FPALTSLLSQKVRESE', 21842, nan, True, 'Matched'), ('LSDHLINQGY', 21730, nan, True, 'Matched'), ('LSDHLINQGY', 21717, nan, True, 'Matched'), ('VYFPALTSL', 21755, nan, True, 'Matched'), ('FPALTSLLSQKVRESE', 21844, nan, True, 'Matched'), ('TFNHSGISV', 21646, nan, True, 'Matched'), ('RSSMPICTV', 21940, nan, True, 'Matched'), ('TPLLAHLSSAHLA', 21823, nan, True, 'Matched'), ('ETFPDAKGWIF', 21959, nan, False, 'Matched'), ('LSDHLINQGY', 21732, nan, True, 'Matched'), ('RSSMPICTV', 21938, nan, True, 'Matched'), ('LSDHLINQGY', 21733, nan, True, 'Matched'), ('TFNHSGISV', 21657, nan, True, 'Matched'), ('VYFPALTSL', 21742, nan, True, 'Matched'), ('LSDHLINQGY', 21716, nan, True, 'Matched'), ('ETFPDAKGWIF', 21957, nan, False, 'Matched'), ('VTPLLAHLSSAHLA', 21896, nan, False, 'Matched'), ('TPLLAHLSSAHLA', 21814, nan, True, 'Matched'), ('VYFPALTSL', 21741, nan, True, 'Matched'), ('SAHLAFMTF', 21867, nan, True, 'Matched'), ('LSDHLINQGY', 21677, nan, True, 'Matched'), ('TPLLAHLSSAHLA', 21815, nan, True, 'Matched'), ('LSDHLINQGY', 21715, nan, True, 'Matched'), ('FPALTSLLSQKVRESE', 21845, nan, True, 'Matched'), ('LSDHLINQGY', 21734, nan, True, 'Matched'), ('LSDHLINQGY', 21680, nan, True, 'Matched'), ('VYFPALTSL', 21751, nan, True, 'Matched'), ('VYFPALTSL', 21780, nan, True, 'Matched'), ('RSSMPICTV', 21939, nan, True, 'Matched'), ('LSDHLINQGY', 21727, nan, True, 'Matched'), ('VYFPALTSL', 21740, nan, True, 'Matched'), ('VYFPALTSL', 21786, nan, True, 'Matched'), ('LSDHLINQGY', 21697, nan, True, 'Matched'), ('VYFPALTSL', 21798, nan, True, 'Matched'), ('VYFPALTSL', 21797, nan, True, 'Matched'), ('LSDHLINQGY', 21699, nan, True, 'Matched'), ('LSDHLINQGY', 21698, nan, True, 'Matched'), ('LSDHLINQGY', 21690, nan, True, 'Matched'), ('VYFPALTSL', 21790, nan, True, 'Matched'), ('VTPLLAHLSSAHLA', 21890, nan, False, 'Matched'), ('VDLSSTHEDL', 21952, nan, True, 'Matched'), ('LSDHLINQGY', 21736, nan, True, 'Matched'), ('VYFPALTSL', 21746, nan, True, 'Matched'), ('VYFPALTSL', 21782, nan, True, 'Matched'), ('VYFPALTSL', 21788, nan, True, 'Matched'), ('VYFPALTSL', 21783, nan, True, 'Matched'), ('VYFPALTSL', 21743, nan, True, 'Matched'), ('VYFPALTSL', 21749, nan, True, 'Matched'), ('TFNHSGISV', 21625, nan, True, 'Matched'), ('VTPLLAHLSSAHLA', 21894, nan, False, 'Matched'), ('VYFPALTSL', 21781, nan, True, 'Matched'), ('VYFPALTSL', 21753, nan, True, 'Matched'), ('VYFPALTSL', 21784, nan, True, 'Matched'), ('LSDHLINQGY', 21731, nan, True, 'Matched'), ('VYFPALTSL', 21748, nan, True, 'Matched'), ('VYFPALTSL', 21787, nan, True, 'Matched'), ('VYFPALTSL', 21791, nan, True, 'Matched'), ('VYFPALTSL', 21747, nan, True, 'Matched'), ('VYFPALTSL', 21792, nan, True, 'Matched'), ('VYFPALTSL', 21789, nan, True, 'Matched'), ('VYFPALTSL', 21778, nan, True, 'Matched'), ('VYFPALTSL', 21757, nan, True, 'Matched'), ('VYFPALTSL', 21779, nan, True, 'Matched'), ('VYFPALTSL', 21794, nan, True, 'Matched'), ('TPLLAHLSSAHLA', 21819, nan, True, 'Matched'), ('VYFPALTSL', 21750, nan, True, 'Matched'), ('VYFPALTSL', 21795, nan, True, 'Matched'), ('VYFPALTSL', 21745, nan, True, 'Matched'), ('KVRESERAF', 21964, nan, True, 'Matched'), ('VYFPALTSL', 21752, nan, True, 'Matched'), ('VYFPALTSL', 21785, nan, True, 'Matched'), ('FPALTSLLSQKVRESE', 21830, nan, True, 'Matched'), ('KVRESERAF', 21965, nan, True, 'Matched'), ('TPLLAHLSSAHLA', 21817, nan, True, 'Matched'), ('VYFPALTSL', 21754, nan, True, 'Matched'), ('LSDHLINQGY', 21676, nan, True, 'Matched'), ('RSSMPICTV', 21937, nan, True, 'Matched'), ('VYFPALTSL', 21796, nan, True, 'Matched'), ('VYFPALTSL', 21756, nan, True, 'Matched'), ('VTPLLAHLSSAHLA', 21893, nan, False, 'Matched'), ('FRKPAVWAA', 21906, nan, True, 'Matched'), ('VYFPALTSL', 21744, nan, True, 'Matched'), ('TPLLAHLSSAHLA', 21824, nan, True, 'Matched'), ('KPAVWAAVVSQLSAA', 21946, nan, True, 'Matched'), ('KPAVWAAVVSQLSAA', 21944, nan, True, 'Matched'), ('KPAVWAAVVSQLSAA', 21945, nan, True, 'Matched'), ('KPAVWAAVVSQLSAA', 21943, nan, True, 'Matched'), ('VTPLLAHLSSAHLA', 21900, nan, False, 'Matched'), ('VTPLLAHLSSAHLA', 21891, nan, False, 'Matched'), ('FRKPAVWAA', 21904, nan, True, 'Matched'), ('FRKPAVWAA', 21908, nan, True, 'Matched'), ('VTPLLAHLSSAHLA', 21897, nan, False, 'Matched'), ('FRKPAVWAA', 21909, nan, True, 'Matched'), ('FRKPAVWAA', 21902, nan, True, 'Matched'), ('FRKPAVWAA', 21901, nan, True, 'Matched'), ('FRKPAVWAA', 21907, nan, True, 'Matched'), ('TPLLAHLSSAHLAF', 21967, nan, False, 'Matched'), ('FRKPAVWAA', 21903, nan, True, 'Matched'), ('FRKPAVWAA', 21910, nan, True, 'Matched')] | G4: 17 | H4: [('RSSMPICTV', 21941, 'non_standard_modification', True, 'Missed'), ('RSSMPICTV', 21942, 'non_standard_modification', True, 'Missed'), ('TFNHSGISV', 21622, 'HLA1', True, 'Missed'), ('LSDHLINQGY', 21735, 'IDENTIFIED', True, 'Missed'), ('VYFPALTSL', 21758, 'IDENTIFIED', True, 'Missed'), ('VYFPALTSL', 21739, 'IDENTIFIED', True, 'Missed'), ('LSDHLINQGY', 21721, 'IDENTIFIED', True, 'Missed'), ('LSDHLINQGY', 21737, 'IDENTIFIED', True, 'Missed'), ('KVRESERAF', 21963, 'IDENTIFIED', True, 'Missed'), ('TPLLAHLSSAHLAF', 21966, 'IDENTIFIED', False, 'Missed'), ('VYFPALTSL', 21793, 'IDENTIFIED', True, 'Missed'), ('FPALTSLLSQKVR', 21974, 'lost_3_aa_Nterm', True, 'Missed'), ('TPLLAHLSSAHLA', 21816, 'IDENTIFIED', True, 'Missed'), ('VTPLLAHLSSAHLA', 21898, 'IDENTIFIED', False, 'Missed'), ('YLLSEKDLILA', 21922, 'HLA1', True, 'Missed'), ('LSDHLINQGY', 21700, 'IDENTIFIED', True, 'Missed'), ('YLLSEKDLILA', 21921, 'HLA1', True, 'Missed'), ('VTPLLAHLSSAHLA', 21892, 'IDENTIFIED', False, 'Missed'), ('FRKPAVWAA', 21905, 'IDENTIFIED', True, 'Missed'), ('LSDHLINQGY', 21678, 'IDENTIFIED', True, 'Missed'), ('YLLSEKDLILA', 21924, 'HLA1', True, 'Missed'), ('VTPLLAHLSSAHLAF', 21975, 'HLA2', False, 'Missed'), ('TPLLAHLSSAHLAF', 21968, 'IDENTIFIED', False, 'Missed'), ('YLLSEKDLILA', 21925, 'HLA1', True, 'Missed'), ('KPAVWAAVVSQLSAA', 21947, 'IDENTIFIED', True, 'Missed'), ('YLLSEKDLILA', 21923, 'HLA1', True, 'Missed'), ('YLLSEKDLILA', 21929, 'HLA1', True, 'Missed'), ('YLLSEKDLILA', 21926, 'HLA1', True, 'Missed'), ('YLLSEKDLILA', 21927, 'HLA1', True, 'Missed'), ('YLLSEKDLILA', 21928, 'HLA1', True, 'Missed'), ('TPLLAHLSSAHLA', 21811, nan, True, 'Matched'), ('LSDHLINQGY', 21679, nan, True, 'Matched'), ('TPLLAHLSSAHLA', 21812, nan, True, 'Matched'), ('LSDHLINQGY', 21686, nan, True, 'Matched'), ('LSDHLINQGY', 21684, nan, True, 'Matched'), ('VYFPALTSL', 21770, nan, True, 'Matched'), ('TPLLAHLSSAHLA', 21806, nan, True, 'Matched'), ('LSDHLINQGY', 21706, nan, True, 'Matched'), ('LSDHLINQGY', 21705, nan, True, 'Matched'), ('VDLSSTHEDL', 21951, nan, True, 'Matched'), ('VYFPALTSL', 21771, nan, True, 'Matched'), ('TYSIVGAGSQF', 21933, nan, True, 'Matched'), ('FPALTSLLSQKVRESE', 21838, nan, False, 'Matched'), ('TPLLAHLSSAHLA', 21804, nan, True, 'Matched'), ('VYFPALTSL', 21762, nan, True, 'Matched'), ('FPALTSLLSQKVRESE', 21827, nan, False, 'Matched'), ('TPLLAHLSSAHLA', 21799, nan, True, 'Matched'), ('TPLLAHLSSAHLA', 21805, nan, True, 'Matched'), ('TPLLAHLSSAHLA', 21809, nan, True, 'Matched'), ('MSQDFGWNK', 21953, nan, True, 'Matched'), ('SAHLAFMTF', 21863, nan, True, 'Matched'), ('TYSIVGAGSQF', 21934, nan, True, 'Matched'), ('TYSIVGAGSQF', 21931, nan, True, 'Matched'), ('TYSIVGAGSQF', 21930, nan, True, 'Matched'), ('VYFPALTSL', 21763, nan, True, 'Matched'), ('FPALTSLLSQKVRESE', 21829, nan, False, 'Matched'), ('FPALTSLLSQKVRESE', 21826, nan, False, 'Matched'), ('LSDHLINQGY', 21712, nan, True, 'Matched'), ('LSDHLINQGY', 21711, nan, True, 'Matched'), ('SAHLAFMTF', 21849, nan, True, 'Matched'), ('FPALTSLLSQKVRESE', 21835, nan, False, 'Matched'), ('FPALTSLLSQKVRESE', 21833, nan, False, 'Matched'), ('VYFPALTSL', 21764, nan, True, 'Matched'), ('LSDHLINQGY', 21708, nan, True, 'Matched'), ('LSDHLINQGY', 21707, nan, True, 'Matched'), ('TPLLAHLSSAHLA', 21808, nan, True, 'Matched'), ('FPALTSLLSQKVRESE', 21840, nan, False, 'Matched'), ('VYFPALTSL', 21772, nan, True, 'Matched'), ('TPLLAHLSSAHLA', 21800, nan, True, 'Matched'), ('SAHLAFMTF', 21851, nan, True, 'Matched'), ('NHSGISVNI', 21871, nan, True, 'Matched'), ('TPLLAHLSSAHLA', 21810, nan, True, 'Matched'), ('TYSIVGAGSQF', 21935, nan, True, 'Matched'), ('FPALTSLLSQKVRESE', 21831, nan, False, 'Matched'), ('LSDHLINQGY', 21704, nan, True, 'Matched'), ('LSDHLINQGY', 21703, nan, True, 'Matched'), ('TPLLAHLSSAHLA', 21802, nan, True, 'Matched'), ('LSDHLINQGY', 21691, nan, True, 'Matched'), ('VYFPALTSL', 21761, nan, True, 'Matched'), ('SAHLAFMTF', 21853, nan, True, 'Matched'), ('FPALTSLLSQKVRESE', 21832, nan, False, 'Matched'), ('VYFPALTSL', 21765, nan, True, 'Matched'), ('VYFPALTSL', 21760, nan, True, 'Matched'), ('VYFPALTSL', 21759, nan, True, 'Matched'), ('SAHLAFMTF', 21850, nan, True, 'Matched'), ('FPALTSLLSQKVRESE', 21836, nan, False, 'Matched'), ('SAHLAFMTF', 21852, nan, True, 'Matched'), ('VYFPALTSL', 21766, nan, True, 'Matched'), ('FPALTSLLSQKVRESE', 21848, nan, False, 'Matched'), ('LSDHLINQGY', 21710, nan, True, 'Matched'), ('LSDHLINQGY', 21709, nan, True, 'Matched'), ('NHSGISVNI', 21877, nan, True, 'Matched'), ('NHSGISVNI', 21874, nan, True, 'Matched'), ('NHSGISVNI', 21876, nan, True, 'Matched'), ('NHSGISVNI', 21885, nan, True, 'Matched'), ('TPLLAHLSSAHLA', 21801, nan, True, 'Matched'), ('VYFPALTSL', 21767, nan, True, 'Matched'), ('VYFPALTSL', 21769, nan, True, 'Matched'), ('NHSGISVNI', 21880, nan, True, 'Matched'), ('NHSGISVNI', 21879, nan, True, 'Matched'), ('FPALTSLLSQKVRESE', 21834, nan, False, 'Matched'), ('TYSIVGAGSQF', 21932, nan, True, 'Matched'), ('SAHLAFMTF', 21854, nan, True, 'Matched'), ('VYFPALTSL', 21777, nan, True, 'Matched'), ('NHSGISVNI', 21881, nan, True, 'Matched'), ('NHSGISVNI', 21887, nan, True, 'Matched'), ('VYFPALTSL', 21773, nan, True, 'Matched'), ('FPALTSLLSQKVRESE', 21825, nan, False, 'Matched'), ('MSQDFGWNK', 21955, nan, True, 'Matched'), ('YFPALTSLLSQKVRESE', 21972, nan, False, 'Matched'), ('SAHLAFMTF', 21855, nan, True, 'Matched'), ('NHSGISVNI', 21882, nan, True, 'Matched'), ('MSQDFGWNK', 21956, nan, True, 'Matched'), ('SAHLAFMTF', 21856, nan, True, 'Matched'), ('TFNHSGISV', 21675, nan, True, 'Matched'), ('VYFPALTSL', 21775, nan, True, 'Matched'), ('NHSGISVNI', 21875, nan, True, 'Matched'), ('LSDHLINQGY', 21702, nan, True, 'Matched'), ('LSDHLINQGY', 21701, nan, True, 'Matched'), ('NHSGISVNI', 21886, nan, True, 'Matched'), ('TFNHSGISV', 21586, nan, True, 'Matched'), ('NHSGISVNI', 21888, nan, True, 'Matched'), ('SAHLAFMTF', 21861, nan, True, 'Matched'), ('TFNHSGISV', 21674, nan, True, 'Matched'), ('NHSGISVNI', 21883, nan, True, 'Matched'), ('SAHLAFMTF', 21862, nan, True, 'Matched'), ('SLFSGFLSDHLINQGYR', 21971, nan, False, 'Matched'), ('SAHLAFMTF', 21869, nan, True, 'Matched'), ('LSDHLINQGY', 21713, nan, True, 'Matched'), ('TFNHSGISV', 21595, nan, True, 'Matched'), ('NHSGISVNI', 21872, nan, True, 'Matched'), ('LSDHLINQGY', 21689, nan, True, 'Matched'), ('TFNHSGISV', 21611, nan, True, 'Matched'), ('VYFPALTSL', 21776, nan, True, 'Matched'), ('TPLLAHLSSAHLA', 21813, nan, True, 'Matched'), ('FPALTSLLSQKVRESE', 21846, nan, False, 'Matched'), ('LSDHLINQGY', 21725, nan, True, 'Matched'), ('SAHLAFMTF', 21868, nan, True, 'Matched'), ('SAHLAFMTF', 21866, nan, True, 'Matched'), ('TFNHSGISV', 21663, nan, True, 'Matched'), ('TFNHSGISV', 21642, nan, True, 'Matched'), ('ITAVTPLLAHLSSAH', 21969, nan, True, 'Matched'), ('VYFPALTSL', 21768, nan, True, 'Matched'), ('TFNHSGISV', 21672, nan, True, 'Matched'), ('FPALTSLLSQKVRESE', 21828, nan, False, 'Matched'), ('FPALTSLLSQKVRESE', 21841, nan, False, 'Matched'), ('TFNHSGISV', 21592, nan, True, 'Matched'), ('TFNHSGISV', 21598, nan, True, 'Matched'), ('TFNHSGISV', 21645, nan, True, 'Matched'), ('NHSGISVNI', 21873, nan, True, 'Matched'), ('TFNHSGISV', 21603, nan, True, 'Matched'), ('YFPALTSLLSQKVRESE', 21973, nan, False, 'Matched'), ('SAHLAFMTF', 21858, nan, True, 'Matched'), ('TFNHSGISV', 21617, nan, True, 'Matched'), ('SAHLAFMTF', 21859, nan, True, 'Matched'), ('TFNHSGISV', 21606, nan, True, 'Matched'), ('TYSIVGAGSQF', 21936, nan, True, 'Matched'), ('LSDHLINQGY', 21688, nan, True, 'Matched'), ('LSDHLINQGY', 21738, nan, True, 'Matched'), ('TFNHSGISV', 21671, nan, True, 'Matched'), ('TFNHSGISV', 21659, nan, True, 'Matched'), ('TFNHSGISV', 21585, nan, True, 'Matched'), ('TFNHSGISV', 21667, nan, True, 'Matched'), ('TFNHSGISV', 21643, nan, True, 'Matched'), ('TPLLAHLSSAHLA', 21807, nan, True, 'Matched'), ('TFNHSGISV', 21621, nan, True, 'Matched'), ('TFNHSGISV', 21616, nan, True, 'Matched'), ('TFNHSGISV', 21624, nan, True, 'Matched'), ('LSDHLINQGY', 21685, nan, True, 'Matched'), ('TFNHSGISV', 21591, nan, True, 'Matched'), ('TFNHSGISV', 21656, nan, True, 'Matched'), ('TPLLAHLSSAHLA', 21803, nan, True, 'Matched'), ('TFNHSGISV', 21618, nan, True, 'Matched'), ('HLSSAHLAF', 21912, nan, True, 'Matched'), ('TFNHSGISV', 21669, nan, True, 'Matched'), ('TFNHSGISV', 21590, nan, True, 'Matched'), ('TFNHSGISV', 21604, nan, True, 'Matched'), ('TFNHSGISV', 21650, nan, True, 'Matched'), ('TFNHSGISV', 21589, nan, True, 'Matched'), ('TFNHSGISV', 21649, nan, True, 'Matched'), ('TFNHSGISV', 21605, nan, True, 'Matched'), ('TFNHSGISV', 21583, nan, True, 'Matched'), ('TFNHSGISV', 21600, nan, True, 'Matched'), ('NHSGISVNI', 21884, nan, True, 'Matched'), ('TFNHSGISV', 21596, nan, True, 'Matched'), ('TFNHSGISV', 21638, nan, True, 'Matched'), ('TFNHSGISV', 21612, nan, True, 'Matched'), ('ITAVTPLLAHLSSAH', 21970, nan, True, 'Matched'), ('TFNHSGISV', 21601, nan, True, 'Matched'), ('TFNHSGISV', 21593, nan, True, 'Matched'), ('TFNHSGISV', 21660, nan, True, 'Matched'), ('FPDAKGWIF', 21960, nan, True, 'Matched'), ('TFNHSGISV', 21628, nan, True, 'Matched'), ('TFNHSGISV', 21608, nan, True, 'Matched'), ('TFNHSGISV', 21673, nan, True, 'Matched'), ('TFNHSGISV', 21602, nan, True, 'Matched'), ('TFNHSGISV', 21623, nan, True, 'Matched'), ('TFNHSGISV', 21633, nan, True, 'Matched'), ('TFNHSGISV', 21635, nan, True, 'Matched'), ('NHSGISVNI', 21889, nan, True, 'Matched'), ('TFNHSGISV', 21629, nan, True, 'Matched'), ('TFNHSGISV', 21614, nan, True, 'Matched'), ('SAHLAFMTF', 21864, nan, True, 'Matched'), ('HLSSAHLAF', 21918, nan, True, 'Matched'), ('TFNHSGISV', 21652, nan, True, 'Matched'), ('TFNHSGISV', 21607, nan, True, 'Matched'), ('TFNHSGISV', 21626, nan, True, 'Matched'), ('TFNHSGISV', 21655, nan, True, 'Matched'), ('TFNHSGISV', 21637, nan, True, 'Matched'), ('TFNHSGISV', 21619, nan, True, 'Matched'), ('TFNHSGISV', 21588, nan, True, 'Matched'), ('LSDHLINQGY', 21714, nan, True, 'Matched'), ('TPLLAHLSSAHLA', 21818, nan, True, 'Matched'), ('TFNHSGISV', 21658, nan, True, 'Matched'), ('TFNHSGISV', 21631, nan, True, 'Matched'), ('HLSSAHLAF', 21919, nan, True, 'Matched'), ('TFNHSGISV', 21653, nan, True, 'Matched'), ('TFNHSGISV', 21640, nan, True, 'Matched'), ('HLSSAHLAF', 21920, nan, True, 'Matched'), ('TFNHSGISV', 21647, nan, True, 'Matched'), ('TFNHSGISV', 21634, nan, True, 'Matched'), ('VYFPALTSL', 21774, nan, True, 'Matched'), ('TFNHSGISV', 21582, nan, True, 'Matched'), ('LSDHLINQGY', 21726, nan, True, 'Matched'), ('TFNHSGISV', 21627, nan, True, 'Matched'), ('SAHLAFMTF', 21857, nan, True, 'Matched'), ('TFNHSGISV', 21632, nan, True, 'Matched'), ('FPALTSLLSQKVRESE', 21847, nan, False, 'Matched'), ('TFNHSGISV', 21662, nan, True, 'Matched'), ('HLSSAHLAF', 21917, nan, True, 'Matched'), ('TFNHSGISV', 21597, nan, True, 'Matched'), ('HLSSAHLAF', 21914, nan, True, 'Matched'), ('TFNHSGISV', 21630, nan, True, 'Matched'), ('HLSSAHLAF', 21916, nan, True, 'Matched'), ('TFNHSGISV', 21609, nan, True, 'Matched'), ('TFNHSGISV', 21654, nan, True, 'Matched'), ('TFNHSGISV', 21594, nan, True, 'Matched'), ('TFNHSGISV', 21615, nan, True, 'Matched'), ('TFNHSGISV', 21664, nan, True, 'Matched'), ('TFNHSGISV', 21584, nan, True, 'Matched'), ('TFNHSGISV', 21599, nan, True, 'Matched'), ('LSDHLINQGY', 21728, nan, True, 'Matched'), ('TPLLAHLSSAHLA', 21820, nan, True, 'Matched'), ('FPDAKGWIF', 21961, nan, True, 'Matched'), ('TFNHSGISV', 21651, nan, True, 'Matched'), ('LSDHLINQGY', 21681, nan, True, 'Matched'), ('FPALTSLLSQKVRESE', 21839, nan, False, 'Matched'), ('TFNHSGISV', 21620, nan, True, 'Matched'), ('TFNHSGISV', 21610, nan, True, 'Matched'), ('TFNHSGISV', 21587, nan, True, 'Matched'), ('TFNHSGISV', 21670, nan, True, 'Matched'), ('SAHLAFMTF', 21870, nan, True, 'Matched'), ('HLSSAHLAF', 21913, nan, True, 'Matched'), ('TFNHSGISV', 21613, nan, True, 'Matched'), ('TPLLAHLSSAHLA', 21821, nan, True, 'Matched'), ('NHSGISVNI', 21878, nan, True, 'Matched'), ('FPALTSLLSQKVRESE', 21843, nan, False, 'Matched'), ('TFNHSGISV', 21636, nan, True, 'Matched'), ('LSDHLINQGY', 21694, nan, True, 'Matched'), ('LSDHLINQGY', 21693, nan, True, 'Matched'), ('LSDHLINQGY', 21729, nan, True, 'Matched'), ('LSDHLINQGY', 21718, nan, True, 'Matched'), ('LSDHLINQGY', 21683, nan, True, 'Matched'), ('LSDHLINQGY', 21722, nan, True, 'Matched'), ('LSDHLINQGY', 21724, nan, True, 'Matched'), ('FPALTSLLSQKVRESE', 21837, nan, False, 'Matched'), ('LSDHLINQGY', 21687, nan, True, 'Matched'), ('LSDHLINQGY', 21720, nan, True, 'Matched'), ('HLSSAHLAF', 21915, nan, True, 'Matched'), ('LSDHLINQGY', 21692, nan, True, 'Matched'), ('TFNHSGISV', 21661, nan, True, 'Matched'), ('LSDHLINQGY', 21723, nan, True, 'Matched'), ('TFNHSGISV', 21668, nan, True, 'Matched'), ('VDLSSTHEDL', 21949, nan, True, 'Matched'), ('TFNHSGISV', 21644, nan, True, 'Matched'), ('FPDAKGWIF', 21962, nan, True, 'Matched'), ('TFNHSGISV', 21639, nan, True, 'Matched'), ('LSDHLINQGY', 21696, nan, True, 'Matched'), ('LSDHLINQGY', 21695, nan, True, 'Matched'), ('VDLSSTHEDL', 21948, nan, True, 'Matched'), ('TFNHSGISV', 21666, nan, True, 'Matched'), ('TFNHSGISV', 21665, nan, True, 'Matched'), ('LSDHLINQGY', 21719, nan, True, 'Matched'), ('VTPLLAHLSSAHLA', 21899, nan, False, 'Matched'), ('SAHLAFMTF', 21865, nan, True, 'Matched'), ('TFNHSGISV', 21641, nan, True, 'Matched'), ('VTPLLAHLSSAHLA', 21895, nan, False, 'Matched'), ('TFNHSGISV', 21648, nan, True, 'Matched'), ('ETFPDAKGWIF', 21958, nan, False, 'Matched'), ('TPLLAHLSSAHLA', 21822, nan, True, 'Matched'), ('LSDHLINQGY', 21682, nan, True, 'Matched'), ('SAHLAFMTF', 21860, nan, True, 'Matched'), ('FPALTSLLSQKVRESE', 21842, nan, False, 'Matched'), ('LSDHLINQGY', 21730, nan, True, 'Matched'), ('LSDHLINQGY', 21717, nan, True, 'Matched'), ('VYFPALTSL', 21755, nan, True, 'Matched'), ('FPALTSLLSQKVRESE', 21844, nan, False, 'Matched'), ('TFNHSGISV', 21646, nan, True, 'Matched'), ('RSSMPICTV', 21940, nan, True, 'Matched'), ('TPLLAHLSSAHLA', 21823, nan, True, 'Matched'), ('ETFPDAKGWIF', 21959, nan, False, 'Matched'), ('LSDHLINQGY', 21732, nan, True, 'Matched'), ('RSSMPICTV', 21938, nan, True, 'Matched'), ('LSDHLINQGY', 21733, nan, True, 'Matched'), ('TFNHSGISV', 21657, nan, True, 'Matched'), ('VYFPALTSL', 21742, nan, True, 'Matched'), ('LSDHLINQGY', 21716, nan, True, 'Matched'), ('ETFPDAKGWIF', 21957, nan, False, 'Matched'), ('VTPLLAHLSSAHLA', 21896, nan, False, 'Matched'), ('TPLLAHLSSAHLA', 21814, nan, True, 'Matched'), ('VYFPALTSL', 21741, nan, True, 'Matched'), ('SAHLAFMTF', 21867, nan, True, 'Matched'), ('LSDHLINQGY', 21677, nan, True, 'Matched'), ('TPLLAHLSSAHLA', 21815, nan, True, 'Matched'), ('LSDHLINQGY', 21715, nan, True, 'Matched'), ('FPALTSLLSQKVRESE', 21845, nan, False, 'Matched'), ('LSDHLINQGY', 21734, nan, True, 'Matched'), ('LSDHLINQGY', 21680, nan, True, 'Matched'), ('VYFPALTSL', 21751, nan, True, 'Matched'), ('VYFPALTSL', 21780, nan, True, 'Matched'), ('RSSMPICTV', 21939, nan, True, 'Matched'), ('LSDHLINQGY', 21727, nan, True, 'Matched'), ('VYFPALTSL', 21740, nan, True, 'Matched'), ('VYFPALTSL', 21786, nan, True, 'Matched'), ('LSDHLINQGY', 21697, nan, True, 'Matched'), ('VYFPALTSL', 21798, nan, True, 'Matched'), ('VYFPALTSL', 21797, nan, True, 'Matched'), ('LSDHLINQGY', 21699, nan, True, 'Matched'), ('LSDHLINQGY', 21698, nan, True, 'Matched'), ('LSDHLINQGY', 21690, nan, True, 'Matched'), ('VYFPALTSL', 21790, nan, True, 'Matched'), ('VTPLLAHLSSAHLA', 21890, nan, False, 'Matched'), ('VDLSSTHEDL', 21952, nan, True, 'Matched'), ('LSDHLINQGY', 21736, nan, True, 'Matched'), ('VYFPALTSL', 21746, nan, True, 'Matched'), ('VYFPALTSL', 21782, nan, True, 'Matched'), ('VYFPALTSL', 21788, nan, True, 'Matched'), ('VYFPALTSL', 21783, nan, True, 'Matched'), ('VYFPALTSL', 21743, nan, True, 'Matched'), ('VYFPALTSL', 21749, nan, True, 'Matched'), ('TFNHSGISV', 21625, nan, True, 'Matched'), ('VTPLLAHLSSAHLA', 21894, nan, False, 'Matched'), ('VYFPALTSL', 21781, nan, True, 'Matched'), ('VYFPALTSL', 21753, nan, True, 'Matched'), ('VYFPALTSL', 21784, nan, True, 'Matched'), ('LSDHLINQGY', 21731, nan, True, 'Matched'), ('VYFPALTSL', 21748, nan, True, 'Matched'), ('VYFPALTSL', 21787, nan, True, 'Matched'), ('VYFPALTSL', 21791, nan, True, 'Matched'), ('VYFPALTSL', 21747, nan, True, 'Matched'), ('VYFPALTSL', 21792, nan, True, 'Matched'), ('VYFPALTSL', 21789, nan, True, 'Matched'), ('VYFPALTSL', 21778, nan, True, 'Matched'), ('VYFPALTSL', 21757, nan, True, 'Matched'), ('VYFPALTSL', 21779, nan, True, 'Matched'), ('VYFPALTSL', 21794, nan, True, 'Matched'), ('TPLLAHLSSAHLA', 21819, nan, True, 'Matched'), ('VYFPALTSL', 21750, nan, True, 'Matched'), ('VYFPALTSL', 21795, nan, True, 'Matched'), ('VYFPALTSL', 21745, nan, True, 'Matched'), ('KVRESERAF', 21964, nan, True, 'Matched'), ('VYFPALTSL', 21752, nan, True, 'Matched'), ('VYFPALTSL', 21785, nan, True, 'Matched'), ('FPALTSLLSQKVRESE', 21830, nan, False, 'Matched'), ('KVRESERAF', 21965, nan, True, 'Matched'), ('TPLLAHLSSAHLA', 21817, nan, True, 'Matched'), ('VYFPALTSL', 21754, nan, True, 'Matched'), ('LSDHLINQGY', 21676, nan, True, 'Matched'), ('RSSMPICTV', 21937, nan, True, 'Matched'), ('VYFPALTSL', 21796, nan, True, 'Matched'), ('VYFPALTSL', 21756, nan, True, 'Matched'), ('VTPLLAHLSSAHLA', 21893, nan, False, 'Matched'), ('FRKPAVWAA', 21906, nan, True, 'Matched'), ('VYFPALTSL', 21744, nan, True, 'Matched'), ('TPLLAHLSSAHLA', 21824, nan, True, 'Matched'), ('KPAVWAAVVSQLSAA', 21946, nan, True, 'Matched'), ('KPAVWAAVVSQLSAA', 21944, nan, True, 'Matched'), ('KPAVWAAVVSQLSAA', 21945, nan, True, 'Matched'), ('KPAVWAAVVSQLSAA', 21943, nan, True, 'Matched'), ('VTPLLAHLSSAHLA', 21900, nan, False, 'Matched'), ('VTPLLAHLSSAHLA', 21891, nan, False, 'Matched'), ('FRKPAVWAA', 21904, nan, True, 'Matched'), ('FRKPAVWAA', 21908, nan, True, 'Matched'), ('VTPLLAHLSSAHLA', 21897, nan, False, 'Matched'), ('FRKPAVWAA', 21909, nan, True, 'Matched'), ('FRKPAVWAA', 21902, nan, True, 'Matched'), ('FRKPAVWAA', 21901, nan, True, 'Matched'), ('FRKPAVWAA', 21907, nan, True, 'Matched'), ('TPLLAHLSSAHLAF', 21967, nan, False, 'Matched'), ('FRKPAVWAA', 21903, nan, True, 'Matched'), ('FRKPAVWAA', 21910, nan, True, 'Matched')] | I4: 18 | J4: =IFERROR(VLOOKUP(A4,dbg_proteins!$A$2:$A$20161,1,FALSE)," ---") -> Q9BYT1
A5: Q9HC10 | B5: 178 | C5: [('YFASIDTMKEQLR', 23245, 'non_standard_modification', True, 'Missed'), ('YFASIDTMKEQLR', 23246, 'non_standard_modification', True, 'Missed'), ('LKLLLLLLLLL', 23258, 'HLA1', True, 'Missed'), ('YFASIDTMKEQLR', 23244, 'non_standard_modification', True, 'Missed'), ('ATDLHPADINGK', 23247, 'regular_tryptic', True, 'Missed'), ('TGDDEDGSTEEER', 23220, 'IDENTIFIED', True, 'Missed'), ('TGDDEDGSTEEER', 23123, 'IDENTIFIED', True, 'Missed'), ('TGDDEDGSTEEER', 23111, 'IDENTIFIED', True, 'Missed'), ('TGDDEDGSTEEER', 23174, 'IDENTIFIED', True, 'Missed'), ('TGDDEDGSTEEER', 23032, 'IDENTIFIED', True, 'Missed'), ('TGDDEDGSTEEER', 23098, 'IDENTIFIED', True, 'Missed'), ('KDGKVDGPHF', 23256, 'HLA1', True, 'Missed'), ('TGDDEDGSTEEER', 23145, 'IDENTIFIED', True, 'Missed'), ('TGDDEDGSTEEER', 23140, 'IDENTIFIED', True, 'Missed'), ('TGDDEDGSTEEER', 23046, 'IDENTIFIED', True, 'Missed'), ('TGDDEDGSTEEER', 23037, 'IDENTIFIED', True, 'Missed'), ('TGDDEDGSTEEER', 23108, 'IDENTIFIED', True, 'Missed'), ('TGDDEDGSTEEER', 23072, 'IDENTIFIED', True, 'Missed'), ('TGDDEDGSTEEER', 23213, 'IDENTIFIED', True, 'Missed'), ('TGDDEDGSTEEER', 23058, 'IDENTIFIED', True, 'Missed'), ('TGDDEDGSTEEER', 23071, 'IDENTIFIED', True, 'Missed'), ('TGDDEDGSTEEER', 23059, 'IDENTIFIED', True, 'Missed'), ('TGDDEDGSTEEER', 23049, 'IDENTIFIED', True, 'Missed'), ('TGDDEDGSTEEER', 23057, 'IDENTIFIED', True, 'Missed'), ('TGDDEDGSTEEER', 23063, 'IDENTIFIED', True, 'Missed'), ('TGDDEDGSTEEER', 23208, 'IDENTIFIED', True, 'Missed'), ('TGDDEDGSTEEER', 23198, 'IDENTIFIED', True, 'Missed'), ('TGDDEDGSTEEER', 23045, 'IDENTIFIED', True, 'Missed'), ('TGDDEDGSTEEER', 23055, 'IDENTIFIED', True, 'Missed'), ('TGDDEDGSTEEER', 23086, 'IDENTIFIED', True, 'Missed'), ('TGDDEDGSTEEER', 23215, 'IDENTIFIED', True, 'Missed'), ('TGDDEDGSTEEER', 23039, 'IDENTIFIED', True, 'Missed'), ('TGDDEDGSTEEER', 23038, 'IDENTIFIED', True, 'Missed'), ('TGDDEDGSTEEER', 23064, 'IDENTIFIED', True, 'Missed'), ('TGDDEDGSTEEER', 23192, 'IDENTIFIED', True, 'Missed'), ('TGDDEDGSTEEER', 23163, 'IDENTIFIED', True, 'Missed'), ('TGDDEDGSTEEER', 23102, 'IDENTIFIED', True, 'Missed'), ('TGDDEDGSTEEER', 23194, 'IDENTIFIED', True, 'Missed'), ('TGDDEDGSTEEER', 23168, 'IDENTIFIED', True, 'Missed'), ('TGDDEDGSTEEER', 23080, 'IDENTIFIED', True, 'Missed'), ('TGDDEDGSTEEER', 23097, 'IDENTIFIED', True, 'Missed'), ('TGDDEDGSTEEER', 23144, 'IDENTIFIED', True, 'Missed'), ('TGDDEDGSTEEER', 23044, 'IDENTIFIED', True, 'Missed'), ('TGDDEDGSTEEER', 23104, 'IDENTIFIED', True, 'Missed'), ('TGDDEDGSTEEER', 23151, 'IDENTIFIED', True, 'Missed'), ('TGDDEDGSTEEER', 23209, 'IDENTIFIED', True, 'Missed'), ('TGDDEDGSTEEER', 23030, 'IDENTIFIED', True, 'Missed'), ('TGDDEDGSTEEER', 23078, 'IDENTIFIED', True, 'Missed'), ('TGDDEDGSTEEER', 23136, 'IDENTIFIED', True, 'Missed'), ('TGDDEDGSTEEER', 23103, 'IDENTIFIED', True, 'Missed'), ('TGDDEDGSTEEER', 23066, 'IDENTIFIED', True, 'Missed'), ('TGDDEDGSTEEER', 23214, 'IDENTIFIED', True, 'Missed'), ('TGDDEDGSTEEER', 23035, 'IDENTIFIED', True, 'Missed'), ('TGDDEDGSTEEER', 23033, 'IDENTIFIED', True, 'Missed'), ('TGDDEDGSTEEER', 23081, 'IDENTIFIED', True, 'Missed'), ('TGDDEDGSTEEER', 23048, 'IDENTIFIED', True, 'Missed'), ('TGDDEDGSTEEER', 23155, 'IDENTIFIED', True, 'Missed'), ('TGDDEDGSTEEER', 23043, 'IDENTIFIED', True, 'Missed'), ('TGDDEDGSTEEER', 23153, 'IDENTIFIED', True, 'Missed'), ('TGDDEDGSTEEER', 23093, 'IDENTIFIED', True, 'Missed'), ('TGDDEDGSTEEER', 23053, 'IDENTIFIED', True, 'Missed'), ('TGDDEDGSTEEER', 23042, 'IDENTIFIED', True, 'Missed'), ('TGDDEDGSTEEER', 23217, 'IDENTIFIED', True, 'Missed'), ('TGDDEDGSTEEER', 23084, 'IDENTIFIED', True, 'Missed'), ('TGDDEDGSTEEER', 23050, 'IDENTIFIED', True, 'Missed'), ('TGDDEDGSTEEER', 23087, 'IDENTIFIED', True, 'Missed'), ('TGDDEDGSTEEER', 23082, 'IDENTIFIED', True, 'Missed'), ('TGDDEDGSTEEER', 23121, 'IDENTIFIED', True, 'Missed'), ('TGDDEDGSTEEER', 23036, 'IDENTIFIED', True, 'Missed'), ('TGDDEDGSTEEER', 23115, 'IDENTIFIED', True, 'Missed'), ('TGDDEDGSTEEER', 23152, 'IDENTIFIED', True, 'Missed'), ('TGDDEDGSTEEER', 23158, 'IDENTIFIED', True, 'Missed'), ('TGDDEDGSTEEER', 23056, 'IDENTIFIED', True, 'Missed'), ('TGDDEDGSTEEER', 23197, 'IDENTIFIED', True, 'Missed'), ('TGDDEDGSTEEER', 23070, 'IDENTIFIED', True, 'Missed'), ('TGDDEDGSTEEER', 23107, 'IDENTIFIED', True, 'Missed'), ('TGDDEDGSTEEER', 23124, 'IDENTIFIED', True, 'Missed'), ('TGDDEDGSTEEER', 23238, 'IDENTIFIED', True, 'Missed'), ('TGDDEDGSTEEER', 23210, 'IDENTIFIED', True, 'Missed'), ('TGDDEDGSTEEER', 23052, 'IDENTIFIED', True, 'Missed'), ('TGDDEDGSTEEER', 23219, 'IDENTIFIED', True, 'Missed'), ('TGDDEDGSTEEER', 23142, 'IDENTIFIED', True, 'Missed'), ('TGDDEDGSTEEER', 23089, 'IDENTIFIED', True, 'Missed'), ('TGDDEDGSTEEER', 23095, 'IDENTIFIED', True, 'Missed'), ('TGDDEDGSTEEER', 23176, 'IDENTIFIED', True, 'Missed'), ('TGDDEDGSTEEER', 23129, 'IDENTIFIED', True, 'Missed'), ('TGDDEDGSTEEER', 23054, 'IDENTIFIED', True, 'Missed'), ('TGDDEDGSTEEER', 23154, 'IDENTIFIED', True, 'Missed'), ('TGDDEDGSTEEER', 23096, 'IDENTIFIED', True, 'Missed'), ('TGDDEDGSTEEER', 23141, 'IDENTIFIED', True, 'Missed'), ('TGDDEDGSTEEER', 23188, 'IDENTIFIED', True, 'Missed'), ('TGDDEDGSTEEER', 23062, 'IDENTIFIED', True, 'Missed'), ('TGDDEDGSTEEER', 23227, 'IDENTIFIED', True, 'Missed'), ('TGDDEDGSTEEER', 23241, 'IDENTIFIED', True, 'Missed'), ('TGDDEDGSTEEER', 23146, 'IDENTIFIED', True, 'Missed'), ('TGDDEDGSTEEER', 23125, 'IDENTIFIED', True, 'Missed'), ('TGDDEDGSTEEER', 23218, 'IDENTIFIED', True, 'Missed'), ('TGDDEDGSTEEER', 23242, 'IDENTIFIED', True, 'Missed'), ('TGDDEDGSTEEER', 23112, 'IDENTIFIED', True, 'Missed'), ('TGDDEDGSTEEER', 23075, 'IDENTIFIED', True, 'Missed'), ('TGDDEDGSTEEER', 23133, 'IDENTIFIED', True, 'Missed'), ('TGDDEDGSTEEER', 23230, 'IDENTIFIED', True, 'Missed'), ('TGDDEDGSTEEER', 23228, 'IDENTIFIED', True, 'Missed'), ('TGDDEDGSTEEER', 23160, 'IDENTIFIED', True, 'Missed'), ('TGDDEDGSTEEER', 23191, 'IDENTIFIED', True, 'Missed'), ('TGDDEDGSTEEER', 23094, 'IDENTIFIED', True, 'Missed'), ('TGDDEDGSTEEER', 23085, 'IDENTIFIED', True, 'Missed'), ('TGDDEDGSTEEER', 23028, 'IDENTIFIED', True, 'Missed'), ('TGDDEDGSTEEER', 23156, 'IDENTIFIED', True, 'Missed'), ('TGDDEDGSTEEER', 23159, 'IDENTIFIED', True, 'Missed'), ('TGDDEDGSTEEER', 23222, 'IDENTIFIED', True, 'Missed'), ('TGDDEDGSTEEER', 23186, 'IDENTIFIED', True, 'Missed'), ('TGDDEDGSTEEER', 23165, 'IDENTIFIED', True, 'Missed'), ('TGDDEDGSTEEER', 23077, 'IDENTIFIED', True, 'Missed'), ('TGDDEDGSTEEER', 23076, 'IDENTIFIED', True, 'Missed'), ('TGDDEDGSTEEER', 23061, 'IDENTIFIED', True, 'Missed'), ('TGDDEDGSTEEER', 23232, 'IDENTIFIED', True, 'Missed'), ('TGDDEDGSTEEER', 23031, 'IDENTIFIED', True, 'Missed'), ('TGDDEDGSTEEER', 23233, 'IDENTIFIED', True, 'Missed'), ('TGDDEDGSTEEER', 23161, 'IDENTIFIED', True, 'Missed'), ('TGDDEDGSTEEER', 23127, 'IDENTIFIED', True, 'Missed'), ('TGDDEDGSTEEER', 23090, 'IDENTIFIED', True, 'Missed'), ('TGDDEDGSTEEER', 23223, 'IDENTIFIED', True, 'Missed'), ('TGDDEDGSTEEER', 23190, 'IDENTIFIED', True, 'Missed'), ('TGDDEDGSTEEER', 23100, 'IDENTIFIED', True, 'Missed'), ('TGDDEDGSTEEER', 23120, 'IDENTIFIED', True, 'Missed'), ('TGDDEDGSTEEER', 23236, 'IDENTIFIED', True, 'Missed'), ('TGDDEDGSTEEER', 23170, 'IDENTIFIED', True, 'Missed'), ('TGDDEDGSTEEER', 23206, 'IDENTIFIED', True, 'Missed'), ('TGDDEDGSTEEER', 23234, 'IDENTIFIED', True, 'Missed'), ('TGDDEDGSTEEER', 23134, 'IDENTIFIED', True, 'Missed'), ('TGDDEDGSTEEER', 23109, 'IDENTIFIED', True, 'Missed'), ('TGDDEDGSTEEER', 23211, 'IDENTIFIED', True, 'Missed'), ('TGDDEDGSTEEER', 23199, 'IDENTIFIED', True, 'Missed'), ('TGDDEDGSTEEER', 23181, 'IDENTIFIED', True, 'Missed'), ('TGDDEDGSTEEER', 23131, 'IDENTIFIED', True, 'Missed'), ('TGDDEDGSTEEER', 23113, 'IDENTIFIED', True, 'Missed'), ('TGDDEDGSTEEER', 23166, 'IDENTIFIED', True, 'Missed'), ('TGDDEDGSTEEER', 23193, 'IDENTIFIED', True, 'Missed'), ('TGDDEDGSTEEER', 23106, 'IDENTIFIED', True, 'Missed'), ('TGDDEDGSTEEER', 23135, 'IDENTIFIED', True, 'Missed'), ('TGDDEDGSTEEER', 23130, 'IDENTIFIED', True, 'Missed'), ('TGDDEDGSTEEER', 23051, 'IDENTIFIED', True, 'Missed'), ('TGDDEDGSTEEER', 23237, 'IDENTIFIED', True, 'Missed'), ('TGDDEDGSTEEER', 23143, 'IDENTIFIED', True, 'Missed'), ('TGDDEDGSTEEER', 23205, 'IDENTIFIED', True, 'Missed'), ('TGDDEDGSTEEER', 23207, 'IDENTIFIED', True, 'Missed'), ('TGDDEDGSTEEER', 23164, 'IDENTIFIED', True, 'Missed'), ('TGDDEDGSTEEER', 23229, 'IDENTIFIED', True, 'Missed'), ('TGDDEDGSTEEER', 23203, 'IDENTIFIED', True, 'Missed'), ('TGDDEDGSTEEER', 23189, 'IDENTIFIED', True, 'Missed'), ('TGDDEDGSTEEER', 23122, 'IDENTIFIED', True, 'Missed'), ('TGDDEDGSTEEER', 23224, 'IDENTIFIED', True, 'Missed'), ('TGDDEDGSTEEER', 23137, 'IDENTIFIED', True, 'Missed'), ('TGDDEDGSTEEER', 23195, 'IDENTIFIED', True, 'Missed'), ('TGDDEDGSTEEER', 23150, 'IDENTIFIED', True, 'Missed'), ('TGDDEDGSTEEER', 23243, 'IDENTIFIED', True, 'Missed'), ('TGDDEDGSTEEER', 23172, 'IDENTIFIED', True, 'Missed'), ('TGDDEDGSTEEER', 23148, 'IDENTIFIED', True, 'Missed'), ('TGDDEDGSTEEER', 23171, 'IDENTIFIED', True, 'Missed'), ('TGDDEDGSTEEER', 23187, 'IDENTIFIED', True, 'Missed'), ('TGDDEDGSTEEER', 23180, 'IDENTIFIED', True, 'Missed'), ('TGDDEDGSTEEER', 23118, 'IDENTIFIED', True, 'Missed'), ('TGDDEDGSTEEER', 23149, 'IDENTIFIED', True, 'Missed'), ('TGDDEDGSTEEER', 23126, 'IDENTIFIED', True, 'Missed'), ('TGDDEDGSTEEER', 23239, 'IDENTIFIED', True, 'Missed'), ('TGDDEDGSTEEER', 23157, 'IDENTIFIED', True, 'Missed'), ('TGDDEDGSTEEER', 23231, 'IDENTIFIED', True, 'Missed'), ('TGDDEDGSTEEER', 23201, 'IDENTIFIED', True, 'Missed'), ('TGDDEDGSTEEER', 23202, 'IDENTIFIED', True, 'Missed'), ('TGDDEDGSTEEER', 23221, 'IDENTIFIED', True, 'Missed'), ('TGDDEDGSTEEER', 23184, 'IDENTIFIED', True, 'Missed'), ('TGDDEDGSTEEER', 23173, 'IDENTIFIED', True, 'Missed'), ('TGDDEDGSTEEER', 23179, 'IDENTIFIED', True, 'Missed'), ('TGDDEDGSTEEER', 23200, 'IDENTIFIED', True, 'Missed'), ('TGDDEDGSTEEER', 23110, 'IDENTIFIED', True, 'Missed'), ('TGDDEDGSTEEER', 23175, 'IDENTIFIED', True, 'Missed'), ('TGDDEDGSTEEER', 23196, 'IDENTIFIED', True, 'Missed')] | D5: 5 | E5: 44 | F5: [('VLENCEDVADFDETFR', 23262, nan, True, 'Matched'), ('SLFAADSSGLSDPFAR', 23260, nan, True, 'Matched'), ('DLLFSIVEEETGKDCAK', 23254, nan, False, 'Matched'), ('WAILSDPDDISSGLK', 23264, nan, True, 'Matched'), ('VFTGPSEIEDENGQR', 23261, nan, True, 'Matched'), ('DLLFSIVEEETGK', 23253, nan, True, 'Matched'), ('VPLPEDVSR', 23263, nan, True, 'Matched'), ('YFASIDTMK', 23265, nan, True, 'Matched'), ('KGTAEEPEEEEPDESMLDWWSK', 23257, nan, False, 'Matched'), ('YLFPFDYLAAEEK', 23266, nan, True, 'Matched'), ('GTAEEPEEEEPDESMLDWWSK', 23248, nan, True, 'Matched'), ('GVQSSLIHNYK', 23255, nan, True, 'Matched'), ('AAQGLGLHAFPPVSLVYTK', 23252, nan, True, 'Matched'), ('NEPDPLEKPNRPDTSFIWFLNPLK', 23259, nan, True, 'Matched'), ('TGDDEDGSTEEER', 23091, nan, True, 'Matched'), ('TGDDEDGSTEEER', 23067, nan, True, 'Matched'), ('GTAEEPEEEEPDESMLDWWSK', 23249, nan, True, 'Matched'), ('TGDDEDGSTEEER', 23069, nan, True, 'Matched'), ('TGDDEDGSTEEER', 23117, nan, True, 'Matched'), ('TGDDEDGSTEEER', 23047, nan, True, 'Matched'), ('TGDDEDGSTEEER', 23101, nan, True, 'Matched'), ('TGDDEDGSTEEER', 23092, nan, True, 'Matched'), ('TGDDEDGSTEEER', 23114, nan, True, 'Matched'), ('TGDDEDGSTEEER', 23099, nan, True, 'Matched'), ('TGDDEDGSTEEER', 23040, nan, True, 'Matched'), ('TGDDEDGSTEEER', 23116, nan, True, 'Matched'), ('TGDDEDGSTEEER', 23068, nan, True, 'Matched'), ('TGDDEDGSTEEER', 23083, nan, True, 'Matched'), ('TGDDEDGSTEEER', 23235, nan, True, 'Matched'), ('TGDDEDGSTEEER', 23139, nan, True, 'Matched'), ('TGDDEDGSTEEER', 23079, nan, True, 'Matched'), ('TGDDEDGSTEEER', 23074, nan, True, 'Matched'), ('TGDDEDGSTEEER', 23029, nan, True, 'Matched'), ('TGDDEDGSTEEER', 23128, nan, True, 'Matched'), ('TGDDEDGSTEEER', 23182, nan, True, 'Matched'), ('TGDDEDGSTEEER', 23167, nan, True, 'Matched'), ('TGDDEDGSTEEER', 23073, nan, True, 'Matched'), ('TGDDEDGSTEEER', 23216, nan, True, 'Matched'), ('TGDDEDGSTEEER', 23065, nan, True, 'Matched'), ('TGDDEDGSTEEER', 23060, nan, True, 'Matched'), ('TGDDEDGSTEEER', 23119, nan, True, 'Matched'), ('TGDDEDGSTEEER', 23034, nan, True, 'Matched'), ('TGDDEDGSTEEER', 23147, nan, True, 'Matched'), ('TGDDEDGSTEEER', 23041, nan, True, 'Matched')] | G5: 13 | H5: [('YFASIDTMKEQLR', 23245, 'non_standard_modification', False, 'Missed'), ('YFASIDTMKEQLR', 23246, 'non_standard_modification', False, 'Missed'), ('LKLLLLLLLLL', 23258, 'HLA1', True, 'Missed'), ('YFASIDTMKEQLR', 23244, 'non_standard_modification', False, 'Missed'), ('ATDLHPADINGK', 23247, 'regular_tryptic', True, 'Missed'), ('TGDDEDGSTEEER', 23220, 'IDENTIFIED', True, 'Missed'), ('TGDDEDGSTEEER', 23123, 'IDENTIFIED', True, 'Missed'), ('TGDDEDGSTEEER', 23111, 'IDENTIFIED', True, 'Missed'), ('TGDDEDGSTEEER', 23174, 'IDENTIFIED', True, 'Missed'), ('TGDDEDGSTEEER', 23032, 'IDENTIFIED', True, 'Missed'), ('TGDDEDGSTEEER', 23098, 'IDENTIFIED', True, 'Missed'), ('KDGKVDGPHF', 23256, 'HLA1', True, 'Missed'), ('TGDDEDGSTEEER', 23145, 'IDENTIFIED', True, 'Missed'), ('TGDDEDGSTEEER', 23140, 'IDENTIFIED', True, 'Missed'), ('TGDDEDGSTEEER', 23046, 'IDENTIFIED', True, 'Missed'), ('TGDDEDGSTEEER', 23037, 'IDENTIFIED', True, 'Missed'), ('TGDDEDGSTEEER', 23108, 'IDENTIFIED', True, 'Missed'), ('TGDDEDGSTEEER', 23072, 'IDENTIFIED', True, 'Missed'), ('TGDDEDGSTEEER', 23213, 'IDENTIFIED', True, 'Missed'), ('TGDDEDGSTEEER', 23058, 'IDENTIFIED', True, 'Missed'), ('TGDDEDGSTEEER', 23071, 'IDENTIFIED', True, 'Missed'), ('TGDDEDGSTEEER', 23059, 'IDENTIFIED', True, 'Missed'), ('TGDDEDGSTEEER', 23049, 'IDENTIFIED', True, 'Missed'), ('TGDDEDGSTEEER', 23057, 'IDENTIFIED', True, 'Missed'), ('TGDDEDGSTEEER', 23063, 'IDENTIFIED', True, 'Missed'), ('TGDDEDGSTEEER', 23208, 'IDENTIFIED', True, 'Missed'), ('TGDDEDGSTEEER', 23198, 'IDENTIFIED', True, 'Missed'), ('TGDDEDGSTEEER', 23045, 'IDENTIFIED', True, 'Missed'), ('TGDDEDGSTEEER', 23055, 'IDENTIFIED', True, 'Missed'), ('TGDDEDGSTEEER', 23086, 'IDENTIFIED', True, 'Missed'), ('TGDDEDGSTEEER', 23215, 'IDENTIFIED', True, 'Missed'), ('TGDDEDGSTEEER', 23039, 'IDENTIFIED', True, 'Missed'), ('TGDDEDGSTEEER', 23038, 'IDENTIFIED', True, 'Missed'), ('TGDDEDGSTEEER', 23064, 'IDENTIFIED', True, 'Missed'), ('TGDDEDGSTEEER', 23192, 'IDENTIFIED', True, 'Missed'), ('TGDDEDGSTEEER', 23163, 'IDENTIFIED', True, 'Missed'), ('TGDDEDGSTEEER', 23102, 'IDENTIFIED', True, 'Missed'), ('TGDDEDGSTEEER', 23194, 'IDENTIFIED', True, 'Missed'), ('TGDDEDGSTEEER', 23168, 'IDENTIFIED', True, 'Missed'), ('TGDDEDGSTEEER', 23080, 'IDENTIFIED', True, 'Missed'), ('TGDDEDGSTEEER', 23097, 'IDENTIFIED', True, 'Missed'), ('TGDDEDGSTEEER', 23144, 'IDENTIFIED', True, 'Missed'), ('TGDDEDGSTEEER', 23044, 'IDENTIFIED', True, 'Missed'), ('TGDDEDGSTEEER', 23104, 'IDENTIFIED', True, 'Missed'), ('TGDDEDGSTEEER', 23151, 'IDENTIFIED', True, 'Missed'), ('TGDDEDGSTEEER', 23209, 'IDENTIFIED', True, 'Missed'), ('TGDDEDGSTEEER', 23030, 'IDENTIFIED', True, 'Missed'), ('TGDDEDGSTEEER', 23078, 'IDENTIFIED', True, 'Missed'), ('TGDDEDGSTEEER', 23136, 'IDENTIFIED', True, 'Missed'), ('TGDDEDGSTEEER', 23103, 'IDENTIFIED', True, 'Missed'), ('TGDDEDGSTEEER', 23066, 'IDENTIFIED', True, 'Missed'), ('TGDDEDGSTEEER', 23214, 'IDENTIFIED', True, 'Missed'), ('TGDDEDGSTEEER', 23035, 'IDENTIFIED', True, 'Missed'), ('TGDDEDGSTEEER', 23033, 'IDENTIFIED', True, 'Missed'), ('TGDDEDGSTEEER', 23081, 'IDENTIFIED', True, 'Missed'), ('TGDDEDGSTEEER', 23048, 'IDENTIFIED', True, 'Missed'), ('TGDDEDGSTEEER', 23155, 'IDENTIFIED', True, 'Missed'), ('TGDDEDGSTEEER', 23043, 'IDENTIFIED', True, 'Missed'), ('TGDDEDGSTEEER', 23153, 'IDENTIFIED', True, 'Missed'), ('TGDDEDGSTEEER', 23093, 'IDENTIFIED', True, 'Missed'), ('TGDDEDGSTEEER', 23053, 'IDENTIFIED', True, 'Missed'), ('TGDDEDGSTEEER', 23042, 'IDENTIFIED', True, 'Missed'), ('TGDDEDGSTEEER', 23217, 'IDENTIFIED', True, 'Missed'), ('TGDDEDGSTEEER', 23084, 'IDENTIFIED', True, 'Missed'), ('TGDDEDGSTEEER', 23050, 'IDENTIFIED', True, 'Missed'), ('TGDDEDGSTEEER', 23087, 'IDENTIFIED', True, 'Missed'), ('TGDDEDGSTEEER', 23082, 'IDENTIFIED', True, 'Missed'), ('TGDDEDGSTEEER', 23121, 'IDENTIFIED', True, 'Missed'), ('TGDDEDGSTEEER', 23036, 'IDENTIFIED', True, 'Missed'), ('TGDDEDGSTEEER', 23115, 'IDENTIFIED', True, 'Missed'), ('TGDDEDGSTEEER', 23152, 'IDENTIFIED', True, 'Missed'), ('TGDDEDGSTEEER', 23158, 'IDENTIFIED', True, 'Missed'), ('TGDDEDGSTEEER', 23056, 'IDENTIFIED', True, 'Missed'), ('TGDDEDGSTEEER', 23197, 'IDENTIFIED', True, 'Missed'), ('TGDDEDGSTEEER', 23070, 'IDENTIFIED', True, 'Missed'), ('TGDDEDGSTEEER', 23107, 'IDENTIFIED', True, 'Missed'), ('TGDDEDGSTEEER', 23124, 'IDENTIFIED', True, 'Missed'), ('TGDDEDGSTEEER', 23238, 'IDENTIFIED', True, 'Missed'), ('TGDDEDGSTEEER', 23210, 'IDENTIFIED', True, 'Missed'), ('TGDDEDGSTEEER', 23052, 'IDENTIFIED', True, 'Missed'), ('TGDDEDGSTEEER', 23219, 'IDENTIFIED', True, 'Missed'), ('TGDDEDGSTEEER', 23142, 'IDENTIFIED', True, 'Missed'), ('TGDDEDGSTEEER', 23089, 'IDENTIFIED', True, 'Missed'), ('TGDDEDGSTEEER', 23095, 'IDENTIFIED', True, 'Missed'), ('TGDDEDGSTEEER', 23176, 'IDENTIFIED', True, 'Missed'), ('TGDDEDGSTEEER', 23129, 'IDENTIFIED', True, 'Missed'), ('TGDDEDGSTEEER', 23054, 'IDENTIFIED', True, 'Missed'), ('TGDDEDGSTEEER', 23154, 'IDENTIFIED', True, 'Missed'), ('TGDDEDGSTEEER', 23096, 'IDENTIFIED', True, 'Missed'), ('TGDDEDGSTEEER', 23141, 'IDENTIFIED', True, 'Missed'), ('TGDDEDGSTEEER', 23188, 'IDENTIFIED', True, 'Missed'), ('TGDDEDGSTEEER', 23062, 'IDENTIFIED', True, 'Missed'), ('TGDDEDGSTEEER', 23227, 'IDENTIFIED', True, 'Missed'), ('TGDDEDGSTEEER', 23241, 'IDENTIFIED', True, 'Missed'), ('TGDDEDGSTEEER', 23146, 'IDENTIFIED', True, 'Missed'), ('TGDDEDGSTEEER', 23125, 'IDENTIFIED', True, 'Missed'), ('TGDDEDGSTEEER', 23218, 'IDENTIFIED', True, 'Missed'), ('TGDDEDGSTEEER', 23242, 'IDENTIFIED', True, 'Missed'), ('TGDDEDGSTEEER', 23112, 'IDENTIFIED', True, 'Missed'), ('TGDDEDGSTEEER', 23075, 'IDENTIFIED', True, 'Missed'), ('TGDDEDGSTEEER', 23133, 'IDENTIFIED', True, 'Missed'), ('TGDDEDGSTEEER', 23230, 'IDENTIFIED', True, 'Missed'), ('TGDDEDGSTEEER', 23228, 'IDENTIFIED', True, 'Missed'), ('TGDDEDGSTEEER', 23160, 'IDENTIFIED', True, 'Missed'), ('TGDDEDGSTEEER', 23191, 'IDENTIFIED', True, 'Missed'), ('TGDDEDGSTEEER', 23094, 'IDENTIFIED', True, 'Missed'), ('TGDDEDGSTEEER', 23085, 'IDENTIFIED', True, 'Missed'), ('TGDDEDGSTEEER', 23028, 'IDENTIFIED', True, 'Missed'), ('TGDDEDGSTEEER', 23156, 'IDENTIFIED', True, 'Missed'), ('TGDDEDGSTEEER', 23159, 'IDENTIFIED', True, 'Missed'), ('TGDDEDGSTEEER', 23222, 'IDENTIFIED', True, 'Missed'), ('TGDDEDGSTEEER', 23186, 'IDENTIFIED', True, 'Missed'), ('TGDDEDGSTEEER', 23165, 'IDENTIFIED', True, 'Missed'), ('TGDDEDGSTEEER', 23077, 'IDENTIFIED', True, 'Missed'), ('TGDDEDGSTEEER', 23076, 'IDENTIFIED', True, 'Missed'), ('TGDDEDGSTEEER', 23061, 'IDENTIFIED', True, 'Missed'), ('TGDDEDGSTEEER', 23232, 'IDENTIFIED', True, 'Missed'), ('TGDDEDGSTEEER', 23031, 'IDENTIFIED', True, 'Missed'), ('TGDDEDGSTEEER', 23233, 'IDENTIFIED', True, 'Missed'), ('TGDDEDGSTEEER', 23161, 'IDENTIFIED', True, 'Missed'), ('TGDDEDGSTEEER', 23127, 'IDENTIFIED', True, 'Missed'), ('TGDDEDGSTEEER', 23090, 'IDENTIFIED', True, 'Missed'), ('TGDDEDGSTEEER', 23223, 'IDENTIFIED', True, 'Missed'), ('TGDDEDGSTEEER', 23190, 'IDENTIFIED', True, 'Missed'), ('TGDDEDGSTEEER', 23100, 'IDENTIFIED', True, 'Missed'), ('TGDDEDGSTEEER', 23120, 'IDENTIFIED', True, 'Missed'), ('TGDDEDGSTEEER', 23236, 'IDENTIFIED', True, 'Missed'), ('TGDDEDGSTEEER', 23170, 'IDENTIFIED', True, 'Missed'), ('TGDDEDGSTEEER', 23206, 'IDENTIFIED', True, 'Missed'), ('TGDDEDGSTEEER', 23234, 'IDENTIFIED', True, 'Missed'), ('TGDDEDGSTEEER', 23134, 'IDENTIFIED', True, 'Missed'), ('TGDDEDGSTEEER', 23109, 'IDENTIFIED', True, 'Missed'), ('TGDDEDGSTEEER', 23211, 'IDENTIFIED', True, 'Missed'), ('TGDDEDGSTEEER', 23199, 'IDENTIFIED', True, 'Missed'), ('TGDDEDGSTEEER', 23181, 'IDENTIFIED', True, 'Missed'), ('TGDDEDGSTEEER', 23131, 'IDENTIFIED', True, 'Missed'), ('TGDDEDGSTEEER', 23113, 'IDENTIFIED', True, 'Missed'), ('TGDDEDGSTEEER', 23166, 'IDENTIFIED', True, 'Missed'), ('TGDDEDGSTEEER', 23193, 'IDENTIFIED', True, 'Missed'), ('TGDDEDGSTEEER', 23106, 'IDENTIFIED', True, 'Missed'), ('TGDDEDGSTEEER', 23135, 'IDENTIFIED', True, 'Missed'), ('TGDDEDGSTEEER', 23130, 'IDENTIFIED', True, 'Missed'), ('TGDDEDGSTEEER', 23051, 'IDENTIFIED', True, 'Missed'), ('TGDDEDGSTEEER', 23237, 'IDENTIFIED', True, 'Missed'), ('TGDDEDGSTEEER', 23143, 'IDENTIFIED', True, 'Missed'), ('TGDDEDGSTEEER', 23205, 'IDENTIFIED', True, 'Missed'), ('TGDDEDGSTEEER', 23207, 'IDENTIFIED', True, 'Missed'), ('TGDDEDGSTEEER', 23164, 'IDENTIFIED', True, 'Missed'), ('TGDDEDGSTEEER', 23229, 'IDENTIFIED', True, 'Missed'), ('TGDDEDGSTEEER', 23203, 'IDENTIFIED', True, 'Missed'), ('TGDDEDGSTEEER', 23189, 'IDENTIFIED', True, 'Missed'), ('TGDDEDGSTEEER', 23122, 'IDENTIFIED', True, 'Missed'), ('TGDDEDGSTEEER', 23224, 'IDENTIFIED', True, 'Missed'), ('TGDDEDGSTEEER', 23137, 'IDENTIFIED', True, 'Missed'), ('TGDDEDGSTEEER', 23195, 'IDENTIFIED', True, 'Missed'), ('TGDDEDGSTEEER', 23150, 'IDENTIFIED', True, 'Missed'), ('TGDDEDGSTEEER', 23243, 'IDENTIFIED', True, 'Missed'), ('TGDDEDGSTEEER', 23172, 'IDENTIFIED', True, 'Missed'), ('TGDDEDGSTEEER', 23148, 'IDENTIFIED', True, 'Missed'), ('TGDDEDGSTEEER', 23171, 'IDENTIFIED', True, 'Missed'), ('TGDDEDGSTEEER', 23187, 'IDENTIFIED', True, 'Missed'), ('TGDDEDGSTEEER', 23180, 'IDENTIFIED', True, 'Missed'), ('TGDDEDGSTEEER', 23118, 'IDENTIFIED', True, 'Missed'), ('TGDDEDGSTEEER', 23149, 'IDENTIFIED', True, 'Missed'), ('TGDDEDGSTEEER', 23126, 'IDENTIFIED', True, 'Missed'), ('TGDDEDGSTEEER', 23239, 'IDENTIFIED', True, 'Missed'), ('TGDDEDGSTEEER', 23157, 'IDENTIFIED', True, 'Missed'), ('TGDDEDGSTEEER', 23231, 'IDENTIFIED', True, 'Missed'), ('TGDDEDGSTEEER', 23201, 'IDENTIFIED', True, 'Missed'), ('TGDDEDGSTEEER', 23202, 'IDENTIFIED', True, 'Missed'), ('TGDDEDGSTEEER', 23221, 'IDENTIFIED', True, 'Missed'), ('TGDDEDGSTEEER', 23184, 'IDENTIFIED', True, 'Missed'), ('TGDDEDGSTEEER', 23173, 'IDENTIFIED', True, 'Missed'), ('TGDDEDGSTEEER', 23179, 'IDENTIFIED', True, 'Missed'), ('TGDDEDGSTEEER', 23200, 'IDENTIFIED', True, 'Missed'), ('TGDDEDGSTEEER', 23110, 'IDENTIFIED', True, 'Missed'), ('TGDDEDGSTEEER', 23175, 'IDENTIFIED', True, 'Missed'), ('TGDDEDGSTEEER', 23196, 'IDENTIFIED', True, 'Missed'), ('VLENCEDVADFDETFR', 23262, nan, True, 'Matched'), ('SLFAADSSGLSDPFAR', 23260, nan, True, 'Matched'), ('DLLFSIVEEETGKDCAK', 23254, nan, False, 'Matched'), ('WAILSDPDDISSGLK', 23264, nan, True, 'Matched'), ('VFTGPSEIEDENGQR', 23261, nan, True, 'Matched'), ('DLLFSIVEEETGK', 23253, nan, True, 'Matched'), ('VPLPEDVSR', 23263, nan, True, 'Matched'), ('YFASIDTMK', 23265, nan, True, 'Matched'), ('KGTAEEPEEEEPDESMLDWWSK', 23257, nan, False, 'Matched'), ('YLFPFDYLAAEEK', 23266, nan, True, 'Matched'), ('GTAEEPEEEEPDESMLDWWSK', 23248, nan, True, 'Matched'), ('GVQSSLIHNYK', 23255, nan, True, 'Matched'), ('AAQGLGLHAFPPVSLVYTK', 23252, nan, True, 'Matched'), ('NEPDPLEKPNRPDTSFIWFLNPLK', 23259, nan, True, 'Matched'), ('TGDDEDGSTEEER', 23091, nan, True, 'Matched'), ('TGDDEDGSTEEER', 23067, nan, True, 'Matched'), ('GTAEEPEEEEPDESMLDWWSK', 23249, nan, True, 'Matched'), ('TGDDEDGSTEEER', 23069, nan, True, 'Matched'), ('TGDDEDGSTEEER', 23117, nan, True, 'Matched'), ('TGDDEDGSTEEER', 23047, nan, True, 'Matched'), ('TGDDEDGSTEEER', 23101, nan, True, 'Matched'), ('TGDDEDGSTEEER', 23092, nan, True, 'Matched'), ('TGDDEDGSTEEER', 23114, nan, True, 'Matched'), ('TGDDEDGSTEEER', 23099, nan, True, 'Matched'), ('TGDDEDGSTEEER', 23040, nan, True, 'Matched'), ('TGDDEDGSTEEER', 23116, nan, True, 'Matched'), ('TGDDEDGSTEEER', 23068, nan, True, 'Matched'), ('TGDDEDGSTEEER', 23083, nan, True, 'Matched'), ('TGDDEDGSTEEER', 23235, nan, True, 'Matched'), ('TGDDEDGSTEEER', 23139, nan, True, 'Matched'), ('TGDDEDGSTEEER', 23079, nan, True, 'Matched'), ('TGDDEDGSTEEER', 23074, nan, True, 'Matched'), ('TGDDEDGSTEEER', 23029, nan, True, 'Matched'), ('TGDDEDGSTEEER', 23128, nan, True, 'Matched'), ('TGDDEDGSTEEER', 23182, nan, True, 'Matched'), ('TGDDEDGSTEEER', 23167, nan, True, 'Matched'), ('TGDDEDGSTEEER', 23073, nan, True, 'Matched'), ('TGDDEDGSTEEER', 23216, nan, True, 'Matched'), ('TGDDEDGSTEEER', 23065, nan, True, 'Matched'), ('TGDDEDGSTEEER', 23060, nan, True, 'Matched'), ('TGDDEDGSTEEER', 23119, nan, True, 'Matched'), ('TGDDEDGSTEEER', 23034, nan, True, 'Matched'), ('TGDDEDGSTEEER', 23147, nan, True, 'Matched'), ('TGDDEDGSTEEER', 23041, nan, True, 'Matched')] | I5: 16 | J5: =IFERROR(VLOOKUP(A5,dbg_proteins!$A$2:$A$20161,1,FALSE)," ---") -> Q9HC10
A6: O15492 | B6: 59 | C6: [('TCFDAAQGKTR', 2097, 'lost_3_aa_Nterm', True, 'Missed'), ('TCFDAAQGKTR', 2096, 'lost_3_aa_Nterm', True, 'Missed'), ('TCFDAAQGKTR', 2093, 'lost_3_aa_Nterm', True, 'Missed'), ('TCFDAAQGKTR', 2095, 'lost_3_aa_Nterm', True, 'Missed'), ('TCFDAAQGKTR', 2094, 'lost_3_aa_Nterm', True, 'Missed'), ('SELGCDTGSTGKFEWGSK', 2182, 'non_standard_modification', True, 'Missed'), ('TCFDAAQGKTR', 2091, 'non_standard_modification', True, 'Missed'), ('TCFDAAQGKTR', 2092, 'non_standard_modification', True, 'Missed'), ('TCFDAAQGKTR', 2098, 'lost_3_aa_Nterm', True, 'Missed'), ('TCFDAAQGKTR', 2099, 'lost_3_aa_Nterm', True, 'Missed'), ('TCFDAAQGKTR', 2105, 'lost_3_aa_Nterm', True, 'Missed'), ('TCFDAAQGKTR', 2106, 'lost_3_aa_Nterm', True, 'Missed'), ('KENRNFSEDVL', 2111, 'HLA1', True, 'Missed'), ('TCFDAAQGKTR', 2103, 'lost_3_aa_Nterm', True, 'Missed'), ('RAHQIFEEF', 2191, 'HLA1', True, 'Missed'), ('KENRNFSEDVL', 2110, 'HLA1', True, 'Missed'), ('KENRNFSEDVL', 2113, 'HLA1', True, 'Missed'), ('SELGCDTGSTGKFEWGSK', 2184, 'non_standard_modification', True, 'Missed'), ('KENRNFSEDVL', 2117, 'HLA1', True, 'Missed'), ('KENRNFSEDVL', 2116, 'HLA1', True, 'Missed'), ('TCFDAAQGKTR', 2102, 'lost_3_aa_Nterm', True, 'Missed'), ('KENRNFSEDVL', 2118, 'HLA1', True, 'Missed'), ('KENRNFSEDVL', 2119, 'HLA1', True, 'Missed'), ('KENRNFSEDVL', 2114, 'HLA1', True, 'Missed'), ('KENRNFSEDVL', 2120, 'HLA1', True, 'Missed'), ('TCFDAAQGKTR', 2100, 'lost_3_aa_Nterm', True, 'Missed'), ('KENRNFSEDVL', 2112, 'HLA1', True, 'Missed'), ('TCFDAAQGKTR', 2104, 'lost_3_aa_Nterm', True, 'Missed'), ('TCFDAAQGKTR', 2101, 'lost_3_aa_Nterm', True, 'Missed'), ('TCFDAAQGKTR', 2107, 'lost_3_aa_Nterm', True, 'Missed'), ('KENRNFSEDVL', 2115, 'HLA1', True, 'Missed'), ('SPAYRDLAAQASAAS', 2002, 'IDENTIFIED', False, 'Missed'), ('SPAYRDLAAQASAAS', 1986, 'IDENTIFIED', False, 'Missed'), ('SELGCDTGSTGKFEWGSK', 2183, 'non_standard_modification', True, 'Missed'), ('KENRNFSEDVL', 2109, 'HLA1', True, 'Missed'), ('KENRNFSEDVL', 2108, 'HLA1', True, 'Missed'), ('SPAYRDLAAQASAAS', 2036, 'IDENTIFIED', False, 'Missed'), ('KSPAYRDLAAQASAAS', 2133, 'IDENTIFIED', False, 'Missed'), ('KSPAYRDLAAQASAAS', 2132, 'IDENTIFIED', False, 'Missed'), ('SPAYRDLAAQASAAS', 2017, 'IDENTIFIED', False, 'Missed'), ('SPAYRDLAA', 2063, 'IDENTIFIED', True, 'Missed'), ('SPAYRDLAA', 2071, 'IDENTIFIED', True, 'Missed'), ('SPAYRDLAA', 2066, 'IDENTIFIED', True, 'Missed'), ('EFKKIRSATKLASRAHQ', 2181, 'HLA2', True, 'Missed'), ('SPAYRDLAAQASAAS', 2024, 'IDENTIFIED', False, 'Missed'), ('SPAYRDLAA', 2062, 'IDENTIFIED', True, 'Missed'), ('SPAYRDLAA', 2064, 'IDENTIFIED', True, 'Missed'), ('SPAYRDLAA', 2068, 'IDENTIFIED', True, 'Missed'), ('SPAYRDLAA', 2065, 'IDENTIFIED', True, 'Missed'), ('SPAYRDLAA', 2074, 'IDENTIFIED', True, 'Missed'), ('SPAYRDLAA', 2067, 'IDENTIFIED', True, 'Missed'), ('SPAYRDLAAQASAAS', 2019, 'IDENTIFIED', False, 'Missed'), ('SPAYRDLAA', 2069, 'IDENTIFIED', True, 'Missed'), ('SPAYRDLAA', 2061, 'IDENTIFIED', True, 'Missed'), ('SPAYRDLAA', 2070, 'IDENTIFIED', True, 'Missed'), ('SPAYRDLAA', 2073, 'IDENTIFIED', True, 'Missed'), ('SPAYRDLAA', 2072, 'IDENTIFIED', True, 'Missed'), ('DLAAQASAASATLSSCSLDEPSHT', 2172, 'non_standard_modification', True, 'Missed'), ('DLAAQASAASATLSSCSLDEPSHT', 2171, 'non_standard_modification', True, 'Missed')] | D6: 7 | E6: 167 | F6: [('STGKFEWGSK', 2187, nan, True, 'Matched'), ('STGKFEWGSK', 2186, nan, True, 'Matched'), ('KLASRAHQI', 2178, nan, True, 'Matched'), ('KLASRAHQI', 2177, nan, True, 'Matched'), ('SPAYRDLAAQASAAS', 1982, nan, False, 'Matched'), ('KLASRAHQI', 2175, nan, True, 'Matched'), ('SPAYRDLAA', 2077, nan, True, 'Matched'), ('KSPAYRDLAAQASAAS', 2123, nan, False, 'Matched'), ('SPAYRDLAA', 2076, nan, True, 'Matched'), ('SPAYRDLAA', 2089, nan, True, 'Matched'), ('SPAYRDLAA', 2081, nan, True, 'Matched'), ('SPAYRDLAA', 2080, nan, True, 'Matched'), ('SPAYRDLAA', 2075, nan, True, 'Matched'), ('SPAYRDLAAQASAAS', 2006, nan, False, 'Matched'), ('EEFKKIRSA', 2154, nan, True, 'Matched'), ('SPAYRDLAA', 2082, nan, True, 'Matched'), ('SPAYRDLAA', 2087, nan, True, 'Matched'), ('AAQGKTRTL', 2138, nan, True, 'Matched'), ('SPAYRDLAA', 2084, nan, True, 'Matched'), ('SPAYRDLAA', 2083, nan, True, 'Matched'), ('SPAYRDLAAQASAAS', 1980, nan, False, 'Matched'), ('SPAYRDLAA', 2085, nan, True, 'Matched'), ('SPAYRDLAAQASAAS', 1997, nan, False, 'Matched'), ('SPAYRDLAA', 2088, nan, True, 'Matched'), ('LAAFPTTCL', 2145, nan, True, 'Matched'), ('AAQGKTRTL', 2141, nan, True, 'Matched'), ('KSPAYRDLAAQASAAS', 2126, nan, False, 'Matched'), ('STGKFEWGSK', 2185, nan, True, 'Matched'), ('SPAYRDLAA', 2043, nan, True, 'Matched'), ('NGVAAFHAFLK', 2190, nan, True, 'Matched'), ('SPAYRDLAA', 2079, nan, True, 'Matched'), ('SPAYRDLAA', 2086, nan, True, 'Matched'), ('EEFKKIRSA', 2159, nan, True, 'Matched'), ('AAQGKTRTL', 2139, nan, True, 'Matched'), ('SPAYRDLAA', 2078, nan, True, 'Matched'), ('SPAYRDLAAQASAAS', 1995, nan, False, 'Matched'), ('SPAYRDLAA', 2052, nan, True, 'Matched'), ('LAAFPTTCL', 2144, nan, True, 'Matched'), ('SPAYRDLAAQASAAS', 2018, nan, False, 'Matched'), ('SPAYRDLAAQASAAS', 2005, nan, False, 'Matched'), ('SPAYRDLAA', 2058, nan, True, 'Matched'), ('EEFKKIRSA', 2157, nan, True, 'Matched'), ('SPAYRDLAAQASAAS', 1974, nan, False, 'Matched'), ('EEFKKIRSA', 2156, nan, True, 'Matched'), ('LAAFPTTCL', 2146, nan, True, 'Matched'), ('SPAYRDLAAQASAAS', 1965, nan, False, 'Matched'), ('SPAYRDLAAQASAAS', 1976, nan, False, 'Matched'), ('LAAFPTTCL', 2148, nan, True, 'Matched'), ('SPAYRDLAA', 2090, nan, True, 'Matched'), ('SPAYRDLAA', 2050, nan, True, 'Matched'), ('SPAYRDLAAQASAAS', 2000, nan, False, 'Matched'), ('SPAYRDLAA', 2044, nan, True, 'Matched'), ('SPAYRDLAAQASAAS', 1990, nan, False, 'Matched'), ('SPAYRDLAA', 2059, nan, True, 'Matched'), ('LAAFPTTCL', 2147, nan, True, 'Matched'), ('SPAYRDLAAQASAAS', 2010, nan, False, 'Matched'), ('SPAYRDLAA', 2060, nan, True, 'Matched'), ('SPAYRDLAAQASAAS', 2004, nan, False, 'Matched'), ('KLASRAHQI', 2176, nan, True, 'Matched'), ('SPAYRDLAA', 2056, nan, True, 'Matched'), ('SPAYRDLAA', 2042, nan, True, 'Matched'), ('KSPAYRDLAAQASAAS', 2122, nan, False, 'Matched'), ('KSPAYRDLAAQASAAS', 2127, nan, False, 'Matched'), ('SPAYRDLAAQASAAS', 1989, nan, False, 'Matched'), ('SPAYRDLAA', 2040, nan, True, 'Matched'), ('EEFKKIRSA', 2160, nan, True, 'Matched'), ('KSPAYRDLAAQASAAS', 2121, nan, False, 'Matched'), ('SPAYRDLAA', 2046, nan, True, 'Matched'), ('SPAYRDLAAQASAAS', 1973, nan, False, 'Matched'), ('KTRTLMEKDSY', 2170, nan, True, 'Matched'), ('SPAYRDLAA', 2041, nan, True, 'Matched'), ('SPAYRDLAA', 2054, nan, True, 'Matched'), ('EEFKKIRSA', 2158, nan, True, 'Matched'), ('SPAYRDLAA', 2048, nan, True, 'Matched'), ('SPAYRDLAA', 2045, nan, True, 'Matched'), ('KTRTLMEKDSY', 2168, nan, True, 'Matched'), ('EEFKKIRSA', 2162, nan, True, 'Matched'), ('SPAYRDLAA', 2039, nan, True, 'Matched'), ('SPAYRDLAA', 2049, nan, True, 'Matched'), ('SPAYRDLAAQASAAS', 2021, nan, False, 'Matched'), ('SPAYRDLAA', 2053, nan, True, 'Matched'), ('NFSEDVLGWR', 2189, nan, True, 'Matched'), ('KTRTLMEKDSY', 2167, nan, True, 'Matched'), ('SPAYRDLAAQASAAS', 2003, nan, False, 'Matched'), ('SPAYRDLAA', 2051, nan, True, 'Matched'), ('SPAYRDLAAQASAAS', 1991, nan, False, 'Matched'), ('KSPAYRDLAAQASAAS', 2125, nan, False, 'Matched'), ('SPAYRDLAA', 2047, nan, True, 'Matched'), ('KSPAYRDLAAQASAAS', 2128, nan, False, 'Matched'), ('SPAYRDLAA', 2057, nan, True, 'Matched'), ('SPAYRDLAAQASAAS', 1977, nan, False, 'Matched'), ('SPAYRDLAAQASAAS', 1978, nan, False, 'Matched'), ('SPAYRDLAAQASAAS', 1970, nan, False, 'Matched'), ('SPAYRDLAAQASAAS', 1994, nan, False, 'Matched'), ('SPAYRDLAAQASAAS', 2023, nan, False, 'Matched'), ('EEFKKIRSA', 2161, nan, True, 'Matched'), ('AHQIFEEFICSEAPK', 2163, nan, True, 'Matched'), ('SPAYRDLAAQASAAS', 1999, nan, False, 'Matched'), ('SPAYRDLAA', 2055, nan, True, 'Matched'), ('LAAFPTTCL', 2150, nan, True, 'Matched'), ('SPAYRDLAAQASAAS', 1972, nan, False, 'Matched'), ('SPAYRDLAAQASAAS', 1969, nan, False, 'Matched'), ('SPAYRDLAAQASAAS', 1983, nan, False, 'Matched'), ('SPAYRDLAAQASAAS', 1981, nan, False, 'Matched'), ('SPAYRDLAAQASAAS', 1966, nan, False, 'Matched'), ('SPAYRDLAAQASAAS', 1988, nan, False, 'Matched'), ('SPAYRDLAAQASAAS', 1985, nan, False, 'Matched'), ('KTRTLMEKDSY', 2165, nan, True, 'Matched'), ('SPAYRDLAAQASAAS', 2001, nan, False, 'Matched'), ('SPAYRDLAAQASAAS', 2014, nan, False, 'Matched'), ('SPAYRDLAAQASAAS', 1984, nan, False, 'Matched'), ('LAAFPTTCL', 2153, nan, True, 'Matched'), ('SPAYRDLAAQASAAS', 2030, nan, False, 'Matched'), ('SPAYRDLAAQASAAS', 1964, nan, False, 'Matched'), ('LAAFPTTCL', 2149, nan, True, 'Matched'), ('SPAYRDLAAQASAAS', 1968, nan, False, 'Matched'), ('LAAFPTTCL', 2152, nan, True, 'Matched'), ('SPAYRDLAAQASAAS', 2015, nan, False, 'Matched'), ('EEFKKIRSA', 2155, nan, True, 'Matched'), ('SPAYRDLAAQASAAS', 1971, nan, False, 'Matched'), ('SPAYRDLAAQASAAS', 2028, nan, False, 'Matched'), ('AAQGKTRTL', 2143, nan, True, 'Matched'), ('AAQGKTRTL', 2142, nan, True, 'Matched'), ('SPAYRDLAAQASAAS', 2011, nan, False, 'Matched'), ('AAQGKTRTL', 2140, nan, True, 'Matched'), ('KTRTLMEKDSY', 2169, nan, True, 'Matched'), ('KTRTLMEKDSY', 2166, nan, True, 'Matched'), ('SPAYRDLAAQASAAS', 2013, nan, False, 'Matched'), ('LAAFPTTCL', 2151, nan, True, 'Matched'), ('SPAYRDLAAQASAAS', 1962, nan, False, 'Matched'), ('KSPAYRDLAAQASAAS', 2129, nan, False, 'Matched'), ('SPAYRDLAAQASAAS', 1987, nan, False, 'Matched'), ('AAQGKTRTL', 2136, nan, True, 'Matched'), ('SPAYRDLAAQASAAS', 1967, nan, False, 'Matched'), ('SPAYRDLAAQASAAS', 2009, nan, False, 'Matched'), ('SPAYRDLAAQASAAS', 1993, nan, False, 'Matched'), ('SPAYRDLAAQASAAS', 2022, nan, False, 'Matched'), ('AAQGKTRTL', 2137, nan, True, 'Matched'), ('SPAYRDLAAQASAAS', 2025, nan, False, 'Matched'), ('SPAYRDLAAQASAAS', 1975, nan, False, 'Matched'), ('AAQGKTRTL', 2135, nan, True, 'Matched'), ('AAQGKTRTL', 2134, nan, True, 'Matched'), ('SPAYRDLAAQASAAS', 2008, nan, False, 'Matched'), ('SPAYRDLAAQASAAS', 2020, nan, False, 'Matched'), ('SPAYRDLAAQASAAS', 2012, nan, False, 'Matched'), ('KSPAYRDLAAQASAAS', 2124, nan, False, 'Matched'), ('SPAYRDLAAQASAAS', 1996, nan, False, 'Matched'), ('SPAYRDLAAQASAAS', 2029, nan, False, 'Matched'), ('SPAYRDLAAQASAAS', 2033, nan, False, 'Matched'), ('SPAYRDLAAQASAAS', 2016, nan, False, 'Matched'), ('SPAYRDLAAQASAAS', 2038, nan, False, 'Matched'), ('SPAYRDLAAQASAAS', 2007, nan, False, 'Matched'), ('SPAYRDLAAQASAAS', 2031, nan, False, 'Matched'), ('SPAYRDLAAQASAAS', 2034, nan, False, 'Matched'), ('SPAYRDLAAQASAAS', 2027, nan, False, 'Matched'), ('SPAYRDLAAQASAAS', 1963, nan, False, 'Matched'), ('SPAYRDLAAQASAAS', 1992, nan, False, 'Matched'), ('SPAYRDLAAQASAAS', 1979, nan, False, 'Matched'), ('SPAYRDLAAQASAAS', 2037, nan, False, 'Matched'), ('SPAYRDLAAQASAAS', 2026, nan, False, 'Matched'), ('SPAYRDLAAQASAAS', 2035, nan, False, 'Matched'), ('KKIRSATKLASRAHQ', 2188, nan, True, 'Matched'), ('KSPAYRDLAAQASAAS', 2131, nan, False, 'Matched'), ('SPAYRDLAAQASAAS', 2032, nan, False, 'Matched'), ('SPAYRDLAAQASAAS', 1998, nan, False, 'Matched'), ('DLAAQASAASATLSSCSLDEPSHT', 2173, nan, True, 'Matched'), ('DLAAQASAASATLSSCSLDEPSHT', 2174, nan, True, 'Matched')] | G6: 12 | H6: [('TCFDAAQGKTR', 2097, 'lost_3_aa_Nterm', True, 'Missed'), ('TCFDAAQGKTR', 2096, 'lost_3_aa_Nterm', True, 'Missed'), ('TCFDAAQGKTR', 2093, 'lost_3_aa_Nterm', True, 'Missed'), ('TCFDAAQGKTR', 2095, 'lost_3_aa_Nterm', True, 'Missed'), ('TCFDAAQGKTR', 2094, 'lost_3_aa_Nterm', True, 'Missed'), ('SELGCDTGSTGKFEWGSK', 2182, 'non_standard_modification', False, 'Missed'), ('TCFDAAQGKTR', 2091, 'non_standard_modification', True, 'Missed'), ('TCFDAAQGKTR', 2092, 'non_standard_modification', True, 'Missed'), ('TCFDAAQGKTR', 2098, 'lost_3_aa_Nterm', True, 'Missed'), ('TCFDAAQGKTR', 2099, 'lost_3_aa_Nterm', True, 'Missed'), ('TCFDAAQGKTR', 2105, 'lost_3_aa_Nterm', True, 'Missed'), ('TCFDAAQGKTR', 2106, 'lost_3_aa_Nterm', True, 'Missed'), ('KENRNFSEDVL', 2111, 'HLA1', True, 'Missed'), ('TCFDAAQGKTR', 2103, 'lost_3_aa_Nterm', True, 'Missed'), ('RAHQIFEEF', 2191, 'HLA1', True, 'Missed'), ('KENRNFSEDVL', 2110, 'HLA1', True, 'Missed'), ('KENRNFSEDVL', 2113, 'HLA1', True, 'Missed'), ('SELGCDTGSTGKFEWGSK', 2184, 'non_standard_modification', False, 'Missed'), ('KENRNFSEDVL', 2117, 'HLA1', True, 'Missed'), ('KENRNFSEDVL', 2116, 'HLA1', True, 'Missed'), ('TCFDAAQGKTR', 2102, 'lost_3_aa_Nterm', True, 'Missed'), ('KENRNFSEDVL', 2118, 'HLA1', True, 'Missed'), ('KENRNFSEDVL', 2119, 'HLA1', True, 'Missed'), ('KENRNFSEDVL', 2114, 'HLA1', True, 'Missed'), ('KENRNFSEDVL', 2120, 'HLA1', True, 'Missed'), ('TCFDAAQGKTR', 2100, 'lost_3_aa_Nterm', True, 'Missed'), ('KENRNFSEDVL', 2112, 'HLA1', True, 'Missed'), ('TCFDAAQGKTR', 2104, 'lost_3_aa_Nterm', True, 'Missed'), ('TCFDAAQGKTR', 2101, 'lost_3_aa_Nterm', True, 'Missed'), ('TCFDAAQGKTR', 2107, 'lost_3_aa_Nterm', True, 'Missed'), ('KENRNFSEDVL', 2115, 'HLA1', True, 'Missed'), ('SPAYRDLAAQASAAS', 2002, 'IDENTIFIED', False, 'Missed'), ('SPAYRDLAAQASAAS', 1986, 'IDENTIFIED', False, 'Missed'), ('SELGCDTGSTGKFEWGSK', 2183, 'non_standard_modification', False, 'Missed'), ('KENRNFSEDVL', 2109, 'HLA1', True, 'Missed'), ('KENRNFSEDVL', 2108, 'HLA1', True, 'Missed'), ('SPAYRDLAAQASAAS', 2036, 'IDENTIFIED', False, 'Missed'), ('KSPAYRDLAAQASAAS', 2133, 'IDENTIFIED', False, 'Missed'), ('KSPAYRDLAAQASAAS', 2132, 'IDENTIFIED', False, 'Missed'), ('SPAYRDLAAQASAAS', 2017, 'IDENTIFIED', False, 'Missed'), ('SPAYRDLAA', 2063, 'IDENTIFIED', True, 'Missed'), ('SPAYRDLAA', 2071, 'IDENTIFIED', True, 'Missed'), ('SPAYRDLAA', 2066, 'IDENTIFIED', True, 'Missed'), ('EFKKIRSATKLASRAHQ', 2181, 'HLA2', False, 'Missed'), ('SPAYRDLAAQASAAS', 2024, 'IDENTIFIED', False, 'Missed'), ('SPAYRDLAA', 2062, 'IDENTIFIED', True, 'Missed'), ('SPAYRDLAA', 2064, 'IDENTIFIED', True, 'Missed'), ('SPAYRDLAA', 2068, 'IDENTIFIED', True, 'Missed'), ('SPAYRDLAA', 2065, 'IDENTIFIED', True, 'Missed'), ('SPAYRDLAA', 2074, 'IDENTIFIED', True, 'Missed'), ('SPAYRDLAA', 2067, 'IDENTIFIED', True, 'Missed'), ('SPAYRDLAAQASAAS', 2019, 'IDENTIFIED', False, 'Missed'), ('SPAYRDLAA', 2069, 'IDENTIFIED', True, 'Missed'), ('SPAYRDLAA', 2061, 'IDENTIFIED', True, 'Missed'), ('SPAYRDLAA', 2070, 'IDENTIFIED', True, 'Missed'), ('SPAYRDLAA', 2073, 'IDENTIFIED', True, 'Missed'), ('SPAYRDLAA', 2072, 'IDENTIFIED', True, 'Missed'), ('DLAAQASAASATLSSCSLDEPSHT', 2172, 'non_standard_modification', True, 'Missed'), ('DLAAQASAASATLSSCSLDEPSHT', 2171, 'non_standard_modification', True, 'Missed'), ('STGKFEWGSK', 2187, nan, True, 'Matched'), ('STGKFEWGSK', 2186, nan, True, 'Matched'), ('KLASRAHQI', 2178, nan, True, 'Matched'), ('KLASRAHQI', 2177, nan, True, 'Matched'), ('SPAYRDLAAQASAAS', 1982, nan, False, 'Matched'), ('KLASRAHQI', 2175, nan, True, 'Matched'), ('SPAYRDLAA', 2077, nan, True, 'Matched'), ('KSPAYRDLAAQASAAS', 2123, nan, False, 'Matched'), ('SPAYRDLAA', 2076, nan, True, 'Matched'), ('SPAYRDLAA', 2089, nan, True, 'Matched'), ('SPAYRDLAA', 2081, nan, True, 'Matched'), ('SPAYRDLAA', 2080, nan, True, 'Matched'), ('SPAYRDLAA', 2075, nan, True, 'Matched'), ('SPAYRDLAAQASAAS', 2006, nan, False, 'Matched'), ('EEFKKIRSA', 2154, nan, True, 'Matched'), ('SPAYRDLAA', 2082, nan, True, 'Matched'), ('SPAYRDLAA', 2087, nan, True, 'Matched'), ('AAQGKTRTL', 2138, nan, True, 'Matched'), ('SPAYRDLAA', 2084, nan, True, 'Matched'), ('SPAYRDLAA', 2083, nan, True, 'Matched'), ('SPAYRDLAAQASAAS', 1980, nan, False, 'Matched'), ('SPAYRDLAA', 2085, nan, True, 'Matched'), ('SPAYRDLAAQASAAS', 1997, nan, False, 'Matched'), ('SPAYRDLAA', 2088, nan, True, 'Matched'), ('LAAFPTTCL', 2145, nan, True, 'Matched'), ('AAQGKTRTL', 2141, nan, True, 'Matched'), ('KSPAYRDLAAQASAAS', 2126, nan, False, 'Matched'), ('STGKFEWGSK', 2185, nan, True, 'Matched'), ('SPAYRDLAA', 2043, nan, True, 'Matched'), ('NGVAAFHAFLK', 2190, nan, True, 'Matched'), ('SPAYRDLAA', 2079, nan, True, 'Matched'), ('SPAYRDLAA', 2086, nan, True, 'Matched'), ('EEFKKIRSA', 2159, nan, True, 'Matched'), ('AAQGKTRTL', 2139, nan, True, 'Matched'), ('SPAYRDLAA', 2078, nan, True, 'Matched'), ('SPAYRDLAAQASAAS', 1995, nan, False, 'Matched'), ('SPAYRDLAA', 2052, nan, True, 'Matched'), ('LAAFPTTCL', 2144, nan, True, 'Matched'), ('SPAYRDLAAQASAAS', 2018, nan, False, 'Matched'), ('SPAYRDLAAQASAAS', 2005, nan, False, 'Matched'), ('SPAYRDLAA', 2058, nan, True, 'Matched'), ('EEFKKIRSA', 2157, nan, True, 'Matched'), ('SPAYRDLAAQASAAS', 1974, nan, False, 'Matched'), ('EEFKKIRSA', 2156, nan, True, 'Matched'), ('LAAFPTTCL', 2146, nan, True, 'Matched'), ('SPAYRDLAAQASAAS', 1965, nan, False, 'Matched'), ('SPAYRDLAAQASAAS', 1976, nan, False, 'Matched'), ('LAAFPTTCL', 2148, nan, True, 'Matched'), ('SPAYRDLAA', 2090, nan, True, 'Matched'), ('SPAYRDLAA', 2050, nan, True, 'Matched'), ('SPAYRDLAAQASAAS', 2000, nan, False, 'Matched'), ('SPAYRDLAA', 2044, nan, True, 'Matched'), ('SPAYRDLAAQASAAS', 1990, nan, False, 'Matched'), ('SPAYRDLAA', 2059, nan, True, 'Matched'), ('LAAFPTTCL', 2147, nan, True, 'Matched'), ('SPAYRDLAAQASAAS', 2010, nan, False, 'Matched'), ('SPAYRDLAA', 2060, nan, True, 'Matched'), ('SPAYRDLAAQASAAS', 2004, nan, False, 'Matched'), ('KLASRAHQI', 2176, nan, True, 'Matched'), ('SPAYRDLAA', 2056, nan, True, 'Matched'), ('SPAYRDLAA', 2042, nan, True, 'Matched'), ('KSPAYRDLAAQASAAS', 2122, nan, False, 'Matched'), ('KSPAYRDLAAQASAAS', 2127, nan, False, 'Matched'), ('SPAYRDLAAQASAAS', 1989, nan, False, 'Matched'), ('SPAYRDLAA', 2040, nan, True, 'Matched'), ('EEFKKIRSA', 2160, nan, True, 'Matched'), ('KSPAYRDLAAQASAAS', 2121, nan, False, 'Matched'), ('SPAYRDLAA', 2046, nan, True, 'Matched'), ('SPAYRDLAAQASAAS', 1973, nan, False, 'Matched'), ('KTRTLMEKDSY', 2170, nan, True, 'Matched'), ('SPAYRDLAA', 2041, nan, True, 'Matched'), ('SPAYRDLAA', 2054, nan, True, 'Matched'), ('EEFKKIRSA', 2158, nan, True, 'Matched'), ('SPAYRDLAA', 2048, nan, True, 'Matched'), ('SPAYRDLAA', 2045, nan, True, 'Matched'), ('KTRTLMEKDSY', 2168, nan, True, 'Matched'), ('EEFKKIRSA', 2162, nan, True, 'Matched'), ('SPAYRDLAA', 2039, nan, True, 'Matched'), ('SPAYRDLAA', 2049, nan, True, 'Matched'), ('SPAYRDLAAQASAAS', 2021, nan, False, 'Matched'), ('SPAYRDLAA', 2053, nan, True, 'Matched'), ('NFSEDVLGWR', 2189, nan, True, 'Matched'), ('KTRTLMEKDSY', 2167, nan, True, 'Matched'), ('SPAYRDLAAQASAAS', 2003, nan, False, 'Matched'), ('SPAYRDLAA', 2051, nan, True, 'Matched'), ('SPAYRDLAAQASAAS', 1991, nan, False, 'Matched'), ('KSPAYRDLAAQASAAS', 2125, nan, False, 'Matched'), ('SPAYRDLAA', 2047, nan, True, 'Matched'), ('KSPAYRDLAAQASAAS', 2128, nan, False, 'Matched'), ('SPAYRDLAA', 2057, nan, True, 'Matched'), ('SPAYRDLAAQASAAS', 1977, nan, False, 'Matched'), ('SPAYRDLAAQASAAS', 1978, nan, False, 'Matched'), ('SPAYRDLAAQASAAS', 1970, nan, False, 'Matched'), ('SPAYRDLAAQASAAS', 1994, nan, False, 'Matched'), ('SPAYRDLAAQASAAS', 2023, nan, False, 'Matched'), ('EEFKKIRSA', 2161, nan, True, 'Matched'), ('AHQIFEEFICSEAPK', 2163, nan, True, 'Matched'), ('SPAYRDLAAQASAAS', 1999, nan, False, 'Matched'), ('SPAYRDLAA', 2055, nan, True, 'Matched'), ('LAAFPTTCL', 2150, nan, True, 'Matched'), ('SPAYRDLAAQASAAS', 1972, nan, False, 'Matched'), ('SPAYRDLAAQASAAS', 1969, nan, False, 'Matched'), ('SPAYRDLAAQASAAS', 1983, nan, False, 'Matched'), ('SPAYRDLAAQASAAS', 1981, nan, False, 'Matched'), ('SPAYRDLAAQASAAS', 1966, nan, False, 'Matched'), ('SPAYRDLAAQASAAS', 1988, nan, False, 'Matched'), ('SPAYRDLAAQASAAS', 1985, nan, False, 'Matched'), ('KTRTLMEKDSY', 2165, nan, True, 'Matched'), ('SPAYRDLAAQASAAS', 2001, nan, False, 'Matched'), ('SPAYRDLAAQASAAS', 2014, nan, False, 'Matched'), ('SPAYRDLAAQASAAS', 1984, nan, False, 'Matched'), ('LAAFPTTCL', 2153, nan, True, 'Matched'), ('SPAYRDLAAQASAAS', 2030, nan, False, 'Matched'), ('SPAYRDLAAQASAAS', 1964, nan, False, 'Matched'), ('LAAFPTTCL', 2149, nan, True, 'Matched'), ('SPAYRDLAAQASAAS', 1968, nan, False, 'Matched'), ('LAAFPTTCL', 2152, nan, True, 'Matched'), ('SPAYRDLAAQASAAS', 2015, nan, False, 'Matched'), ('EEFKKIRSA', 2155, nan, True, 'Matched'), ('SPAYRDLAAQASAAS', 1971, nan, False, 'Matched'), ('SPAYRDLAAQASAAS', 2028, nan, False, 'Matched'), ('AAQGKTRTL', 2143, nan, True, 'Matched'), ('AAQGKTRTL', 2142, nan, True, 'Matched'), ('SPAYRDLAAQASAAS', 2011, nan, False, 'Matched'), ('AAQGKTRTL', 2140, nan, True, 'Matched'), ('KTRTLMEKDSY', 2169, nan, True, 'Matched'), ('KTRTLMEKDSY', 2166, nan, True, 'Matched'), ('SPAYRDLAAQASAAS', 2013, nan, False, 'Matched'), ('LAAFPTTCL', 2151, nan, True, 'Matched'), ('SPAYRDLAAQASAAS', 1962, nan, False, 'Matched'), ('KSPAYRDLAAQASAAS', 2129, nan, False, 'Matched'), ('SPAYRDLAAQASAAS', 1987, nan, False, 'Matched'), ('AAQGKTRTL', 2136, nan, True, 'Matched'), ('SPAYRDLAAQASAAS', 1967, nan, False, 'Matched'), ('SPAYRDLAAQASAAS', 2009, nan, False, 'Matched'), ('SPAYRDLAAQASAAS', 1993, nan, False, 'Matched'), ('SPAYRDLAAQASAAS', 2022, nan, False, 'Matched'), ('AAQGKTRTL', 2137, nan, True, 'Matched'), ('SPAYRDLAAQASAAS', 2025, nan, False, 'Matched'), ('SPAYRDLAAQASAAS', 1975, nan, False, 'Matched'), ('AAQGKTRTL', 2135, nan, True, 'Matched'), ('AAQGKTRTL', 2134, nan, True, 'Matched'), ('SPAYRDLAAQASAAS', 2008, nan, False, 'Matched'), ('SPAYRDLAAQASAAS', 2020, nan, False, 'Matched'), ('SPAYRDLAAQASAAS', 2012, nan, False, 'Matched'), ('KSPAYRDLAAQASAAS', 2124, nan, False, 'Matched'), ('SPAYRDLAAQASAAS', 1996, nan, False, 'Matched'), ('SPAYRDLAAQASAAS', 2029, nan, False, 'Matched'), ('SPAYRDLAAQASAAS', 2033, nan, False, 'Matched'), ('SPAYRDLAAQASAAS', 2016, nan, False, 'Matched'), ('SPAYRDLAAQASAAS', 2038, nan, False, 'Matched'), ('SPAYRDLAAQASAAS', 2007, nan, False, 'Matched'), ('SPAYRDLAAQASAAS', 2031, nan, False, 'Matched'), ('SPAYRDLAAQASAAS', 2034, nan, False, 'Matched'), ('SPAYRDLAAQASAAS', 2027, nan, False, 'Matched'), ('SPAYRDLAAQASAAS', 1963, nan, False, 'Matched'), ('SPAYRDLAAQASAAS', 1992, nan, False, 'Matched'), ('SPAYRDLAAQASAAS', 1979, nan, False, 'Matched'), ('SPAYRDLAAQASAAS', 2037, nan, False, 'Matched'), ('SPAYRDLAAQASAAS', 2026, nan, False, 'Matched'), ('SPAYRDLAAQASAAS', 2035, nan, False, 'Matched'), ('KKIRSATKLASRAHQ', 2188, nan, True, 'Matched'), ('KSPAYRDLAAQASAAS', 2131, nan, False, 'Matched'), ('SPAYRDLAAQASAAS', 2032, nan, False, 'Matched'), ('SPAYRDLAAQASAAS', 1998, nan, False, 'Matched'), ('DLAAQASAASATLSSCSLDEPSHT', 2173, nan, True, 'Matched'), ('DLAAQASAASATLSSCSLDEPSHT', 2174, nan, True, 'Matched')] | I6: 15 | J6: =IFERROR(VLOOKUP(A6,dbg_proteins!$A$2:$A$20161,1,FALSE)," ---") -> O15492
A7: Q9UK05 | B7: 18 | C7: [('GCDTLDISVPPGSR', 24817, 'non_standard_modification', True, 'Missed'), ('HTFNLKMFLENVKVD', 24797, 'IDENTIFIED', True, 'Missed'), ('GSAGGNAHSPLGVPGGGLPEHTFNLK', 24675, 'IDENTIFIED', True, 'Missed'), ('GSAGGNAHSPLGVPGGGLPEHTFNLK', 24677, 'IDENTIFIED', True, 'Missed'), ('GSAGGNAHSPLGVPGGGLPEHTFNLK', 24678, 'IDENTIFIED', True, 'Missed'), ('DGSTEAGESSHEEDTDGHVAAGSTLA', 24839, 'Others', True, 'Missed'), ('DGSTEAGESSHEEDTDGHVAAGSTLA', 24838, 'Others', True, 'Missed'), ('HTFNLKMFLENVKVD', 24805, 'IDENTIFIED', True, 'Missed'), ('GCDTLDISVPPGSR', 24816, 'non_standard_modification', True, 'Missed'), ('GSAGGNAHSPLGVPGGGLPEHTFNLK', 24669, 'IDENTIFIED', True, 'Missed'), ('DGSTEAGESSHEEDTDGHVAAGSTLA', 24837, 'Others', True, 'Missed'), ('DGSTEAGESSHEEDTDGHVAAGSTLA', 24836, 'Others', True, 'Missed'), ('HTFNLKMFLENVKVD', 24807, 'IDENTIFIED', True, 'Missed'), ('LYVSCQNHVDPSHDLK', 24726, 'non_standard_modification', True, 'Missed'), ('GSAGGNAHSPLGVPGGGLPEHTFNLK', 24674, 'IDENTIFIED', True, 'Missed'), ('GSAGGNAHSPLGVPGGGLPEHTFNLK', 24686, 'IDENTIFIED', True, 'Missed'), ('GSAGGNAHSPLGVPGGGLPEHTFNLK', 24685, 'IDENTIFIED', True, 'Missed'), ('GSAGGNAHSPLGVPGGGLPEHTFNLK', 24684, 'IDENTIFIED', True, 'Missed')] | D7: 5 | E7: 183 | F7: [('VEPPQYMIDLYNR', 24768, nan, True, 'Matched'), ('VEPPQYMIDLYNR', 24767, nan, True, 'Matched'), ('VEPPQYMIDLYNR', 24766, nan, True, 'Matched'), ('VEPPQYMIDLYNR', 24765, nan, True, 'Matched'), ('EMISHEQESVLK', 24690, nan, True, 'Matched'), ('LSPISVLYK', 24854, nan, True, 'Matched'), ('TRVEPPQYMIDLYNR', 24848, nan, False, 'Matched'), ('LSPISVLYK', 24853, nan, True, 'Matched'), ('YHYEGMSVAECGCR', 24850, nan, True, 'Matched'), ('GCDTLDISVPPGSR', 24818, nan, True, 'Matched'), ('GCDTLDISVPPGSR', 24820, nan, True, 'Matched'), ('GCDTLDISVPPGSR', 24823, nan, True, 'Matched'), ('GCDTLDISVPPGSR', 24822, nan, True, 'Matched'), ('YHYEGMSVAECGCR', 24849, nan, True, 'Matched'), ('LPEHTFNLKMFLENVKVD', 24697, nan, False, 'Matched'), ('TRVEPPQYMIDLYNR', 24846, nan, False, 'Matched'), ('VEPPQYMIDLYNR', 24740, nan, True, 'Matched'), ('LPEHTFNLKMFLENVKVD', 24703, nan, False, 'Matched'), ('TRVEPPQYMIDLYNR', 24847, nan, False, 'Matched'), ('VEPPQYMIDLYNR', 24742, nan, True, 'Matched'), ('VEPPQYMIDLYNR', 24741, nan, True, 'Matched'), ('DDMGVPTLK', 24834, nan, True, 'Matched'), ('LPEHTFNLKMFLENVKVD', 24702, nan, False, 'Matched'), ('LPEHTFNLKMFLENVKVD', 24707, nan, False, 'Matched'), ('EMISHEQESVLK', 24691, nan, True, 'Matched'), ('VEPPQYMIDLYNR', 24747, nan, True, 'Matched'), ('LPEHTFNLKMFLENVKVD', 24699, nan, False, 'Matched'), ('LPEHTFNLKMFLENVKVD', 24700, nan, False, 'Matched'), ('GSAGGNAHSPLGVPGGGLPEHTFNLK', 24670, nan, True, 'Matched'), ('EMISHEQESVLK', 24689, nan, True, 'Matched'), ('LPEHTFNLKMFLENVKVD', 24712, nan, False, 'Matched'), ('VEPPQYMIDLYNR', 24749, nan, True, 'Matched'), ('VEPPQYMIDLYNR', 24748, nan, True, 'Matched'), ('VEPPQYMIDLYNR', 24744, nan, True, 'Matched'), ('VEPPQYMIDLYNR', 24743, nan, True, 'Matched'), ('GCDTLDISVPPGSR', 24821, nan, True, 'Matched'), ('LPEHTFNLKMFLENVKVD', 24710, nan, False, 'Matched'), ('EMISHEQESVLK', 24688, nan, True, 'Matched'), ('DDMGVPTLK', 24828, nan, True, 'Matched'), ('DDMGVPTLK', 24827, nan, True, 'Matched'), ('VEPPQYMIDLYNR', 24746, nan, True, 'Matched'), ('VEPPQYMIDLYNR', 24745, nan, True, 'Matched'), ('VEPPQYMIDLYNR', 24762, nan, True, 'Matched'), ('VEPPQYMIDLYNR', 24761, nan, True, 'Matched'), ('EMISHEQESVLK', 24692, nan, True, 'Matched'), ('HTFNLKMFLENVKVD', 24795, nan, True, 'Matched'), ('YTSDKSTTPASNIVR', 24815, nan, True, 'Matched'), ('LPEHTFNLKMFLENVKVD', 24698, nan, False, 'Matched'), ('GGCFFPLADDVTPTK', 24769, nan, True, 'Matched'), ('GSVVIYDVLDGTDAWDSATETK', 24656, nan, True, 'Matched'), ('GSVVIYDVLDGTDAWDSATETK', 24655, nan, True, 'Matched'), ('VEPPQYMIDLYNR', 24754, nan, True, 'Matched'), ('VEPPQYMIDLYNR', 24753, nan, True, 'Matched'), ('LYVSCQNHVDPSHDLK', 24728, nan, True, 'Matched'), ('LPEHTFNLKMFLENVKVD', 24709, nan, False, 'Matched'), ('DDMGVPTLK', 24832, nan, True, 'Matched'), ('DDMGVPTLK', 24831, nan, True, 'Matched'), ('LPEHTFNLKMFLENVKVD', 24701, nan, False, 'Matched'), ('VEPPQYMIDLYNR', 24752, nan, True, 'Matched'), ('VEPPQYMIDLYNR', 24751, nan, True, 'Matched'), ('VEPPQYMIDLYNR', 24750, nan, True, 'Matched'), ('DDMGVPTLK', 24833, nan, True, 'Matched'), ('GGCFFPLADDVTPTK', 24780, nan, True, 'Matched'), ('GCDTLDISVPPGSR', 24825, nan, True, 'Matched'), ('GCDTLDISVPPGSR', 24824, nan, True, 'Matched'), ('DDMGVPTLK', 24830, nan, True, 'Matched'), ('DDMGVPTLK', 24829, nan, True, 'Matched'), ('GSVVIYDVLDGTDAWDSATETK', 24658, nan, True, 'Matched'), ('GSVVIYDVLDGTDAWDSATETK', 24657, nan, True, 'Matched'), ('GSAGGNAHSPLGVPGGGLPEHTFNLK', 24673, nan, True, 'Matched'), ('GGCFFPLADDVTPTK', 24770, nan, True, 'Matched'), ('LPEHTFNLKMFLENVKVD', 24704, nan, False, 'Matched'), ('GGCFFPLADDVTPTK', 24792, nan, True, 'Matched'), ('GGCFFPLADDVTPTK', 24791, nan, True, 'Matched'), ('GGCFFPLADDVTPTK', 24788, nan, True, 'Matched'), ('GGCFFPLADDVTPTK', 24787, nan, True, 'Matched'), ('HTFNLKMFLENVKVD', 24794, nan, True, 'Matched'), ('LPEHTFNLKMFLENVKVD', 24705, nan, False, 'Matched'), ('VEPPQYMIDLYNR', 24764, nan, True, 'Matched'), ('VEPPQYMIDLYNR', 24763, nan, True, 'Matched'), ('GGCFFPLADDVTPTK', 24784, nan, True, 'Matched'), ('GGCFFPLADDVTPTK', 24783, nan, True, 'Matched'), ('GSAGGNAHSPLGVPGGGLPEHTFNLK', 24668, nan, True, 'Matched'), ('NKLEVTVESHR', 24835, nan, True, 'Matched'), ('GGCFFPLADDVTPTK', 24776, nan, True, 'Matched'), ('GGCFFPLADDVTPTK', 24782, nan, True, 'Matched'), ('GGCFFPLADDVTPTK', 24781, nan, True, 'Matched'), ('HTFNLKMFLENVKVD', 24799, nan, True, 'Matched'), ('LPEHTFNLKMFLENVKVD', 24715, nan, False, 'Matched'), ('LPEHTFNLKMFLENVKVD', 24714, nan, False, 'Matched'), ('GGCFFPLADDVTPTK', 24778, nan, True, 'Matched'), ('GGCFFPLADDVTPTK', 24777, nan, True, 'Matched'), ('LPEHTFNLKMFLENVKVD', 24708, nan, False, 'Matched'), ('GSAGGNAHSPLGVPGGGLPEHTFNLK', 24667, nan, True, 'Matched'), ('GSAGGNAHSPLGVPGGGLPEHTFNLK', 24676, nan, True, 'Matched'), ('LPEHTFNLKMFLENVKVD', 24721, nan, False, 'Matched'), ('GSAGGNAHSPLGVPGGGLPEHTFNLK', 24682, nan, True, 'Matched'), ('GGCFFPLADDVTPTK', 24786, nan, True, 'Matched'), ('GGCFFPLADDVTPTK', 24785, nan, True, 'Matched'), ('LPEHTFNLKMFLENVKVD', 24717, nan, False, 'Matched'), ('VEPPQYMIDLYNR', 24760, nan, True, 'Matched'), ('VEPPQYMIDLYNR', 24759, nan, True, 'Matched'), ('GSAGGNAHSPLGVPGGGLPEHTFNLK', 24680, nan, True, 'Matched'), ('HTFNLKMFLENVKVD', 24802, nan, True, 'Matched'), ('LPEHTFNLKMFLENVKVD', 24716, nan, False, 'Matched'), ('GSAGGNAHSPLGVPGGGLPEHTFNLK', 24662, nan, True, 'Matched'), ('LYVSCQNHVDPSHDLK', 24734, nan, True, 'Matched'), ('HTFNLKMFLENVKVD', 24796, nan, True, 'Matched'), ('LPEHTFNLKMFLENVKVD', 24718, nan, False, 'Matched'), ('GSAGGNAHSPLGVPGGGLPEHTFNLK', 24679, nan, True, 'Matched'), ('LPEHTFNLKMFLENVKVD', 24720, nan, False, 'Matched'), ('HTFNLKMFLENVKVD', 24814, nan, True, 'Matched'), ('LPEHTFNLKMFLENVKVD', 24719, nan, False, 'Matched'), ('HTFNLKMFLENVKVD', 24801, nan, True, 'Matched'), ('HTFNLKMFLENVKVD', 24800, nan, True, 'Matched'), ('HTFNLKMFLENVKVD', 24798, nan, True, 'Matched'), ('GGCFFPLADDVTPTK', 24774, nan, True, 'Matched'), ('GGCFFPLADDVTPTK', 24773, nan, True, 'Matched'), ('GSAGGNAHSPLGVPGGGLPEHTFNLK', 24663, nan, True, 'Matched'), ('GGCFFPLADDVTPTK', 24775, nan, True, 'Matched'), ('HTFNLKMFLENVKVD', 24806, nan, True, 'Matched'), ('LYVSCQNHVDPSHDLK', 24732, nan, True, 'Matched'), ('GSVVIYDVLDGTDAWDSATETK', 24659, nan, True, 'Matched'), ('DDMGVPTLK', 24826, nan, True, 'Matched'), ('HTFNLKMFLENVKVD', 24804, nan, True, 'Matched'), ('GSAGGNAHSPLGVPGGGLPEHTFNLK', 24660, nan, True, 'Matched'), ('LYVSCQNHVDPSHDLK', 24733, nan, True, 'Matched'), ('LPEHTFNLKMFLENVKVD', 24693, nan, False, 'Matched'), ('GSAGGNAHSPLGVPGGGLPEHTFNLK', 24687, nan, True, 'Matched'), ('GCDTLDISVPPGSR', 24819, nan, True, 'Matched'), ('LPEHTFNLKMFLENVKVD', 24723, nan, False, 'Matched'), ('HTFNLKMFLENVKVD', 24813, nan, True, 'Matched'), ('GSAGGNAHSPLGVPGGGLPEHTFNLK', 24683, nan, True, 'Matched'), ('LYVSCQNHVDPSHDLK', 24731, nan, True, 'Matched'), ('GSAGGNAHSPLGVPGGGLPEHTFNLK', 24672, nan, True, 'Matched'), ('LYVSCQNHVDPSHDLK', 24739, nan, True, 'Matched'), ('GLPEHTFNLKMFLENVKVD', 24852, nan, False, 'Matched'), ('GSAGGNAHSPLGVPGGGLPEHTFNLK', 24664, nan, True, 'Matched'), ('GGCFFPLADDVTPTK', 24779, nan, True, 'Matched'), ('LYVSCQNHVDPSHDLK', 24736, nan, True, 'Matched'), ('GSAGGNAHSPLGVPGGGLPEHTFNLK', 24666, nan, True, 'Matched'), ('HTFNLKMFLENVKVD', 24808, nan, True, 'Matched'), ('LPEHTFNLKMFLENVKVD', 24722, nan, False, 'Matched'), ('LPEHTFNLKMFLENVKVD', 24695, nan, False, 'Matched'), ('VEPPQYMIDLYNR', 24756, nan, True, 'Matched'), ('LYVSCQNHVDPSHDLK', 24735, nan, True, 'Matched'), ('VPGGGLPEHTFNLKMFLENVKVD', 24840, nan, False, 'Matched'), ('GGCFFPLADDVTPTK', 24772, nan, True, 'Matched'), ('LYVSCQNHVDPSHDLK', 24738, nan, True, 'Matched'), ('LPEHTFNLKMFLENVKVD', 24713, nan, False, 'Matched'), ('LPEHTFNLKMFLENVKVD', 24724, nan, False, 'Matched'), ('LPEHTFNLKMFLENVKVD', 24696, nan, False, 'Matched'), ('VPGGGLPEHTFNLKMFLENVKVD', 24841, nan, False, 'Matched'), ('LYVSCQNHVDPSHDLK', 24727, nan, True, 'Matched'), ('HTFNLKMFLENVKVD', 24812, nan, True, 'Matched'), ('LPEHTFNLKMFLENVKVD', 24711, nan, False, 'Matched'), ('VPGGGLPEHTFNLKMFLENVKVD', 24843, nan, False, 'Matched'), ('LYVSCQNHVDPSHDLK', 24730, nan, True, 'Matched'), ('LPEHTFNLKMFLENVKVD', 24725, nan, False, 'Matched'), ('HTFNLKMFLENVKVD', 24809, nan, True, 'Matched'), ('GSAGGNAHSPLGVPGGGLPEHTFNLK', 24671, nan, True, 'Matched'), ('LYVSCQNHVDPSHDLK', 24737, nan, True, 'Matched'), ('GGCFFPLADDVTPTK', 24771, nan, True, 'Matched'), ('VPGGGLPEHTFNLKMFLENVKVD', 24844, nan, False, 'Matched'), ('GSAGGNAHSPLGVPGGGLPEHTFNLK', 24661, nan, True, 'Matched'), ('GSAGGNAHSPLGVPGGGLPEHTFNLK', 24681, nan, True, 'Matched'), ('LPEHTFNLKMFLENVKVD', 24694, nan, False, 'Matched'), ('LYVSCQNHVDPSHDLK', 24729, nan, True, 'Matched'), ('GSAGGNAHSPLGVPGGGLPEHTFNLK', 24665, nan, True, 'Matched'), ('HTFNLKMFLENVKVD', 24811, nan, True, 'Matched'), ('TRVEPPQYMIDLYNR', 24845, nan, False, 'Matched'), ('HTFNLKMFLENVKVD', 24810, nan, True, 'Matched'), ('GLPEHTFNLKMFLENVKVD', 24851, nan, False, 'Matched'), ('VEPPQYMIDLYNR', 24758, nan, True, 'Matched'), ('VEPPQYMIDLYNR', 24757, nan, True, 'Matched'), ('VPGGGLPEHTFNLKMFLENVKVD', 24842, nan, False, 'Matched'), ('GGCFFPLADDVTPTK', 24790, nan, True, 'Matched'), ('GGCFFPLADDVTPTK', 24789, nan, True, 'Matched'), ('GGCFFPLADDVTPTK', 24793, nan, True, 'Matched'), ('VEPPQYMIDLYNR', 24755, nan, True, 'Matched'), ('VPSQDKTRVEPPQYMIDLYNR', 24855, nan, False, 'Matched'), ('LPEHTFNLKMFLENVKVD', 24706, nan, False, 'Matched'), ('HTFNLKMFLENVKVD', 24803, nan, True, 'Matched')] | G7: 13 | H7: [('GCDTLDISVPPGSR', 24817, 'non_standard_modification', True, 'Missed'), ('HTFNLKMFLENVKVD', 24797, 'IDENTIFIED', True, 'Missed'), ('GSAGGNAHSPLGVPGGGLPEHTFNLK', 24675, 'IDENTIFIED', True, 'Missed'), ('GSAGGNAHSPLGVPGGGLPEHTFNLK', 24677, 'IDENTIFIED', True, 'Missed'), ('GSAGGNAHSPLGVPGGGLPEHTFNLK', 24678, 'IDENTIFIED', True, 'Missed'), ('DGSTEAGESSHEEDTDGHVAAGSTLA', 24839, 'Others', True, 'Missed'), ('DGSTEAGESSHEEDTDGHVAAGSTLA', 24838, 'Others', True, 'Missed'), ('HTFNLKMFLENVKVD', 24805, 'IDENTIFIED', True, 'Missed'), ('GCDTLDISVPPGSR', 24816, 'non_standard_modification', True, 'Missed'), ('GSAGGNAHSPLGVPGGGLPEHTFNLK', 24669, 'IDENTIFIED', True, 'Missed'), ('DGSTEAGESSHEEDTDGHVAAGSTLA', 24837, 'Others', True, 'Missed'), ('DGSTEAGESSHEEDTDGHVAAGSTLA', 24836, 'Others', True, 'Missed'), ('HTFNLKMFLENVKVD', 24807, 'IDENTIFIED', True, 'Missed'), ('LYVSCQNHVDPSHDLK', 24726, 'non_standard_modification', True, 'Missed'), ('GSAGGNAHSPLGVPGGGLPEHTFNLK', 24674, 'IDENTIFIED', True, 'Missed'), ('GSAGGNAHSPLGVPGGGLPEHTFNLK', 24686, 'IDENTIFIED', True, 'Missed'), ('GSAGGNAHSPLGVPGGGLPEHTFNLK', 24685, 'IDENTIFIED', True, 'Missed'), ('GSAGGNAHSPLGVPGGGLPEHTFNLK', 24684, 'IDENTIFIED', True, 'Missed'), ('VEPPQYMIDLYNR', 24768, nan, True, 'Matched'), ('VEPPQYMIDLYNR', 24767, nan, True, 'Matched'), ('VEPPQYMIDLYNR', 24766, nan, True, 'Matched'), ('VEPPQYMIDLYNR', 24765, nan, True, 'Matched'), ('EMISHEQESVLK', 24690, nan, True, 'Matched'), ('LSPISVLYK', 24854, nan, True, 'Matched'), ('TRVEPPQYMIDLYNR', 24848, nan, False, 'Matched'), ('LSPISVLYK', 24853, nan, True, 'Matched'), ('YHYEGMSVAECGCR', 24850, nan, True, 'Matched'), ('GCDTLDISVPPGSR', 24818, nan, True, 'Matched'), ('GCDTLDISVPPGSR', 24820, nan, True, 'Matched'), ('GCDTLDISVPPGSR', 24823, nan, True, 'Matched'), ('GCDTLDISVPPGSR', 24822, nan, True, 'Matched'), ('YHYEGMSVAECGCR', 24849, nan, True, 'Matched'), ('LPEHTFNLKMFLENVKVD', 24697, nan, False, 'Matched'), ('TRVEPPQYMIDLYNR', 24846, nan, False, 'Matched'), ('VEPPQYMIDLYNR', 24740, nan, True, 'Matched'), ('LPEHTFNLKMFLENVKVD', 24703, nan, False, 'Matched'), ('TRVEPPQYMIDLYNR', 24847, nan, False, 'Matched'), ('VEPPQYMIDLYNR', 24742, nan, True, 'Matched'), ('VEPPQYMIDLYNR', 24741, nan, True, 'Matched'), ('DDMGVPTLK', 24834, nan, True, 'Matched'), ('LPEHTFNLKMFLENVKVD', 24702, nan, False, 'Matched'), ('LPEHTFNLKMFLENVKVD', 24707, nan, False, 'Matched'), ('EMISHEQESVLK', 24691, nan, True, 'Matched'), ('VEPPQYMIDLYNR', 24747, nan, True, 'Matched'), ('LPEHTFNLKMFLENVKVD', 24699, nan, False, 'Matched'), ('LPEHTFNLKMFLENVKVD', 24700, nan, False, 'Matched'), ('GSAGGNAHSPLGVPGGGLPEHTFNLK', 24670, nan, True, 'Matched'), ('EMISHEQESVLK', 24689, nan, True, 'Matched'), ('LPEHTFNLKMFLENVKVD', 24712, nan, False, 'Matched'), ('VEPPQYMIDLYNR', 24749, nan, True, 'Matched'), ('VEPPQYMIDLYNR', 24748, nan, True, 'Matched'), ('VEPPQYMIDLYNR', 24744, nan, True, 'Matched'), ('VEPPQYMIDLYNR', 24743, nan, True, 'Matched'), ('GCDTLDISVPPGSR', 24821, nan, True, 'Matched'), ('LPEHTFNLKMFLENVKVD', 24710, nan, False, 'Matched'), ('EMISHEQESVLK', 24688, nan, True, 'Matched'), ('DDMGVPTLK', 24828, nan, True, 'Matched'), ('DDMGVPTLK', 24827, nan, True, 'Matched'), ('VEPPQYMIDLYNR', 24746, nan, True, 'Matched'), ('VEPPQYMIDLYNR', 24745, nan, True, 'Matched'), ('VEPPQYMIDLYNR', 24762, nan, True, 'Matched'), ('VEPPQYMIDLYNR', 24761, nan, True, 'Matched'), ('EMISHEQESVLK', 24692, nan, True, 'Matched'), ('HTFNLKMFLENVKVD', 24795, nan, True, 'Matched'), ('YTSDKSTTPASNIVR', 24815, nan, True, 'Matched'), ('LPEHTFNLKMFLENVKVD', 24698, nan, False, 'Matched'), ('GGCFFPLADDVTPTK', 24769, nan, True, 'Matched'), ('GSVVIYDVLDGTDAWDSATETK', 24656, nan, True, 'Matched'), ('GSVVIYDVLDGTDAWDSATETK', 24655, nan, True, 'Matched'), ('VEPPQYMIDLYNR', 24754, nan, True, 'Matched'), ('VEPPQYMIDLYNR', 24753, nan, True, 'Matched'), ('LYVSCQNHVDPSHDLK', 24728, nan, True, 'Matched'), ('LPEHTFNLKMFLENVKVD', 24709, nan, False, 'Matched'), ('DDMGVPTLK', 24832, nan, True, 'Matched'), ('DDMGVPTLK', 24831, nan, True, 'Matched'), ('LPEHTFNLKMFLENVKVD', 24701, nan, False, 'Matched'), ('VEPPQYMIDLYNR', 24752, nan, True, 'Matched'), ('VEPPQYMIDLYNR', 24751, nan, True, 'Matched'), ('VEPPQYMIDLYNR', 24750, nan, True, 'Matched'), ('DDMGVPTLK', 24833, nan, True, 'Matched'), ('GGCFFPLADDVTPTK', 24780, nan, True, 'Matched'), ('GCDTLDISVPPGSR', 24825, nan, True, 'Matched'), ('GCDTLDISVPPGSR', 24824, nan, True, 'Matched'), ('DDMGVPTLK', 24830, nan, True, 'Matched'), ('DDMGVPTLK', 24829, nan, True, 'Matched'), ('GSVVIYDVLDGTDAWDSATETK', 24658, nan, True, 'Matched'), ('GSVVIYDVLDGTDAWDSATETK', 24657, nan, True, 'Matched'), ('GSAGGNAHSPLGVPGGGLPEHTFNLK', 24673, nan, True, 'Matched'), ('GGCFFPLADDVTPTK', 24770, nan, True, 'Matched'), ('LPEHTFNLKMFLENVKVD', 24704, nan, False, 'Matched'), ('GGCFFPLADDVTPTK', 24792, nan, True, 'Matched'), ('GGCFFPLADDVTPTK', 24791, nan, True, 'Matched'), ('GGCFFPLADDVTPTK', 24788, nan, True, 'Matched'), ('GGCFFPLADDVTPTK', 24787, nan, True, 'Matched'), ('HTFNLKMFLENVKVD', 24794, nan, True, 'Matched'), ('LPEHTFNLKMFLENVKVD', 24705, nan, False, 'Matched'), ('VEPPQYMIDLYNR', 24764, nan, True, 'Matched'), ('VEPPQYMIDLYNR', 24763, nan, True, 'Matched'), ('GGCFFPLADDVTPTK', 24784, nan, True, 'Matched'), ('GGCFFPLADDVTPTK', 24783, nan, True, 'Matched'), ('GSAGGNAHSPLGVPGGGLPEHTFNLK', 24668, nan, True, 'Matched'), ('NKLEVTVESHR', 24835, nan, True, 'Matched'), ('GGCFFPLADDVTPTK', 24776, nan, True, 'Matched'), ('GGCFFPLADDVTPTK', 24782, nan, True, 'Matched'), ('GGCFFPLADDVTPTK', 24781, nan, True, 'Matched'), ('HTFNLKMFLENVKVD', 24799, nan, True, 'Matched'), ('LPEHTFNLKMFLENVKVD', 24715, nan, False, 'Matched'), ('LPEHTFNLKMFLENVKVD', 24714, nan, False, 'Matched'), ('GGCFFPLADDVTPTK', 24778, nan, True, 'Matched'), ('GGCFFPLADDVTPTK', 24777, nan, True, 'Matched'), ('LPEHTFNLKMFLENVKVD', 24708, nan, False, 'Matched'), ('GSAGGNAHSPLGVPGGGLPEHTFNLK', 24667, nan, True, 'Matched'), ('GSAGGNAHSPLGVPGGGLPEHTFNLK', 24676, nan, True, 'Matched'), ('LPEHTFNLKMFLENVKVD', 24721, nan, False, 'Matched'), ('GSAGGNAHSPLGVPGGGLPEHTFNLK', 24682, nan, True, 'Matched'), ('GGCFFPLADDVTPTK', 24786, nan, True, 'Matched'), ('GGCFFPLADDVTPTK', 24785, nan, True, 'Matched'), ('LPEHTFNLKMFLENVKVD', 24717, nan, False, 'Matched'), ('VEPPQYMIDLYNR', 24760, nan, True, 'Matched'), ('VEPPQYMIDLYNR', 24759, nan, True, 'Matched'), ('GSAGGNAHSPLGVPGGGLPEHTFNLK', 24680, nan, True, 'Matched'), ('HTFNLKMFLENVKVD', 24802, nan, True, 'Matched'), ('LPEHTFNLKMFLENVKVD', 24716, nan, False, 'Matched'), ('GSAGGNAHSPLGVPGGGLPEHTFNLK', 24662, nan, True, 'Matched'), ('LYVSCQNHVDPSHDLK', 24734, nan, True, 'Matched'), ('HTFNLKMFLENVKVD', 24796, nan, True, 'Matched'), ('LPEHTFNLKMFLENVKVD', 24718, nan, False, 'Matched'), ('GSAGGNAHSPLGVPGGGLPEHTFNLK', 24679, nan, True, 'Matched'), ('LPEHTFNLKMFLENVKVD', 24720, nan, False, 'Matched'), ('HTFNLKMFLENVKVD', 24814, nan, True, 'Matched'), ('LPEHTFNLKMFLENVKVD', 24719, nan, False, 'Matched'), ('HTFNLKMFLENVKVD', 24801, nan, True, 'Matched'), ('HTFNLKMFLENVKVD', 24800, nan, True, 'Matched'), ('HTFNLKMFLENVKVD', 24798, nan, True, 'Matched'), ('GGCFFPLADDVTPTK', 24774, nan, True, 'Matched'), ('GGCFFPLADDVTPTK', 24773, nan, True, 'Matched'), ('GSAGGNAHSPLGVPGGGLPEHTFNLK', 24663, nan, True, 'Matched'), ('GGCFFPLADDVTPTK', 24775, nan, True, 'Matched'), ('HTFNLKMFLENVKVD', 24806, nan, True, 'Matched'), ('LYVSCQNHVDPSHDLK', 24732, nan, True, 'Matched'), ('GSVVIYDVLDGTDAWDSATETK', 24659, nan, True, 'Matched'), ('DDMGVPTLK', 24826, nan, True, 'Matched'), ('HTFNLKMFLENVKVD', 24804, nan, True, 'Matched'), ('GSAGGNAHSPLGVPGGGLPEHTFNLK', 24660, nan, True, 'Matched'), ('LYVSCQNHVDPSHDLK', 24733, nan, True, 'Matched'), ('LPEHTFNLKMFLENVKVD', 24693, nan, False, 'Matched'), ('GSAGGNAHSPLGVPGGGLPEHTFNLK', 24687, nan, True, 'Matched'), ('GCDTLDISVPPGSR', 24819, nan, True, 'Matched'), ('LPEHTFNLKMFLENVKVD', 24723, nan, False, 'Matched'), ('HTFNLKMFLENVKVD', 24813, nan, True, 'Matched'), ('GSAGGNAHSPLGVPGGGLPEHTFNLK', 24683, nan, True, 'Matched'), ('LYVSCQNHVDPSHDLK', 24731, nan, True, 'Matched'), ('GSAGGNAHSPLGVPGGGLPEHTFNLK', 24672, nan, True, 'Matched'), ('LYVSCQNHVDPSHDLK', 24739, nan, True, 'Matched'), ('GLPEHTFNLKMFLENVKVD', 24852, nan, False, 'Matched'), ('GSAGGNAHSPLGVPGGGLPEHTFNLK', 24664, nan, True, 'Matched'), ('GGCFFPLADDVTPTK', 24779, nan, True, 'Matched'), ('LYVSCQNHVDPSHDLK', 24736, nan, True, 'Matched'), ('GSAGGNAHSPLGVPGGGLPEHTFNLK', 24666, nan, True, 'Matched'), ('HTFNLKMFLENVKVD', 24808, nan, True, 'Matched'), ('LPEHTFNLKMFLENVKVD', 24722, nan, False, 'Matched'), ('LPEHTFNLKMFLENVKVD', 24695, nan, False, 'Matched'), ('VEPPQYMIDLYNR', 24756, nan, True, 'Matched'), ('LYVSCQNHVDPSHDLK', 24735, nan, True, 'Matched'), ('VPGGGLPEHTFNLKMFLENVKVD', 24840, nan, False, 'Matched'), ('GGCFFPLADDVTPTK', 24772, nan, True, 'Matched'), ('LYVSCQNHVDPSHDLK', 24738, nan, True, 'Matched'), ('LPEHTFNLKMFLENVKVD', 24713, nan, False, 'Matched'), ('LPEHTFNLKMFLENVKVD', 24724, nan, False, 'Matched'), ('LPEHTFNLKMFLENVKVD', 24696, nan, False, 'Matched'), ('VPGGGLPEHTFNLKMFLENVKVD', 24841, nan, False, 'Matched'), ('LYVSCQNHVDPSHDLK', 24727, nan, True, 'Matched'), ('HTFNLKMFLENVKVD', 24812, nan, True, 'Matched'), ('LPEHTFNLKMFLENVKVD', 24711, nan, False, 'Matched'), ('VPGGGLPEHTFNLKMFLENVKVD', 24843, nan, False, 'Matched'), ('LYVSCQNHVDPSHDLK', 24730, nan, True, 'Matched'), ('LPEHTFNLKMFLENVKVD', 24725, nan, False, 'Matched'), ('HTFNLKMFLENVKVD', 24809, nan, True, 'Matched'), ('GSAGGNAHSPLGVPGGGLPEHTFNLK', 24671, nan, True, 'Matched'), ('LYVSCQNHVDPSHDLK', 24737, nan, True, 'Matched'), ('GGCFFPLADDVTPTK', 24771, nan, True, 'Matched'), ('VPGGGLPEHTFNLKMFLENVKVD', 24844, nan, False, 'Matched'), ('GSAGGNAHSPLGVPGGGLPEHTFNLK', 24661, nan, True, 'Matched'), ('GSAGGNAHSPLGVPGGGLPEHTFNLK', 24681, nan, True, 'Matched'), ('LPEHTFNLKMFLENVKVD', 24694, nan, False, 'Matched'), ('LYVSCQNHVDPSHDLK', 24729, nan, True, 'Matched'), ('GSAGGNAHSPLGVPGGGLPEHTFNLK', 24665, nan, True, 'Matched'), ('HTFNLKMFLENVKVD', 24811, nan, True, 'Matched'), ('TRVEPPQYMIDLYNR', 24845, nan, False, 'Matched'), ('HTFNLKMFLENVKVD', 24810, nan, True, 'Matched'), ('GLPEHTFNLKMFLENVKVD', 24851, nan, False, 'Matched'), ('VEPPQYMIDLYNR', 24758, nan, True, 'Matched'), ('VEPPQYMIDLYNR', 24757, nan, True, 'Matched'), ('VPGGGLPEHTFNLKMFLENVKVD', 24842, nan, False, 'Matched'), ('GGCFFPLADDVTPTK', 24790, nan, True, 'Matched'), ('GGCFFPLADDVTPTK', 24789, nan, True, 'Matched'), ('GGCFFPLADDVTPTK', 24793, nan, True, 'Matched'), ('VEPPQYMIDLYNR', 24755, nan, True, 'Matched'), ('VPSQDKTRVEPPQYMIDLYNR', 24855, nan, False, 'Matched'), ('LPEHTFNLKMFLENVKVD', 24706, nan, False, 'Matched'), ('HTFNLKMFLENVKVD', 24803, nan, True, 'Matched')] | I7: 14 | J7: =IFERROR(VLOOKUP(A7,dbg_proteins!$A$2:$A$20161,1,FALSE)," ---") -> Q9UK05
A8: Q9Y2Y4 | B8: 29 | C8: [('RALGVQSLEEACW', 26173, 'HLA2', True, 'Missed'), ('RALGVQSLEEACW', 26172, 'HLA2', True, 'Missed'), ('RALGVQSLEEACW', 26174, 'HLA2', True, 'Missed'), ('KRFSLKHQM', 26109, 'IDENTIFIED', True, 'Missed'), ('KRFSLKHQM', 26117, 'IDENTIFIED', True, 'Missed'), ('KRFSLKHQM', 26115, 'IDENTIFIED', True, 'Missed'), ('SPYGSDRLVQL', 26071, 'IDENTIFIED', True, 'Missed'), ('RLQAPVGQRGADGK', 26178, 'regular_tryptic', True, 'Missed'), ('SPYGSDRLVQL', 26062, 'IDENTIFIED', True, 'Missed'), ('SPYGSDRLVQL', 26056, 'IDENTIFIED', True, 'Missed'), ('SPYGSDRLVQL', 26066, 'IDENTIFIED', True, 'Missed'), ('SPYGSDRLVQL', 26069, 'IDENTIFIED', True, 'Missed'), ('SPYGSDRLVQL', 26068, 'IDENTIFIED', True, 'Missed'), ('SPYGSDRLVQL', 26059, 'IDENTIFIED', True, 'Missed'), ('SPYGSDRLVQL', 26073, 'IDENTIFIED', True, 'Missed'), ('SPYGSDRLVQL', 26063, 'IDENTIFIED', True, 'Missed'), ('SPYGSDRLVQL', 26061, 'IDENTIFIED', True, 'Missed'), ('SPYGSDRLVQL', 26060, 'IDENTIFIED', True, 'Missed'), ('SPYGSDRLVQL', 26065, 'IDENTIFIED', True, 'Missed'), ('KRFSLKHQMETHY', 26128, 'IDENTIFIED', False, 'Missed'), ('KRFSLKHQMETHY', 26127, 'IDENTIFIED', False, 'Missed'), ('FVYGESVEL', 26027, 'IDENTIFIED', True, 'Missed'), ('SPYGSDRLVQL', 26057, 'IDENTIFIED', True, 'Missed'), ('SPYGSDRLVQL', 26072, 'IDENTIFIED', True, 'Missed'), ('SPYGSDRLVQL', 26074, 'IDENTIFIED', True, 'Missed'), ('ALGVQSLEEACWR', 26153, 'non_standard_modification', True, 'Missed'), ('SPYGSDRLVQL', 26070, 'IDENTIFIED', True, 'Missed'), ('SPYGSDRLVQL', 26058, 'IDENTIFIED', True, 'Missed'), ('PSRPSTSPCCPSSSTT', 26175, 'non_standard_modification', True, 'Missed')] | D8: 7 | E8: 114 | F8: [('CSLCGAGCPSLASMQAH', 26177, nan, True, 'Matched'), ('RLQAPVGQR', 26140, nan, True, 'Matched'), ('ALGVQSLEEACWR', 26155, nan, True, 'Matched'), ('RLQAPVGQR', 26139, nan, True, 'Matched'), ('KRLQAPVGQR', 26079, nan, False, 'Matched'), ('ALGVQSLEEACWR', 26152, nan, True, 'Matched'), ('APKGLWSQNQL', 26135, nan, True, 'Matched'), ('RLQAPVGQR', 26137, nan, True, 'Matched'), ('SPYGSDRLVQL', 26075, nan, True, 'Matched'), ('RLQAPVGQR', 26138, nan, True, 'Matched'), ('ALGVQSLEEACWR', 26156, nan, True, 'Matched'), ('SPYGSDRLVQL', 26076, nan, True, 'Matched'), ('RENPGGSEESL', 26097, nan, True, 'Matched'), ('RENPGGSEESL', 26096, nan, True, 'Matched'), ('RENPGGSEESL', 26102, nan, True, 'Matched'), ('APKGLWSQNQL', 26133, nan, True, 'Matched'), ('APKGLWSQNQL', 26136, nan, True, 'Matched'), ('RENPGGSEESL', 26099, nan, True, 'Matched'), ('RENPGGSEESL', 26100, nan, True, 'Matched'), ('RLQAPVGQR', 26141, nan, True, 'Matched'), ('RENPGGSEESL', 26098, nan, True, 'Matched'), ('SPYGSDRLVQL', 26078, nan, True, 'Matched'), ('RENPGGSEESL', 26101, nan, True, 'Matched'), ('RENPGGSEESL', 26093, nan, True, 'Matched'), ('APKGLWSQNQL', 26134, nan, True, 'Matched'), ('RLQAPVGQR', 26143, nan, True, 'Matched'), ('RENPGGSEESL', 26094, nan, True, 'Matched'), ('RENPGGSEESL', 26095, nan, True, 'Matched'), ('RENPGGSEESL', 26106, nan, True, 'Matched'), ('RENPGGSEESL', 26105, nan, True, 'Matched'), ('RLQAPVGQR', 26142, nan, True, 'Matched'), ('RENPGGSEESL', 26104, nan, True, 'Matched'), ('RLQAPVGQR', 26144, nan, True, 'Matched'), ('APKGLWSQNQL', 26131, nan, True, 'Matched'), ('FVYGESVEL', 26022, nan, True, 'Matched'), ('RENPGGSEESL', 26103, nan, True, 'Matched'), ('GRPEMAGATQEAQQEQTR', 26035, nan, True, 'Matched'), ('KRLQAPVGQR', 26088, nan, False, 'Matched'), ('KRLQAPVGQR', 26080, nan, False, 'Matched'), ('KRLQAPVGQR', 26084, nan, False, 'Matched'), ('HQMETHYRV', 26169, nan, True, 'Matched'), ('SPYGSDRLVQL', 26055, nan, True, 'Matched'), ('FVYGESVEL', 26024, nan, True, 'Matched'), ('KRLQAPVGQR', 26091, nan, False, 'Matched'), ('KRLQAPVGQR', 26085, nan, False, 'Matched'), ('GRPEMAGATQEAQQEQTR', 26030, nan, True, 'Matched'), ('FVYGESVEL', 26006, nan, True, 'Matched'), ('FVYGESVEL', 26008, nan, True, 'Matched'), ('FVYGESVEL', 26009, nan, True, 'Matched'), ('FVYGESVEL', 26019, nan, True, 'Matched'), ('FVYGESVEL', 26003, nan, True, 'Matched'), ('FVYGESVEL', 25999, nan, True, 'Matched'), ('KRLQAPVGQR', 26081, nan, False, 'Matched'), ('KRFSLKHQM', 26108, nan, True, 'Matched'), ('KRLQAPVGQR', 26092, nan, False, 'Matched'), ('FVYGESVEL', 25998, nan, True, 'Matched'), ('FVYGESVEL', 26018, nan, True, 'Matched'), ('KRFSLKHQM', 26107, nan, True, 'Matched'), ('HQMETHYRV', 26167, nan, True, 'Matched'), ('FVYGESVEL', 26005, nan, True, 'Matched'), ('FVYGESVEL', 26012, nan, True, 'Matched'), ('GRPEMAGATQEAQQEQTR', 26031, nan, True, 'Matched'), ('FVYGESVEL', 26004, nan, True, 'Matched'), ('FVYGESVEL', 26007, nan, True, 'Matched'), ('KRLQAPVGQR', 26083, nan, False, 'Matched'), ('FVYGESVEL', 26015, nan, True, 'Matched'), ('FVYGESVEL', 26016, nan, True, 'Matched'), ('APKGLWSQNQL', 26132, nan, True, 'Matched'), ('FVYGESVEL', 26011, nan, True, 'Matched'), ('KRLQAPVGQR', 26082, nan, False, 'Matched'), ('FVYGESVEL', 26013, nan, True, 'Matched'), ('FVYGESVEL', 26017, nan, True, 'Matched'), ('KRLQAPVGQR', 26089, nan, False, 'Matched'), ('FVYGESVEL', 26025, nan, True, 'Matched'), ('FVYGESVEL', 26010, nan, True, 'Matched'), ('KRFSLKHQM', 26113, nan, True, 'Matched'), ('APKGLWSQNQL', 26130, nan, True, 'Matched'), ('FVYGESVEL', 25997, nan, True, 'Matched'), ('KRLQAPVGQR', 26086, nan, False, 'Matched'), ('APKGLWSQNQL', 26129, nan, True, 'Matched'), ('FVYGESVEL', 26002, nan, True, 'Matched'), ('KRLQAPVGQR', 26087, nan, False, 'Matched'), ('FVYGESVEL', 26001, nan, True, 'Matched'), ('KRFSLKHQM', 26114, nan, True, 'Matched'), ('KRLQAPVGQR', 26090, nan, False, 'Matched'), ('HQMETHYRV', 26170, nan, True, 'Matched'), ('KRFSLKHQMETHY', 26122, nan, False, 'Matched'), ('FVYGESVEL', 26020, nan, True, 'Matched'), ('KRFSLKHQM', 26111, nan, True, 'Matched'), ('FVYGESVEL', 26000, nan, True, 'Matched'), ('SPSTFAQLLNFVYG', 26179, nan, True, 'Matched'), ('FVYGESVEL', 26021, nan, True, 'Matched'), ('KRFSLKHQMETHY', 26123, nan, False, 'Matched'), ('KRFSLKHQMETHY', 26120, nan, False, 'Matched'), ('KRFSLKHQMETHY', 26125, nan, False, 'Matched'), ('SPYGSDRLVQL', 26077, nan, True, 'Matched'), ('FVYGESVEL', 26014, nan, True, 'Matched'), ('KRFSLKHQMETHY', 26126, nan, False, 'Matched'), ('FVYGESVEL', 26023, nan, True, 'Matched'), ('HQMETHYRV', 26171, nan, True, 'Matched'), ('AEAPWLVGGQPALW', 26158, nan, True, 'Matched'), ('AEAPWLVGGQPALW', 26159, nan, True, 'Matched'), ('KRFSLKHQMETHY', 26124, nan, False, 'Matched'), ('KRFSLKHQM', 26112, nan, True, 'Matched'), ('KRFSLKHQMETHY', 26121, nan, False, 'Matched'), ('AEAPWLVGGQPALW', 26160, nan, True, 'Matched'), ('HQMETHYRV', 26168, nan, True, 'Matched'), ('AEAPWLVGGQPALW', 26161, nan, True, 'Matched'), ('FVYGESVEL', 26026, nan, True, 'Matched'), ('KRFSLKHQMETHY', 26119, nan, False, 'Matched'), ('FVYGESVEL', 26028, nan, True, 'Matched'), ('AEAPWLVGGQPALW', 26157, nan, True, 'Matched'), ('ALGVQSLEEACWR', 26154, nan, True, 'Matched'), ('PSRPSTSPCCPSSSTT', 26176, nan, True, 'Matched')] | G8: 13 | H8: [('RALGVQSLEEACW', 26173, 'HLA2', True, 'Missed'), ('RALGVQSLEEACW', 26172, 'HLA2', True, 'Missed'), ('RALGVQSLEEACW', 26174, 'HLA2', True, 'Missed'), ('KRFSLKHQM', 26109, 'IDENTIFIED', True, 'Missed'), ('KRFSLKHQM', 26117, 'IDENTIFIED', True, 'Missed'), ('KRFSLKHQM', 26115, 'IDENTIFIED', True, 'Missed'), ('SPYGSDRLVQL', 26071, 'IDENTIFIED', True, 'Missed'), ('RLQAPVGQRGADGK', 26178, 'regular_tryptic', False, 'Missed'), ('SPYGSDRLVQL', 26062, 'IDENTIFIED', True, 'Missed'), ('SPYGSDRLVQL', 26056, 'IDENTIFIED', True, 'Missed'), ('SPYGSDRLVQL', 26066, 'IDENTIFIED', True, 'Missed'), ('SPYGSDRLVQL', 26069, 'IDENTIFIED', True, 'Missed'), ('SPYGSDRLVQL', 26068, 'IDENTIFIED', True, 'Missed'), ('SPYGSDRLVQL', 26059, 'IDENTIFIED', True, 'Missed'), ('SPYGSDRLVQL', 26073, 'IDENTIFIED', True, 'Missed'), ('SPYGSDRLVQL', 26063, 'IDENTIFIED', True, 'Missed'), ('SPYGSDRLVQL', 26061, 'IDENTIFIED', True, 'Missed'), ('SPYGSDRLVQL', 26060, 'IDENTIFIED', True, 'Missed'), ('SPYGSDRLVQL', 26065, 'IDENTIFIED', True, 'Missed'), ('KRFSLKHQMETHY', 26128, 'IDENTIFIED', False, 'Missed'), ('KRFSLKHQMETHY', 26127, 'IDENTIFIED', False, 'Missed'), ('FVYGESVEL', 26027, 'IDENTIFIED', True, 'Missed'), ('SPYGSDRLVQL', 26057, 'IDENTIFIED', True, 'Missed'), ('SPYGSDRLVQL', 26072, 'IDENTIFIED', True, 'Missed'), ('SPYGSDRLVQL', 26074, 'IDENTIFIED', True, 'Missed'), ('ALGVQSLEEACWR', 26153, 'non_standard_modification', True, 'Missed'), ('SPYGSDRLVQL', 26070, 'IDENTIFIED', True, 'Missed'), ('SPYGSDRLVQL', 26058, 'IDENTIFIED', True, 'Missed'), ('PSRPSTSPCCPSSSTT', 26175, 'non_standard_modification', True, 'Missed'), ('CSLCGAGCPSLASMQAH', 26177, nan, True, 'Matched'), ('RLQAPVGQR', 26140, nan, True, 'Matched'), ('ALGVQSLEEACWR', 26155, nan, True, 'Matched'), ('RLQAPVGQR', 26139, nan, True, 'Matched'), ('KRLQAPVGQR', 26079, nan, False, 'Matched'), ('ALGVQSLEEACWR', 26152, nan, True, 'Matched'), ('APKGLWSQNQL', 26135, nan, True, 'Matched'), ('RLQAPVGQR', 26137, nan, True, 'Matched'), ('SPYGSDRLVQL', 26075, nan, True, 'Matched'), ('RLQAPVGQR', 26138, nan, True, 'Matched'), ('ALGVQSLEEACWR', 26156, nan, True, 'Matched'), ('SPYGSDRLVQL', 26076, nan, True, 'Matched'), ('RENPGGSEESL', 26097, nan, True, 'Matched'), ('RENPGGSEESL', 26096, nan, True, 'Matched'), ('RENPGGSEESL', 26102, nan, True, 'Matched'), ('APKGLWSQNQL', 26133, nan, True, 'Matched'), ('APKGLWSQNQL', 26136, nan, True, 'Matched'), ('RENPGGSEESL', 26099, nan, True, 'Matched'), ('RENPGGSEESL', 26100, nan, True, 'Matched'), ('RLQAPVGQR', 26141, nan, True, 'Matched'), ('RENPGGSEESL', 26098, nan, True, 'Matched'), ('SPYGSDRLVQL', 26078, nan, True, 'Matched'), ('RENPGGSEESL', 26101, nan, True, 'Matched'), ('RENPGGSEESL', 26093, nan, True, 'Matched'), ('APKGLWSQNQL', 26134, nan, True, 'Matched'), ('RLQAPVGQR', 26143, nan, True, 'Matched'), ('RENPGGSEESL', 26094, nan, True, 'Matched'), ('RENPGGSEESL', 26095, nan, True, 'Matched'), ('RENPGGSEESL', 26106, nan, True, 'Matched'), ('RENPGGSEESL', 26105, nan, True, 'Matched'), ('RLQAPVGQR', 26142, nan, True, 'Matched'), ('RENPGGSEESL', 26104, nan, True, 'Matched'), ('RLQAPVGQR', 26144, nan, True, 'Matched'), ('APKGLWSQNQL', 26131, nan, True, 'Matched'), ('FVYGESVEL', 26022, nan, True, 'Matched'), ('RENPGGSEESL', 26103, nan, True, 'Matched'), ('GRPEMAGATQEAQQEQTR', 26035, nan, True, 'Matched'), ('KRLQAPVGQR', 26088, nan, False, 'Matched'), ('KRLQAPVGQR', 26080, nan, False, 'Matched'), ('KRLQAPVGQR', 26084, nan, False, 'Matched'), ('HQMETHYRV', 26169, nan, True, 'Matched'), ('SPYGSDRLVQL', 26055, nan, True, 'Matched'), ('FVYGESVEL', 26024, nan, True, 'Matched'), ('KRLQAPVGQR', 26091, nan, False, 'Matched'), ('KRLQAPVGQR', 26085, nan, False, 'Matched'), ('GRPEMAGATQEAQQEQTR', 26030, nan, True, 'Matched'), ('FVYGESVEL', 26006, nan, True, 'Matched'), ('FVYGESVEL', 26008, nan, True, 'Matched'), ('FVYGESVEL', 26009, nan, True, 'Matched'), ('FVYGESVEL', 26019, nan, True, 'Matched'), ('FVYGESVEL', 26003, nan, True, 'Matched'), ('FVYGESVEL', 25999, nan, True, 'Matched'), ('KRLQAPVGQR', 26081, nan, False, 'Matched'), ('KRFSLKHQM', 26108, nan, True, 'Matched'), ('KRLQAPVGQR', 26092, nan, False, 'Matched'), ('FVYGESVEL', 25998, nan, True, 'Matched'), ('FVYGESVEL', 26018, nan, True, 'Matched'), ('KRFSLKHQM', 26107, nan, True, 'Matched'), ('HQMETHYRV', 26167, nan, True, 'Matched'), ('FVYGESVEL', 26005, nan, True, 'Matched'), ('FVYGESVEL', 26012, nan, True, 'Matched'), ('GRPEMAGATQEAQQEQTR', 26031, nan, True, 'Matched'), ('FVYGESVEL', 26004, nan, True, 'Matched'), ('FVYGESVEL', 26007, nan, True, 'Matched'), ('KRLQAPVGQR', 26083, nan, False, 'Matched'), ('FVYGESVEL', 26015, nan, True, 'Matched'), ('FVYGESVEL', 26016, nan, True, 'Matched'), ('APKGLWSQNQL', 26132, nan, True, 'Matched'), ('FVYGESVEL', 26011, nan, True, 'Matched'), ('KRLQAPVGQR', 26082, nan, False, 'Matched'), ('FVYGESVEL', 26013, nan, True, 'Matched'), ('FVYGESVEL', 26017, nan, True, 'Matched'), ('KRLQAPVGQR', 26089, nan, False, 'Matched'), ('FVYGESVEL', 26025, nan, True, 'Matched'), ('FVYGESVEL', 26010, nan, True, 'Matched'), ('KRFSLKHQM', 26113, nan, True, 'Matched'), ('APKGLWSQNQL', 26130, nan, True, 'Matched'), ('FVYGESVEL', 25997, nan, True, 'Matched'), ('KRLQAPVGQR', 26086, nan, False, 'Matched'), ('APKGLWSQNQL', 26129, nan, True, 'Matched'), ('FVYGESVEL', 26002, nan, True, 'Matched'), ('KRLQAPVGQR', 26087, nan, False, 'Matched'), ('FVYGESVEL', 26001, nan, True, 'Matched'), ('KRFSLKHQM', 26114, nan, True, 'Matched'), ('KRLQAPVGQR', 26090, nan, False, 'Matched'), ('HQMETHYRV', 26170, nan, True, 'Matched'), ('KRFSLKHQMETHY', 26122, nan, False, 'Matched'), ('FVYGESVEL', 26020, nan, True, 'Matched'), ('KRFSLKHQM', 26111, nan, True, 'Matched'), ('FVYGESVEL', 26000, nan, True, 'Matched'), ('SPSTFAQLLNFVYG', 26179, nan, True, 'Matched'), ('FVYGESVEL', 26021, nan, True, 'Matched'), ('KRFSLKHQMETHY', 26123, nan, False, 'Matched'), ('KRFSLKHQMETHY', 26120, nan, False, 'Matched'), ('KRFSLKHQMETHY', 26125, nan, False, 'Matched'), ('SPYGSDRLVQL', 26077, nan, True, 'Matched'), ('FVYGESVEL', 26014, nan, True, 'Matched'), ('KRFSLKHQMETHY', 26126, nan, False, 'Matched'), ('FVYGESVEL', 26023, nan, True, 'Matched'), ('HQMETHYRV', 26171, nan, True, 'Matched'), ('AEAPWLVGGQPALW', 26158, nan, True, 'Matched'), ('AEAPWLVGGQPALW', 26159, nan, True, 'Matched'), ('KRFSLKHQMETHY', 26124, nan, False, 'Matched'), ('KRFSLKHQM', 26112, nan, True, 'Matched'), ('KRFSLKHQMETHY', 26121, nan, False, 'Matched'), ('AEAPWLVGGQPALW', 26160, nan, True, 'Matched'), ('HQMETHYRV', 26168, nan, True, 'Matched'), ('AEAPWLVGGQPALW', 26161, nan, True, 'Matched'), ('FVYGESVEL', 26026, nan, True, 'Matched'), ('KRFSLKHQMETHY', 26119, nan, False, 'Matched'), ('FVYGESVEL', 26028, nan, True, 'Matched'), ('AEAPWLVGGQPALW', 26157, nan, True, 'Matched'), ('ALGVQSLEEACWR', 26154, nan, True, 'Matched'), ('PSRPSTSPCCPSSSTT', 26176, nan, True, 'Matched')] | I8: 14 | J8: =IFERROR(VLOOKUP(A8,dbg_proteins!$A$2:$A$20161,1,FALSE)," ---") -> Q9Y2Y4
A9: O75445 | B9: 5 | C9: [('RFIDKTSAL', 2669, 'HLA1', True, 'Missed'), ('SPRKPNGIIL', 2677, 'HLA1', True, 'Missed'), ('TGQCICKPNVEGR', 2638, 'non_standard_modification', True, 'Missed'), ('RFIDKTSAL', 2668, 'HLA1', True, 'Missed'), ('TGQCICKPNVEGR', 2639, 'non_standard_modification', True, 'Missed')] | D9: 3 | E9: 25 | F9: [('LYQVALTNR', 2659, nan, True, 'Matched'), ('VSIVPTQAVCGLPDR', 2664, nan, True, 'Matched'), ('VSIVPTQAVCGLPDR', 2662, nan, True, 'Matched'), ('STFCHSSAAAESIQFCTQR', 2670, nan, True, 'Matched'), ('ETIHTGSVNTY', 2666, nan, True, 'Matched'), ('GAVVNLASVSSGAVR', 2655, nan, True, 'Matched'), ('LYQVALTNR', 2658, nan, True, 'Matched'), ('ETIHTGSVNTY', 2667, nan, True, 'Matched'), ('FCIQDCPYR', 2650, nan, True, 'Matched'), ('NTERNTFMY', 2675, nan, True, 'Matched'), ('YVDPVGNNY', 2648, nan, True, 'Matched'), ('YVDPVGNNY', 2644, nan, True, 'Matched'), ('YVDPVGNNY', 2647, nan, True, 'Matched'), ('TPFQQPPPR', 2673, nan, True, 'Matched'), ('YVDPVGNNY', 2643, nan, True, 'Matched'), ('YVDPVGNNY', 2642, nan, True, 'Matched'), ('YVDPVGNNY', 2649, nan, True, 'Matched'), ('TGQCICKPNVEGR', 2633, nan, True, 'Matched'), ('YVDPVGNNY', 2646, nan, True, 'Matched'), ('YVDPVGNNY', 2645, nan, True, 'Matched'), ('FCIQDCPYR', 2651, nan, True, 'Matched'), ('GAVVNLASVSSGAVR', 2656, nan, True, 'Matched'), ('SCFSSPPSPK', 2676, nan, True, 'Matched'), ('TGQCICKPNVEGR', 2634, nan, True, 'Matched'), ('VCVNWSDTFLLNGQLK', 2678, nan, True, 'Matched')] | G9: 12 | H9: [('RFIDKTSAL', 2669, 'HLA1', True, 'Missed'), ('SPRKPNGIIL', 2677, 'HLA1', True, 'Missed'), ('TGQCICKPNVEGR', 2638, 'non_standard_modification', True, 'Missed'), ('RFIDKTSAL', 2668, 'HLA1', True, 'Missed'), ('TGQCICKPNVEGR', 2639, 'non_standard_modification', True, 'Missed'), ('LYQVALTNR', 2659, nan, True, 'Matched'), ('VSIVPTQAVCGLPDR', 2664, nan, True, 'Matched'), ('VSIVPTQAVCGLPDR', 2662, nan, True, 'Matched'), ('STFCHSSAAAESIQFCTQR', 2670, nan, True, 'Matched'), ('ETIHTGSVNTY', 2666, nan, True, 'Matched'), ('GAVVNLASVSSGAVR', 2655, nan, True, 'Matched'), ('LYQVALTNR', 2658, nan, True, 'Matched'), ('ETIHTGSVNTY', 2667, nan, True, 'Matched'), ('FCIQDCPYR', 2650, nan, True, 'Matched'), ('NTERNTFMY', 2675, nan, True, 'Matched'), ('YVDPVGNNY', 2648, nan, True, 'Matched'), ('YVDPVGNNY', 2644, nan, True, 'Matched'), ('YVDPVGNNY', 2647, nan, True, 'Matched'), ('TPFQQPPPR', 2673, nan, True, 'Matched'), ('YVDPVGNNY', 2643, nan, True, 'Matched'), ('YVDPVGNNY', 2642, nan, True, 'Matched'), ('YVDPVGNNY', 2649, nan, True, 'Matched'), ('TGQCICKPNVEGR', 2633, nan, True, 'Matched'), ('YVDPVGNNY', 2646, nan, True, 'Matched'), ('YVDPVGNNY', 2645, nan, True, 'Matched'), ('FCIQDCPYR', 2651, nan, True, 'Matched'), ('GAVVNLASVSSGAVR', 2656, nan, True, 'Matched'), ('SCFSSPPSPK', 2676, nan, True, 'Matched'), ('TGQCICKPNVEGR', 2634, nan, True, 'Matched'), ('VCVNWSDTFLLNGQLK', 2678, nan, True, 'Matched')] | I9: 14 | J9: =IFERROR(VLOOKUP(A9,dbg_proteins!$A$2:$A$20161,1,FALSE)," ---") -> ---
A10: Q9Y284 | B10: 117 | C10: [('DTKQMMSSF', 25673, 'IDENTIFIED', True, 'Missed'), ('DTKQMMSSF', 25742, 'IDENTIFIED', True, 'Missed'), ('DTKQMMSSF', 25667, 'IDENTIFIED', True, 'Missed'), ('DTKQMMSSF', 25640, 'IDENTIFIED', True, 'Missed'), ('DTKQMMSSF', 25638, 'IDENTIFIED', True, 'Missed'), ('DYMNLLGMIF', 25945, 'multiple_modifications', True, 'Missed'), ('DYMNLLGMIF', 25946, 'multiple_modifications', True, 'Missed'), ('DTKQMMSSF', 25693, 'IDENTIFIED', True, 'Missed'), ('DYMNLLGMIF', 25940, 'multiple_modifications', True, 'Missed'), ('DYMNLLGMIF', 25942, 'multiple_modifications', True, 'Missed'), ('DTKQMMSSF', 25668, 'IDENTIFIED', True, 'Missed'), ('DTKQMMSSF', 25686, 'IDENTIFIED', True, 'Missed'), ('DYMNLLGMIF', 25941, 'multiple_modifications', True, 'Missed'), ('DTKQMMSSF', 25678, 'IDENTIFIED', True, 'Missed'), ('DTKQMMSSF', 25715, 'IDENTIFIED', True, 'Missed'), ('DTKQMMSSF', 25624, 'IDENTIFIED', True, 'Missed'), ('DYMNLLGMIF', 25935, 'multiple_modifications', True, 'Missed'), ('DTKQMMSSF', 25635, 'IDENTIFIED', True, 'Missed'), ('DYMNLLGMIF', 25938, 'multiple_modifications', True, 'Missed'), ('DTKQMMSSF', 25690, 'IDENTIFIED', True, 'Missed'), ('DTKQMMSSF', 25643, 'IDENTIFIED', True, 'Missed'), ('DTKQMMSSF', 25652, 'IDENTIFIED', True, 'Missed'), ('DYMNLLGMIF', 25947, 'multiple_modifications', True, 'Missed'), ('DYMNLLGMIF', 25939, 'multiple_modifications', True, 'Missed'), ('DTKQMMSSF', 25706, 'IDENTIFIED', True, 'Missed'), ('DTKQMMSSF', 25677, 'IDENTIFIED', True, 'Missed'), ('DTKQMMSSF', 25701, 'IDENTIFIED', True, 'Missed'), ('DTKQMMSSF', 25684, 'IDENTIFIED', True, 'Missed'), ('DTKQMMSSF', 25646, 'IDENTIFIED', True, 'Missed'), ('DTKQMMSSF', 25629, 'IDENTIFIED', True, 'Missed'), ('DTKQMMSSF', 25691, 'IDENTIFIED', True, 'Missed'), ('DTKQMMSSF', 25630, 'IDENTIFIED', True, 'Missed'), ('DYMNLLGMIF', 25943, 'multiple_modifications', True, 'Missed'), ('DTKQMMSSF', 25627, 'IDENTIFIED', True, 'Missed'), ('DTKQMMSSF', 25631, 'IDENTIFIED', True, 'Missed'), ('DTKQMMSSF', 25622, 'IDENTIFIED', True, 'Missed'), ('DTKQMMSSF', 25636, 'IDENTIFIED', True, 'Missed'), ('DYMNLLGMIF', 25944, 'multiple_modifications', True, 'Missed'), ('DTKQMMSSF', 25626, 'IDENTIFIED', True, 'Missed'), ('DTKQMMSSF', 25623, 'IDENTIFIED', True, 'Missed'), ('DTKQMMSSF', 25639, 'IDENTIFIED', True, 'Missed'), ('DTKQMMSSF', 25628, 'IDENTIFIED', True, 'Missed'), ('DTKQMMSSF', 25688, 'IDENTIFIED', True, 'Missed'), ('DTKQMMSSF', 25681, 'IDENTIFIED', True, 'Missed'), ('DTKQMMSSF', 25625, 'IDENTIFIED', True, 'Missed'), ('DTKQMMSSF', 25698, 'IDENTIFIED', True, 'Missed'), ('DTKQMMSSF', 25620, 'IDENTIFIED', True, 'Missed'), ('DTKQMMSSF', 25692, 'IDENTIFIED', True, 'Missed'), ('DTKQMMSSF', 25679, 'IDENTIFIED', True, 'Missed'), ('DTKQMMSSF', 25703, 'IDENTIFIED', True, 'Missed'), ('DTKQMMSSF', 25666, 'IDENTIFIED', True, 'Missed'), ('DTKQMMSSF', 25618, 'IDENTIFIED', True, 'Missed'), ('DTKQMMSSF', 25740, 'IDENTIFIED', True, 'Missed'), ('DTKQMMSSF', 25641, 'IDENTIFIED', True, 'Missed'), ('DYMNLLGMIF', 25936, 'multiple_modifications', True, 'Missed'), ('DTKQMMSSF', 25617, 'IDENTIFIED', True, 'Missed'), ('DTKQMMSSF', 25655, 'IDENTIFIED', True, 'Missed'), ('DTKQMMSSF', 25725, 'IDENTIFIED', True, 'Missed'), ('DTKQMMSSF', 25616, 'IDENTIFIED', True, 'Missed'), ('DTKQMMSSF', 25621, 'IDENTIFIED', True, 'Missed'), ('DTKQMMSSF', 25721, 'IDENTIFIED', True, 'Missed'), ('AVYCSFISF', 25981, 'non_standard_modification', True, 'Missed'), ('DTKQMMSSF', 25714, 'IDENTIFIED', True, 'Missed'), ('DTKQMMSSF', 25741, 'IDENTIFIED', True, 'Missed'), ('DTKQMMSSF', 25619, 'IDENTIFIED', True, 'Missed'), ('DTKQMMSSF', 25717, 'IDENTIFIED', True, 'Missed'), ('DYMNLLGMIF', 25937, 'multiple_modifications', True, 'Missed'), ('SISAVVMSY', 25885, 'IDENTIFIED', True, 'Missed'), ('SISAVVMSY', 25893, 'IDENTIFIED', True, 'Missed'), ('DTKQMMSSF', 25710, 'IDENTIFIED', True, 'Missed'), ('DTKQMMSSF', 25719, 'IDENTIFIED', True, 'Missed'), ('DTKQMMSSF', 25645, 'IDENTIFIED', True, 'Missed'), ('SISAVVMSY', 25890, 'IDENTIFIED', True, 'Missed'), ('DTKQMMSSF', 25723, 'IDENTIFIED', True, 'Missed'), ('DTKQMMSSF', 25642, 'IDENTIFIED', True, 'Missed'), ('DTKQMMSSF', 25730, 'IDENTIFIED', True, 'Missed'), ('DTKQMMSSF', 25728, 'IDENTIFIED', True, 'Missed'), ('DTKQMMSSF', 25675, 'IDENTIFIED', True, 'Missed'), ('DTKQMMSSF', 25657, 'IDENTIFIED', True, 'Missed'), ('DTKQMMSSF', 25615, 'IDENTIFIED', True, 'Missed'), ('SISAVVMSY', 25891, 'IDENTIFIED', True, 'Missed'), ('DTKQMMSSF', 25644, 'IDENTIFIED', True, 'Missed'), ('DTKQMMSSF', 25634, 'IDENTIFIED', True, 'Missed'), ('DTKQMMSSF', 25650, 'IDENTIFIED', True, 'Missed'), ('DTKQMMSSF', 25724, 'IDENTIFIED', True, 'Missed'), ('DTKQMMSSF', 25637, 'IDENTIFIED', True, 'Missed'), ('DTKQMMSSF', 25722, 'IDENTIFIED', True, 'Missed'), ('DTKQMMSSF', 25632, 'IDENTIFIED', True, 'Missed'), ('DTKQMMSSF', 25689, 'IDENTIFIED', True, 'Missed'), ('DTKQMMSSF', 25671, 'IDENTIFIED', True, 'Missed'), ('SISAVVMSY', 25892, 'IDENTIFIED', True, 'Missed'), ('DTKQMMSSF', 25659, 'IDENTIFIED', True, 'Missed'), ('DTKQMMSSF', 25658, 'IDENTIFIED', True, 'Missed'), ('DTKQMMSSF', 25633, 'IDENTIFIED', True, 'Missed'), ('DTKQMMSSF', 25744, 'IDENTIFIED', True, 'Missed'), ('DTKQMMSSF', 25708, 'IDENTIFIED', True, 'Missed'), ('DTKQMMSSF', 25651, 'IDENTIFIED', True, 'Missed'), ('DTKQMMSSF', 25729, 'IDENTIFIED', True, 'Missed'), ('DTKQMMSSF', 25670, 'IDENTIFIED', True, 'Missed'), ('DTKQMMSSF', 25656, 'IDENTIFIED', True, 'Missed'), ('DTKQMMSSF', 25696, 'IDENTIFIED', True, 'Missed'), ('DTKQMMSSF', 25697, 'IDENTIFIED', True, 'Missed'), ('DTKQMMSSF', 25760, 'IDENTIFIED', True, 'Missed'), ('DTKQMMSSF', 25674, 'IDENTIFIED', True, 'Missed'), ('DTKQMMSSF', 25732, 'IDENTIFIED', True, 'Missed'), ('DTKQMMSSF', 25647, 'IDENTIFIED', True, 'Missed'), ('DTKQMMSSF', 25734, 'IDENTIFIED', True, 'Missed'), ('DTKQMMSSF', 25648, 'IDENTIFIED', True, 'Missed'), ('DTKQMMSSF', 25738, 'IDENTIFIED', True, 'Missed'), ('DTKQMMSSF', 25649, 'IDENTIFIED', True, 'Missed'), ('DTKQMMSSF', 25733, 'IDENTIFIED', True, 'Missed'), ('DTKQMMSSF', 25700, 'IDENTIFIED', True, 'Missed'), ('DTKQMMSSF', 25731, 'IDENTIFIED', True, 'Missed'), ('SSEDTKQMMSSF', 25989, 'multiple_modifications', False, 'Missed'), ('RYKPPPSECNPALDDPTPDYMNLL', 25988, 'non_standard_modification', False, 'Missed'), ('YKPPPSECNPALDDPTPDYM', 25966, 'non_standard_modification', True, 'Missed'), ('YKPPPSECNPALDDPTPDYM', 25963, 'non_standard_modification', True, 'Missed')] | D10: 5 | E10: 208 | F10: [('DTKQMMSSF', 25769, nan, True, 'Matched'), ('NPQPMTPPW', 25827, nan, True, 'Matched'), ('NPQPMTPPW', 25828, nan, True, 'Matched'), ('NPQPMTPPW', 25829, nan, True, 'Matched'), ('DTKQMMSSF', 25765, nan, True, 'Matched'), ('NPQPMTPPW', 25825, nan, True, 'Matched'), ('NPQPMTPPW', 25830, nan, True, 'Matched'), ('NPQPMTPPW', 25831, nan, True, 'Matched'), ('DTKQMMSSF', 25771, nan, True, 'Matched'), ('NPQPMTPPW', 25826, nan, True, 'Matched'), ('DTKQMMSSF', 25779, nan, True, 'Matched'), ('DTKQMMSSF', 25746, nan, True, 'Matched'), ('DTKQMMSSF', 25770, nan, True, 'Matched'), ('NPQPMTPPW', 25836, nan, True, 'Matched'), ('NPQPMTPPW', 25832, nan, True, 'Matched'), ('SFISFANSR', 25980, nan, True, 'Matched'), ('DTKQMMSSF', 25773, nan, True, 'Matched'), ('DTKQMMSSF', 25764, nan, True, 'Matched'), ('DTKQMMSSF', 25777, nan, True, 'Matched'), ('DTKQMMSSF', 25778, nan, True, 'Matched'), ('DTKQMMSSF', 25776, nan, True, 'Matched'), ('DTKQMMSSF', 25745, nan, True, 'Matched'), ('NPQPMTPPW', 25833, nan, True, 'Matched'), ('NPQPMTPPW', 25839, nan, True, 'Matched'), ('DTKQMMSSF', 25780, nan, True, 'Matched'), ('NPQPMTPPW', 25840, nan, True, 'Matched'), ('NPQPMTPPW', 25838, nan, True, 'Matched'), ('NPQPMTPPW', 25837, nan, True, 'Matched'), ('NPQPMTPPW', 25842, nan, True, 'Matched'), ('NPQPMTPPW', 25834, nan, True, 'Matched'), ('NPQPMTPPW', 25841, nan, True, 'Matched'), ('NPQPMTPPW', 25844, nan, True, 'Matched'), ('DTKQMMSSF', 25783, nan, True, 'Matched'), ('NPQPMTPPW', 25835, nan, True, 'Matched'), ('SFISFANSR', 25979, nan, True, 'Matched'), ('DTKQMMSSF', 25756, nan, True, 'Matched'), ('NPQPMTPPW', 25852, nan, True, 'Matched'), ('DTKQMMSSF', 25784, nan, True, 'Matched'), ('DTKQMMSSF', 25782, nan, True, 'Matched'), ('NPQPMTPPW', 25863, nan, True, 'Matched'), ('NPQPMTPPW', 25855, nan, True, 'Matched'), ('NPQPMTPPW', 25856, nan, True, 'Matched'), ('NPQPMTPPW', 25850, nan, True, 'Matched'), ('NPQPMTPPW', 25843, nan, True, 'Matched'), ('NPQPMTPPW', 25851, nan, True, 'Matched'), ('NPQPMTPPW', 25846, nan, True, 'Matched'), ('NPQPMTPPW', 25861, nan, True, 'Matched'), ('NPQPMTPPW', 25858, nan, True, 'Matched'), ('NPQPMTPPW', 25849, nan, True, 'Matched'), ('NPQPMTPPW', 25817, nan, True, 'Matched'), ('NPQPMTPPW', 25862, nan, True, 'Matched'), ('NPQPMTPPW', 25847, nan, True, 'Matched'), ('NPQPMTPPW', 25857, nan, True, 'Matched'), ('NPQPMTPPW', 25853, nan, True, 'Matched'), ('NPQPMTPPW', 25854, nan, True, 'Matched'), ('NPQPMTPPW', 25796, nan, True, 'Matched'), ('DTKQMMSSF', 25775, nan, True, 'Matched'), ('SISAVVMSY', 25886, nan, True, 'Matched'), ('NPQPMTPPW', 25848, nan, True, 'Matched'), ('NPQPMTPPW', 25864, nan, True, 'Matched'), ('NPQPMTPPW', 25845, nan, True, 'Matched'), ('DTKQMMSSF', 25768, nan, True, 'Matched'), ('SISAVVMSY', 25878, nan, True, 'Matched'), ('NPQPMTPPW', 25801, nan, True, 'Matched'), ('DTKQMMSSF', 25772, nan, True, 'Matched'), ('SISAVVMSY', 25884, nan, True, 'Matched'), ('NPQPMTPPW', 25859, nan, True, 'Matched'), ('NPQPMTPPW', 25798, nan, True, 'Matched'), ('NPQPMTPPW', 25813, nan, True, 'Matched'), ('NPQPMTPPW', 25860, nan, True, 'Matched'), ('NPQPMTPPW', 25811, nan, True, 'Matched'), ('SISAVVMSY', 25887, nan, True, 'Matched'), ('DTKQMMSSF', 25788, nan, True, 'Matched'), ('NPQPMTPPW', 25793, nan, True, 'Matched'), ('SISAVVMSY', 25876, nan, True, 'Matched'), ('RYKPPPSECNPA', 25987, nan, True, 'Matched'), ('LDDPTPDYMNLL', 25983, nan, True, 'Matched'), ('SISAVVMSY', 25883, nan, True, 'Matched'), ('NPQPMTPPW', 25795, nan, True, 'Matched'), ('SISAVVMSY', 25871, nan, True, 'Matched'), ('NPQPMTPPW', 25797, nan, True, 'Matched'), ('SISAVVMSY', 25877, nan, True, 'Matched'), ('SISAVVMSY', 25872, nan, True, 'Matched'), ('DTKQMMSSF', 25747, nan, True, 'Matched'), ('SISAVVMSY', 25874, nan, True, 'Matched'), ('SISAVVMSY', 25889, nan, True, 'Matched'), ('DTKQMMSSF', 25785, nan, True, 'Matched'), ('SISAVVMSY', 25882, nan, True, 'Matched'), ('NPQPMTPPW', 25803, nan, True, 'Matched'), ('NPQPMTPPW', 25794, nan, True, 'Matched'), ('SISAVVMSY', 25875, nan, True, 'Matched'), ('NPQPMTPPW', 25870, nan, True, 'Matched'), ('NPQPMTPPW', 25808, nan, True, 'Matched'), ('SISAVVMSY', 25888, nan, True, 'Matched'), ('NPQPMTPPW', 25810, nan, True, 'Matched'), ('NPQPMTPPW', 25820, nan, True, 'Matched'), ('NPQPMTPPW', 25818, nan, True, 'Matched'), ('NPQPMTPPW', 25792, nan, True, 'Matched'), ('NPQPMTPPW', 25809, nan, True, 'Matched'), ('NPQPMTPPW', 25800, nan, True, 'Matched'), ('SISAVVMSY', 25880, nan, True, 'Matched'), ('DTKQMMSSF', 25767, nan, True, 'Matched'), ('DTKQMMSSF', 25781, nan, True, 'Matched'), ('SISAVVMSY', 25873, nan, True, 'Matched'), ('NPQPMTPPW', 25819, nan, True, 'Matched'), ('SISAVVMSY', 25895, nan, True, 'Matched'), ('DTKQMMSSF', 25758, nan, True, 'Matched'), ('NPQPMTPPW', 25791, nan, True, 'Matched'), ('NPQPMTPPW', 25802, nan, True, 'Matched'), ('NPQPMTPPW', 25805, nan, True, 'Matched'), ('NPQPMTPPW', 25807, nan, True, 'Matched'), ('NPQPMTPPW', 25815, nan, True, 'Matched'), ('NPQPMTPPW', 25799, nan, True, 'Matched'), ('SISAVVMSY', 25879, nan, True, 'Matched'), ('SISAVVMSY', 25881, nan, True, 'Matched'), ('SISAVVMSY', 25908, nan, True, 'Matched'), ('DTKQMMSSF', 25774, nan, True, 'Matched'), ('DTKQMMSSF', 25766, nan, True, 'Matched'), ('DTKQMMSSF', 25787, nan, True, 'Matched'), ('NPQPMTPPW', 25816, nan, True, 'Matched'), ('DTKQMMSSF', 25743, nan, True, 'Matched'), ('NPQPMTPPW', 25804, nan, True, 'Matched'), ('SISAVVMSY', 25907, nan, True, 'Matched'), ('SISAVVMSY', 25906, nan, True, 'Matched'), ('NPQPMTPPW', 25868, nan, True, 'Matched'), ('DTKQMMSSF', 25763, nan, True, 'Matched'), ('NPQPMTPPW', 25812, nan, True, 'Matched'), ('SISAVVMSY', 25894, nan, True, 'Matched'), ('SISAVVMSY', 25897, nan, True, 'Matched'), ('RYKPPPSECNPALDDPTPDYM', 25974, nan, False, 'Matched'), ('NPQPMTPPW', 25806, nan, True, 'Matched'), ('DTKQMMSSF', 25786, nan, True, 'Matched'), ('NPQPMTPPW', 25867, nan, True, 'Matched'), ('NPQPMTPPW', 25866, nan, True, 'Matched'), ('SYLQNPQPMTPPW', 25969, nan, False, 'Matched'), ('SISAVVMSY', 25903, nan, True, 'Matched'), ('DTKQMMSSF', 25762, nan, True, 'Matched'), ('SMCGLMLKL', 25956, nan, True, 'Matched'), ('NPQPMTPPW', 25869, nan, True, 'Matched'), ('SMCGLMLKL', 25951, nan, True, 'Matched'), ('DTKQMMSSF', 25789, nan, True, 'Matched'), ('NPQPMTPPW', 25865, nan, True, 'Matched'), ('SMCGLMLKL', 25959, nan, True, 'Matched'), ('NPQPMTPPW', 25814, nan, True, 'Matched'), ('SMCGLMLKL', 25953, nan, True, 'Matched'), ('DTKQMMSSF', 25755, nan, True, 'Matched'), ('SMCGLMLKL', 25949, nan, True, 'Matched'), ('SMCGLMLKL', 25952, nan, True, 'Matched'), ('SMCGLMLKL', 25948, nan, True, 'Matched'), ('SISAVVMSY', 25905, nan, True, 'Matched'), ('SMCGLMLKL', 25954, nan, True, 'Matched'), ('SMCGLMLKL', 25950, nan, True, 'Matched'), ('YKPPPSECNPALDDPTPDYM', 25964, nan, True, 'Matched'), ('DTKQMMSSF', 25759, nan, True, 'Matched'), ('SMCGLMLKL', 25955, nan, True, 'Matched'), ('SISAVVMSY', 25896, nan, True, 'Matched'), ('LKWCAWVAVYCSFISFANSR', 25985, nan, False, 'Matched'), ('SISAVVMSY', 25900, nan, True, 'Matched'), ('RYKPPPSECNPALDDPTPDYM', 25975, nan, False, 'Matched'), ('KQMMSSFML', 25982, nan, True, 'Matched'), ('SISAVVMSY', 25901, nan, True, 'Matched'), ('SISAVVMSY', 25904, nan, True, 'Matched'), ('SISAVVMSY', 25898, nan, True, 'Matched'), ('SMCGLMLKL', 25957, nan, True, 'Matched'), ('YKPPPSECNPALDDPTPDYMNLLGMIFSMCGLMLK', 25914, nan, False, 'Matched'), ('SYLQNPQPMTPPW', 25970, nan, False, 'Matched'), ('SISAVVMSY', 25899, nan, True, 'Matched'), ('DTKQMMSSF', 25761, nan, True, 'Matched'), ('SMCGLMLKL', 25958, nan, True, 'Matched'), ('DTKQMMSSF', 25749, nan, True, 'Matched'), ('DTKQMMSSF', 25790, nan, True, 'Matched'), ('DTKQMMSSF', 25751, nan, True, 'Matched'), ('STNNMSDPRRPN', 25990, nan, True, 'Matched'), ('NMSDPRRPNKVL', 25986, nan, True, 'Matched'), ('YKPPPSECNPALDDPTPDYMNLLGMIFSMCGLMLK', 25924, nan, False, 'Matched'), ('YKPPPSECNPALDDPTPDYMNLLGMIFSMCGLMLK', 25928, nan, False, 'Matched'), ('YKPPPSECNPALDDPTPDYMNLLGMIFSMCGLMLK', 25921, nan, False, 'Matched'), ('YKPPPSECNPALDDPTPDYMNLLGMIFSMCGLMLK', 25917, nan, False, 'Matched'), ('RYKPPPSECNPALDDPTPDYM', 25976, nan, False, 'Matched'), ('YKPPPSECNPALDDPTPDYMNLLGMIFSMCGLMLK', 25915, nan, False, 'Matched'), ('YKPPPSECNPALDDPTPDYMNLLGMIFSMCGLMLK', 25925, nan, False, 'Matched'), ('SISAVVMSY', 25902, nan, True, 'Matched'), ('YKPPPSECNPALDDPTPDYM', 25962, nan, True, 'Matched'), ('YKPPPSECNPALDDPTPDYMNLLGMIFSMCGLMLK', 25926, nan, False, 'Matched'), ('YKPPPSECNPALDDPTPDYMNLLGMIFSMCGLMLK', 25916, nan, False, 'Matched'), ('YKPPPSECNPALDDPTPDYM', 25960, nan, True, 'Matched'), ('WCAWVAVYCSFISFANSR', 25991, nan, False, 'Matched'), ('YKPPPSECNPALDDPTPDYM', 25965, nan, True, 'Matched'), ('YKPPPSECNPALDDPTPDYMNLLGMIFSMCGLMLK', 25919, nan, False, 'Matched'), ('YKPPPSECNPALDDPTPDYMNLLGMIFSMCGLMLK', 25920, nan, False, 'Matched'), ('YKPPPSECNPALDDPTPDYMNLLGMIFSMCGLMLK', 25918, nan, False, 'Matched'), ('YKPPPSECNPALDDPTPDYMNLLGMIFSMCGLMLK', 25927, nan, False, 'Matched'), ('YKPPPSECNPALDDPTPDYM', 25961, nan, True, 'Matched'), ('LDDPTPDYMNLLGMIFSMCGLMLK', 25984, nan, False, 'Matched'), ('YKPPPSECNPALDDPTPDYMNLLGMIFSMCGLMLK', 25923, nan, False, 'Matched'), ('YKPPPSECNPALDDPTPDYMNLLGMIFSMCGLMLK', 25912, nan, False, 'Matched'), ('KPPPSECNPALDDPTPDYMNLLGMIFSMCGLMLK', 25978, nan, False, 'Matched'), ('YKPPPSECNPALDDPTPDYMNLLGMIFSMCGLMLK', 25930, nan, False, 'Matched'), ('YKPPPSECNPALDDPTPDYMNLLGMIFSMCGLMLK', 25933, nan, False, 'Matched'), ('YKPPPSECNPALDDPTPDYMNLLGMIFSMCGLMLK', 25931, nan, False, 'Matched'), ('KPPPSECNPALDDPTPDYMNLLGMIFSMCGLMLK', 25977, nan, False, 'Matched'), ('YKPPPSECNPALDDPTPDYMNLLGMIFSMCGLMLK', 25929, nan, False, 'Matched'), ('YKPPPSECNPALDDPTPDYMNLLGMIFSMCGLMLK', 25934, nan, False, 'Matched'), ('YKPPPSECNPALDDPTPDYMNLLGMIFSMCGLMLK', 25932, nan, False, 'Matched'), ('YKPPPSECNPALDDPTPDYMNLLGMIFSMCGLMLK', 25909, nan, False, 'Matched'), ('YKPPPSECNPALDDPTPDYMNLLGMIFSMCGLMLK', 25910, nan, False, 'Matched'), ('YKPPPSECNPALDDPTPDYMNLLGMIFSMCGLMLK', 25911, nan, False, 'Matched'), ('YKPPPSECNPALDDPTPDYMNLLGMIFSMCGLMLK', 25922, nan, False, 'Matched')] | G10: 11 | H10: [('DTKQMMSSF', 25673, 'IDENTIFIED', True, 'Missed'), ('DTKQMMSSF', 25742, 'IDENTIFIED', True, 'Missed'), ('DTKQMMSSF', 25667, 'IDENTIFIED', True, 'Missed'), ('DTKQMMSSF', 25640, 'IDENTIFIED', True, 'Missed'), ('DTKQMMSSF', 25638, 'IDENTIFIED', True, 'Missed'), ('DYMNLLGMIF', 25945, 'multiple_modifications', True, 'Missed'), ('DYMNLLGMIF', 25946, 'multiple_modifications', True, 'Missed'), ('DTKQMMSSF', 25693, 'IDENTIFIED', True, 'Missed'), ('DYMNLLGMIF', 25940, 'multiple_modifications', True, 'Missed'), ('DYMNLLGMIF', 25942, 'multiple_modifications', True, 'Missed'), ('DTKQMMSSF', 25668, 'IDENTIFIED', True, 'Missed'), ('DTKQMMSSF', 25686, 'IDENTIFIED', True, 'Missed'), ('DYMNLLGMIF', 25941, 'multiple_modifications', True, 'Missed'), ('DTKQMMSSF', 25678, 'IDENTIFIED', True, 'Missed'), ('DTKQMMSSF', 25715, 'IDENTIFIED', True, 'Missed'), ('DTKQMMSSF', 25624, 'IDENTIFIED', True, 'Missed'), ('DYMNLLGMIF', 25935, 'multiple_modifications', True, 'Missed'), ('DTKQMMSSF', 25635, 'IDENTIFIED', True, 'Missed'), ('DYMNLLGMIF', 25938, 'multiple_modifications', True, 'Missed'), ('DTKQMMSSF', 25690, 'IDENTIFIED', True, 'Missed'), ('DTKQMMSSF', 25643, 'IDENTIFIED', True, 'Missed'), ('DTKQMMSSF', 25652, 'IDENTIFIED', True, 'Missed'), ('DYMNLLGMIF', 25947, 'multiple_modifications', True, 'Missed'), ('DYMNLLGMIF', 25939, 'multiple_modifications', True, 'Missed'), ('DTKQMMSSF', 25706, 'IDENTIFIED', True, 'Missed'), ('DTKQMMSSF', 25677, 'IDENTIFIED', True, 'Missed'), ('DTKQMMSSF', 25701, 'IDENTIFIED', True, 'Missed'), ('DTKQMMSSF', 25684, 'IDENTIFIED', True, 'Missed'), ('DTKQMMSSF', 25646, 'IDENTIFIED', True, 'Missed'), ('DTKQMMSSF', 25629, 'IDENTIFIED', True, 'Missed'), ('DTKQMMSSF', 25691, 'IDENTIFIED', True, 'Missed'), ('DTKQMMSSF', 25630, 'IDENTIFIED', True, 'Missed'), ('DYMNLLGMIF', 25943, 'multiple_modifications', True, 'Missed'), ('DTKQMMSSF', 25627, 'IDENTIFIED', True, 'Missed'), ('DTKQMMSSF', 25631, 'IDENTIFIED', True, 'Missed'), ('DTKQMMSSF', 25622, 'IDENTIFIED', True, 'Missed'), ('DTKQMMSSF', 25636, 'IDENTIFIED', True, 'Missed'), ('DYMNLLGMIF', 25944, 'multiple_modifications', True, 'Missed'), ('DTKQMMSSF', 25626, 'IDENTIFIED', True, 'Missed'), ('DTKQMMSSF', 25623, 'IDENTIFIED', True, 'Missed'), ('DTKQMMSSF', 25639, 'IDENTIFIED', True, 'Missed'), ('DTKQMMSSF', 25628, 'IDENTIFIED', True, 'Missed'), ('DTKQMMSSF', 25688, 'IDENTIFIED', True, 'Missed'), ('DTKQMMSSF', 25681, 'IDENTIFIED', True, 'Missed'), ('DTKQMMSSF', 25625, 'IDENTIFIED', True, 'Missed'), ('DTKQMMSSF', 25698, 'IDENTIFIED', True, 'Missed'), ('DTKQMMSSF', 25620, 'IDENTIFIED', True, 'Missed'), ('DTKQMMSSF', 25692, 'IDENTIFIED', True, 'Missed'), ('DTKQMMSSF', 25679, 'IDENTIFIED', True, 'Missed'), ('DTKQMMSSF', 25703, 'IDENTIFIED', True, 'Missed'), ('DTKQMMSSF', 25666, 'IDENTIFIED', True, 'Missed'), ('DTKQMMSSF', 25618, 'IDENTIFIED', True, 'Missed'), ('DTKQMMSSF', 25740, 'IDENTIFIED', True, 'Missed'), ('DTKQMMSSF', 25641, 'IDENTIFIED', True, 'Missed'), ('DYMNLLGMIF', 25936, 'multiple_modifications', True, 'Missed'), ('DTKQMMSSF', 25617, 'IDENTIFIED', True, 'Missed'), ('DTKQMMSSF', 25655, 'IDENTIFIED', True, 'Missed'), ('DTKQMMSSF', 25725, 'IDENTIFIED', True, 'Missed'), ('DTKQMMSSF', 25616, 'IDENTIFIED', True, 'Missed'), ('DTKQMMSSF', 25621, 'IDENTIFIED', True, 'Missed'), ('DTKQMMSSF', 25721, 'IDENTIFIED', True, 'Missed'), ('AVYCSFISF', 25981, 'non_standard_modification', True, 'Missed'), ('DTKQMMSSF', 25714, 'IDENTIFIED', True, 'Missed'), ('DTKQMMSSF', 25741, 'IDENTIFIED', True, 'Missed'), ('DTKQMMSSF', 25619, 'IDENTIFIED', True, 'Missed'), ('DTKQMMSSF', 25717, 'IDENTIFIED', True, 'Missed'), ('DYMNLLGMIF', 25937, 'multiple_modifications', True, 'Missed'), ('SISAVVMSY', 25885, 'IDENTIFIED', True, 'Missed'), ('SISAVVMSY', 25893, 'IDENTIFIED', True, 'Missed'), ('DTKQMMSSF', 25710, 'IDENTIFIED', True, 'Missed'), ('DTKQMMSSF', 25719, 'IDENTIFIED', True, 'Missed'), ('DTKQMMSSF', 25645, 'IDENTIFIED', True, 'Missed'), ('SISAVVMSY', 25890, 'IDENTIFIED', True, 'Missed'), ('DTKQMMSSF', 25723, 'IDENTIFIED', True, 'Missed'), ('DTKQMMSSF', 25642, 'IDENTIFIED', True, 'Missed'), ('DTKQMMSSF', 25730, 'IDENTIFIED', True, 'Missed'), ('DTKQMMSSF', 25728, 'IDENTIFIED', True, 'Missed'), ('DTKQMMSSF', 25675, 'IDENTIFIED', True, 'Missed'), ('DTKQMMSSF', 25657, 'IDENTIFIED', True, 'Missed'), ('DTKQMMSSF', 25615, 'IDENTIFIED', True, 'Missed'), ('SISAVVMSY', 25891, 'IDENTIFIED', True, 'Missed'), ('DTKQMMSSF', 25644, 'IDENTIFIED', True, 'Missed'), ('DTKQMMSSF', 25634, 'IDENTIFIED', True, 'Missed'), ('DTKQMMSSF', 25650, 'IDENTIFIED', True, 'Missed'), ('DTKQMMSSF', 25724, 'IDENTIFIED', True, 'Missed'), ('DTKQMMSSF', 25637, 'IDENTIFIED', True, 'Missed'), ('DTKQMMSSF', 25722, 'IDENTIFIED', True, 'Missed'), ('DTKQMMSSF', 25632, 'IDENTIFIED', True, 'Missed'), ('DTKQMMSSF', 25689, 'IDENTIFIED', True, 'Missed'), ('DTKQMMSSF', 25671, 'IDENTIFIED', True, 'Missed'), ('SISAVVMSY', 25892, 'IDENTIFIED', True, 'Missed'), ('DTKQMMSSF', 25659, 'IDENTIFIED', True, 'Missed'), ('DTKQMMSSF', 25658, 'IDENTIFIED', True, 'Missed'), ('DTKQMMSSF', 25633, 'IDENTIFIED', True, 'Missed'), ('DTKQMMSSF', 25744, 'IDENTIFIED', True, 'Missed'), ('DTKQMMSSF', 25708, 'IDENTIFIED', True, 'Missed'), ('DTKQMMSSF', 25651, 'IDENTIFIED', True, 'Missed'), ('DTKQMMSSF', 25729, 'IDENTIFIED', True, 'Missed'), ('DTKQMMSSF', 25670, 'IDENTIFIED', True, 'Missed'), ('DTKQMMSSF', 25656, 'IDENTIFIED', True, 'Missed'), ('DTKQMMSSF', 25696, 'IDENTIFIED', True, 'Missed'), ('DTKQMMSSF', 25697, 'IDENTIFIED', True, 'Missed'), ('DTKQMMSSF', 25760, 'IDENTIFIED', True, 'Missed'), ('DTKQMMSSF', 25674, 'IDENTIFIED', True, 'Missed'), ('DTKQMMSSF', 25732, 'IDENTIFIED', True, 'Missed'), ('DTKQMMSSF', 25647, 'IDENTIFIED', True, 'Missed'), ('DTKQMMSSF', 25734, 'IDENTIFIED', True, 'Missed'), ('DTKQMMSSF', 25648, 'IDENTIFIED', True, 'Missed'), ('DTKQMMSSF', 25738, 'IDENTIFIED', True, 'Missed'), ('DTKQMMSSF', 25649, 'IDENTIFIED', True, 'Missed'), ('DTKQMMSSF', 25733, 'IDENTIFIED', True, 'Missed'), ('DTKQMMSSF', 25700, 'IDENTIFIED', True, 'Missed'), ('DTKQMMSSF', 25731, 'IDENTIFIED', True, 'Missed'), ('SSEDTKQMMSSF', 25989, 'multiple_modifications', False, 'Missed'), ('RYKPPPSECNPALDDPTPDYMNLL', 25988, 'non_standard_modification', False, 'Missed'), ('YKPPPSECNPALDDPTPDYM', 25966, 'non_standard_modification', True, 'Missed'), ('YKPPPSECNPALDDPTPDYM', 25963, 'non_standard_modification', True, 'Missed'), ('DTKQMMSSF', 25769, nan, True, 'Matched'), ('NPQPMTPPW', 25827, nan, True, 'Matched'), ('NPQPMTPPW', 25828, nan, True, 'Matched'), ('NPQPMTPPW', 25829, nan, True, 'Matched'), ('DTKQMMSSF', 25765, nan, True, 'Matched'), ('NPQPMTPPW', 25825, nan, True, 'Matched'), ('NPQPMTPPW', 25830, nan, True, 'Matched'), ('NPQPMTPPW', 25831, nan, True, 'Matched'), ('DTKQMMSSF', 25771, nan, True, 'Matched'), ('NPQPMTPPW', 25826, nan, True, 'Matched'), ('DTKQMMSSF', 25779, nan, True, 'Matched'), ('DTKQMMSSF', 25746, nan, True, 'Matched'), ('DTKQMMSSF', 25770, nan, True, 'Matched'), ('NPQPMTPPW', 25836, nan, True, 'Matched'), ('NPQPMTPPW', 25832, nan, True, 'Matched'), ('SFISFANSR', 25980, nan, True, 'Matched'), ('DTKQMMSSF', 25773, nan, True, 'Matched'), ('DTKQMMSSF', 25764, nan, True, 'Matched'), ('DTKQMMSSF', 25777, nan, True, 'Matched'), ('DTKQMMSSF', 25778, nan, True, 'Matched'), ('DTKQMMSSF', 25776, nan, True, 'Matched'), ('DTKQMMSSF', 25745, nan, True, 'Matched'), ('NPQPMTPPW', 25833, nan, True, 'Matched'), ('NPQPMTPPW', 25839, nan, True, 'Matched'), ('DTKQMMSSF', 25780, nan, True, 'Matched'), ('NPQPMTPPW', 25840, nan, True, 'Matched'), ('NPQPMTPPW', 25838, nan, True, 'Matched'), ('NPQPMTPPW', 25837, nan, True, 'Matched'), ('NPQPMTPPW', 25842, nan, True, 'Matched'), ('NPQPMTPPW', 25834, nan, True, 'Matched'), ('NPQPMTPPW', 25841, nan, True, 'Matched'), ('NPQPMTPPW', 25844, nan, True, 'Matched'), ('DTKQMMSSF', 25783, nan, True, 'Matched'), ('NPQPMTPPW', 25835, nan, True, 'Matched'), ('SFISFANSR', 25979, nan, True, 'Matched'), ('DTKQMMSSF', 25756, nan, True, 'Matched'), ('NPQPMTPPW', 25852, nan, True, 'Matched'), ('DTKQMMSSF', 25784, nan, True, 'Matched'), ('DTKQMMSSF', 25782, nan, True, 'Matched'), ('NPQPMTPPW', 25863, nan, True, 'Matched'), ('NPQPMTPPW', 25855, nan, True, 'Matched'), ('NPQPMTPPW', 25856, nan, True, 'Matched'), ('NPQPMTPPW', 25850, nan, True, 'Matched'), ('NPQPMTPPW', 25843, nan, True, 'Matched'), ('NPQPMTPPW', 25851, nan, True, 'Matched'), ('NPQPMTPPW', 25846, nan, True, 'Matched'), ('NPQPMTPPW', 25861, nan, True, 'Matched'), ('NPQPMTPPW', 25858, nan, True, 'Matched'), ('NPQPMTPPW', 25849, nan, True, 'Matched'), ('NPQPMTPPW', 25817, nan, True, 'Matched'), ('NPQPMTPPW', 25862, nan, True, 'Matched'), ('NPQPMTPPW', 25847, nan, True, 'Matched'), ('NPQPMTPPW', 25857, nan, True, 'Matched'), ('NPQPMTPPW', 25853, nan, True, 'Matched'), ('NPQPMTPPW', 25854, nan, True, 'Matched'), ('NPQPMTPPW', 25796, nan, True, 'Matched'), ('DTKQMMSSF', 25775, nan, True, 'Matched'), ('SISAVVMSY', 25886, nan, True, 'Matched'), ('NPQPMTPPW', 25848, nan, True, 'Matched'), ('NPQPMTPPW', 25864, nan, True, 'Matched'), ('NPQPMTPPW', 25845, nan, True, 'Matched'), ('DTKQMMSSF', 25768, nan, True, 'Matched'), ('SISAVVMSY', 25878, nan, True, 'Matched'), ('NPQPMTPPW', 25801, nan, True, 'Matched'), ('DTKQMMSSF', 25772, nan, True, 'Matched'), ('SISAVVMSY', 25884, nan, True, 'Matched'), ('NPQPMTPPW', 25859, nan, True, 'Matched'), ('NPQPMTPPW', 25798, nan, True, 'Matched'), ('NPQPMTPPW', 25813, nan, True, 'Matched'), ('NPQPMTPPW', 25860, nan, True, 'Matched'), ('NPQPMTPPW', 25811, nan, True, 'Matched'), ('SISAVVMSY', 25887, nan, True, 'Matched'), ('DTKQMMSSF', 25788, nan, True, 'Matched'), ('NPQPMTPPW', 25793, nan, True, 'Matched'), ('SISAVVMSY', 25876, nan, True, 'Matched'), ('RYKPPPSECNPA', 25987, nan, True, 'Matched'), ('LDDPTPDYMNLL', 25983, nan, True, 'Matched'), ('SISAVVMSY', 25883, nan, True, 'Matched'), ('NPQPMTPPW', 25795, nan, True, 'Matched'), ('SISAVVMSY', 25871, nan, True, 'Matched'), ('NPQPMTPPW', 25797, nan, True, 'Matched'), ('SISAVVMSY', 25877, nan, True, 'Matched'), ('SISAVVMSY', 25872, nan, True, 'Matched'), ('DTKQMMSSF', 25747, nan, True, 'Matched'), ('SISAVVMSY', 25874, nan, True, 'Matched'), ('SISAVVMSY', 25889, nan, True, 'Matched'), ('DTKQMMSSF', 25785, nan, True, 'Matched'), ('SISAVVMSY', 25882, nan, True, 'Matched'), ('NPQPMTPPW', 25803, nan, True, 'Matched'), ('NPQPMTPPW', 25794, nan, True, 'Matched'), ('SISAVVMSY', 25875, nan, True, 'Matched'), ('NPQPMTPPW', 25870, nan, True, 'Matched'), ('NPQPMTPPW', 25808, nan, True, 'Matched'), ('SISAVVMSY', 25888, nan, True, 'Matched'), ('NPQPMTPPW', 25810, nan, True, 'Matched'), ('NPQPMTPPW', 25820, nan, True, 'Matched'), ('NPQPMTPPW', 25818, nan, True, 'Matched'), ('NPQPMTPPW', 25792, nan, True, 'Matched'), ('NPQPMTPPW', 25809, nan, True, 'Matched'), ('NPQPMTPPW', 25800, nan, True, 'Matched'), ('SISAVVMSY', 25880, nan, True, 'Matched'), ('DTKQMMSSF', 25767, nan, True, 'Matched'), ('DTKQMMSSF', 25781, nan, True, 'Matched'), ('SISAVVMSY', 25873, nan, True, 'Matched'), ('NPQPMTPPW', 25819, nan, True, 'Matched'), ('SISAVVMSY', 25895, nan, True, 'Matched'), ('DTKQMMSSF', 25758, nan, True, 'Matched'), ('NPQPMTPPW', 25791, nan, True, 'Matched'), ('NPQPMTPPW', 25802, nan, True, 'Matched'), ('NPQPMTPPW', 25805, nan, True, 'Matched'), ('NPQPMTPPW', 25807, nan, True, 'Matched'), ('NPQPMTPPW', 25815, nan, True, 'Matched'), ('NPQPMTPPW', 25799, nan, True, 'Matched'), ('SISAVVMSY', 25879, nan, True, 'Matched'), ('SISAVVMSY', 25881, nan, True, 'Matched'), ('SISAVVMSY', 25908, nan, True, 'Matched'), ('DTKQMMSSF', 25774, nan, True, 'Matched'), ('DTKQMMSSF', 25766, nan, True, 'Matched'), ('DTKQMMSSF', 25787, nan, True, 'Matched'), ('NPQPMTPPW', 25816, nan, True, 'Matched'), ('DTKQMMSSF', 25743, nan, True, 'Matched'), ('NPQPMTPPW', 25804, nan, True, 'Matched'), ('SISAVVMSY', 25907, nan, True, 'Matched'), ('SISAVVMSY', 25906, nan, True, 'Matched'), ('NPQPMTPPW', 25868, nan, True, 'Matched'), ('DTKQMMSSF', 25763, nan, True, 'Matched'), ('NPQPMTPPW', 25812, nan, True, 'Matched'), ('SISAVVMSY', 25894, nan, True, 'Matched'), ('SISAVVMSY', 25897, nan, True, 'Matched'), ('RYKPPPSECNPALDDPTPDYM', 25974, nan, False, 'Matched'), ('NPQPMTPPW', 25806, nan, True, 'Matched'), ('DTKQMMSSF', 25786, nan, True, 'Matched'), ('NPQPMTPPW', 25867, nan, True, 'Matched'), ('NPQPMTPPW', 25866, nan, True, 'Matched'), ('SYLQNPQPMTPPW', 25969, nan, False, 'Matched'), ('SISAVVMSY', 25903, nan, True, 'Matched'), ('DTKQMMSSF', 25762, nan, True, 'Matched'), ('SMCGLMLKL', 25956, nan, True, 'Matched'), ('NPQPMTPPW', 25869, nan, True, 'Matched'), ('SMCGLMLKL', 25951, nan, True, 'Matched'), ('DTKQMMSSF', 25789, nan, True, 'Matched'), ('NPQPMTPPW', 25865, nan, True, 'Matched'), ('SMCGLMLKL', 25959, nan, True, 'Matched'), ('NPQPMTPPW', 25814, nan, True, 'Matched'), ('SMCGLMLKL', 25953, nan, True, 'Matched'), ('DTKQMMSSF', 25755, nan, True, 'Matched'), ('SMCGLMLKL', 25949, nan, True, 'Matched'), ('SMCGLMLKL', 25952, nan, True, 'Matched'), ('SMCGLMLKL', 25948, nan, True, 'Matched'), ('SISAVVMSY', 25905, nan, True, 'Matched'), ('SMCGLMLKL', 25954, nan, True, 'Matched'), ('SMCGLMLKL', 25950, nan, True, 'Matched'), ('YKPPPSECNPALDDPTPDYM', 25964, nan, True, 'Matched'), ('DTKQMMSSF', 25759, nan, True, 'Matched'), ('SMCGLMLKL', 25955, nan, True, 'Matched'), ('SISAVVMSY', 25896, nan, True, 'Matched'), ('LKWCAWVAVYCSFISFANSR', 25985, nan, False, 'Matched'), ('SISAVVMSY', 25900, nan, True, 'Matched'), ('RYKPPPSECNPALDDPTPDYM', 25975, nan, False, 'Matched'), ('KQMMSSFML', 25982, nan, True, 'Matched'), ('SISAVVMSY', 25901, nan, True, 'Matched'), ('SISAVVMSY', 25904, nan, True, 'Matched'), ('SISAVVMSY', 25898, nan, True, 'Matched'), ('SMCGLMLKL', 25957, nan, True, 'Matched'), ('YKPPPSECNPALDDPTPDYMNLLGMIFSMCGLMLK', 25914, nan, False, 'Matched'), ('SYLQNPQPMTPPW', 25970, nan, False, 'Matched'), ('SISAVVMSY', 25899, nan, True, 'Matched'), ('DTKQMMSSF', 25761, nan, True, 'Matched'), ('SMCGLMLKL', 25958, nan, True, 'Matched'), ('DTKQMMSSF', 25749, nan, True, 'Matched'), ('DTKQMMSSF', 25790, nan, True, 'Matched'), ('DTKQMMSSF', 25751, nan, True, 'Matched'), ('STNNMSDPRRPN', 25990, nan, True, 'Matched'), ('NMSDPRRPNKVL', 25986, nan, True, 'Matched'), ('YKPPPSECNPALDDPTPDYMNLLGMIFSMCGLMLK', 25924, nan, False, 'Matched'), ('YKPPPSECNPALDDPTPDYMNLLGMIFSMCGLMLK', 25928, nan, False, 'Matched'), ('YKPPPSECNPALDDPTPDYMNLLGMIFSMCGLMLK', 25921, nan, False, 'Matched'), ('YKPPPSECNPALDDPTPDYMNLLGMIFSMCGLMLK', 25917, nan, False, 'Matched'), ('RYKPPPSECNPALDDPTPDYM', 25976, nan, False, 'Matched'), ('YKPPPSECNPALDDPTPDYMNLLGMIFSMCGLMLK', 25915, nan, False, 'Matched'), ('YKPPPSECNPALDDPTPDYMNLLGMIFSMCGLMLK', 25925, nan, False, 'Matched'), ('SISAVVMSY', 25902, nan, True, 'Matched'), ('YKPPPSECNPALDDPTPDYM', 25962, nan, True, 'Matched'), ('YKPPPSECNPALDDPTPDYMNLLGMIFSMCGLMLK', 25926, nan, False, 'Matched'), ('YKPPPSECNPALDDPTPDYMNLLGMIFSMCGLMLK', 25916, nan, False, 'Matched'), ('YKPPPSECNPALDDPTPDYM', 25960, nan, True, 'Matched'), ('WCAWVAVYCSFISFANSR', 25991, nan, False, 'Matched'), ('YKPPPSECNPALDDPTPDYM', 25965, nan, True, 'Matched'), ('YKPPPSECNPALDDPTPDYMNLLGMIFSMCGLMLK', 25919, nan, False, 'Matched'), ('YKPPPSECNPALDDPTPDYMNLLGMIFSMCGLMLK', 25920, nan, False, 'Matched'), ('YKPPPSECNPALDDPTPDYMNLLGMIFSMCGLMLK', 25918, nan, False, 'Matched'), ('YKPPPSECNPALDDPTPDYMNLLGMIFSMCGLMLK', 25927, nan, False, 'Matched'), ('YKPPPSECNPALDDPTPDYM', 25961, nan, True, 'Matched'), ('LDDPTPDYMNLLGMIFSMCGLMLK', 25984, nan, False, 'Matched'), ('YKPPPSECNPALDDPTPDYMNLLGMIFSMCGLMLK', 25923, nan, False, 'Matched'), ('YKPPPSECNPALDDPTPDYMNLLGMIFSMCGLMLK', 25912, nan, False, 'Matched'), ('KPPPSECNPALDDPTPDYMNLLGMIFSMCGLMLK', 25978, nan, False, 'Matched'), ('YKPPPSECNPALDDPTPDYMNLLGMIFSMCGLMLK', 25930, nan, False, 'Matched'), ('YKPPPSECNPALDDPTPDYMNLLGMIFSMCGLMLK', 25933, nan, False, 'Matched'), ('YKPPPSECNPALDDPTPDYMNLLGMIFSMCGLMLK', 25931, nan, False, 'Matched'), ('KPPPSECNPALDDPTPDYMNLLGMIFSMCGLMLK', 25977, nan, False, 'Matched'), ('YKPPPSECNPALDDPTPDYMNLLGMIFSMCGLMLK', 25929, nan, False, 'Matched'), ('YKPPPSECNPALDDPTPDYMNLLGMIFSMCGLMLK', 25934, nan, False, 'Matched'), ('YKPPPSECNPALDDPTPDYMNLLGMIFSMCGLMLK', 25932, nan, False, 'Matched'), ('YKPPPSECNPALDDPTPDYMNLLGMIFSMCGLMLK', 25909, nan, False, 'Matched'), ('YKPPPSECNPALDDPTPDYMNLLGMIFSMCGLMLK', 25910, nan, False, 'Matched'), ('YKPPPSECNPALDDPTPDYMNLLGMIFSMCGLMLK', 25911, nan, False, 'Matched'), ('YKPPPSECNPALDDPTPDYMNLLGMIFSMCGLMLK', 25922, nan, False, 'Matched')] | I10: 13 | J10: =IFERROR(VLOOKUP(A10,dbg_proteins!$A$2:$A$20161,1,FALSE)," ---") -> Q9Y284
A11: Q9Y271 | B11: 59 | C11: [('CFEPPQDNQTK', 25552, 'non_standard_modification', True, 'Missed'), ('GIWLFGDFLCR', 25577, 'non_standard_modification', True, 'Missed'), ('GIWLFGDFLCR', 25576, 'non_standard_modification', True, 'Missed'), ('CFEPPQDNQTK', 25553, 'non_standard_modification', True, 'Missed'), ('CIAIVFPVQNINLVTQK', 25564, 'non_standard_modification', True, 'Missed'), ('CFEPPQDNQTK', 25554, 'non_standard_modification', True, 'Missed'), ('CIAIVFPVQNINLVTQK', 25563, 'non_standard_modification', True, 'Missed'), ('CFEPPQDNQTK', 25556, 'non_standard_modification', True, 'Missed'), ('CFEPPQDNQTK', 25555, 'non_standard_modification', True, 'Missed'), ('CFEPPQDNQTK', 25551, 'non_standard_modification', True, 'Missed'), ('TIHLHFLHNETKPCDSVLR', 25526, 'non_standard_modification', True, 'Missed'), ('CIAIVFPVQNINLVTQK', 25565, 'non_standard_modification', True, 'Missed'), ('TIHLHFLHNETKPCDSVLR', 25528, 'non_standard_modification', True, 'Missed'), ('TIHLHFLHNETKPCDSVLR', 25537, 'non_standard_modification', True, 'Missed'), ('TIHLHFLHNETKPCDSVLR', 25527, 'non_standard_modification', True, 'Missed'), ('TIHLHFLHNETKPCDSVLR', 25529, 'non_standard_modification', True, 'Missed'), ('TIHLHFLHNETKPCDSVLR', 25539, 'non_standard_modification', True, 'Missed'), ('DSVLRMQKSVVITLS', 25601, 'HLA2', True, 'Missed'), ('TIHLHFLHNETKPCDSVLR', 25538, 'non_standard_modification', True, 'Missed'), ('QRTIHLHFL', 25596, 'HLA1', True, 'Missed'), ('CIAIVFPVQNINLVTQK', 25557, 'non_standard_modification', True, 'Missed'), ('TIHLHFLHNETKPCDSVLR', 25530, 'non_standard_modification', True, 'Missed'), ('MDETGNLTVSSATCHDTIDDFR', 25398, 'non_standard_modification', True, 'Missed'), ('MDETGNLTVSSATCHDTIDDFR', 25400, 'non_standard_modification', True, 'Missed'), ('MDETGNLTVSSATCHDTIDDFR', 25406, 'non_standard_modification', True, 'Missed'), ('MDETGNLTVSSATCHDTIDDFR', 25402, 'non_standard_modification', True, 'Missed'), ('MDETGNLTVSSATCHDTIDDFR', 25407, 'non_standard_modification', True, 'Missed'), ('MDETGNLTVSSATCHDTIDDFR', 25396, 'non_standard_modification', True, 'Missed'), ('MDETGNLTVSSATCHDTIDDFR', 25395, 'non_standard_modification', True, 'Missed'), ('MDETGNLTVSSATCHDTIDDFR', 25408, 'non_standard_modification', True, 'Missed'), ('MDETGNLTVSSATCHDTIDDFR', 25443, 'non_standard_modification', True, 'Missed'), ('MDETGNLTVSSATCHDTIDDFR', 25450, 'non_standard_modification', True, 'Missed'), ('MDETGNLTVSSATCHDTIDDFR', 25394, 'non_standard_modification', True, 'Missed'), ('MDETGNLTVSSATCHDTIDDFR', 25422, 'non_standard_modification', True, 'Missed'), ('MDETGNLTVSSATCHDTIDDFR', 25445, 'non_standard_modification', True, 'Missed'), ('MDETGNLTVSSATCHDTIDDFR', 25403, 'non_standard_modification', True, 'Missed'), ('MDETGNLTVSSATCHDTIDDFR', 25401, 'non_standard_modification', True, 'Missed'), ('MDETGNLTVSSATCHDTIDDFR', 25405, 'non_standard_modification', True, 'Missed'), ('MDETGNLTVSSATCHDTIDDFR', 25441, 'non_standard_modification', True, 'Missed'), ('MDETGNLTVSSATCHDTIDDFR', 25410, 'non_standard_modification', True, 'Missed'), ('MDETGNLTVSSATCHDTIDDFR', 25409, 'non_standard_modification', True, 'Missed'), ('MDETGNLTVSSATCHDTIDDFR', 25417, 'non_standard_modification', True, 'Missed'), ('MDETGNLTVSSATCHDTIDDFR', 25453, 'non_standard_modification', True, 'Missed'), ('MDETGNLTVSSATCHDTIDDFR', 25416, 'non_standard_modification', True, 'Missed'), ('MDETGNLTVSSATCHDTIDDFR', 25413, 'non_standard_modification', True, 'Missed'), ('MDETGNLTVSSATCHDTIDDFR', 25412, 'non_standard_modification', True, 'Missed'), ('MDETGNLTVSSATCHDTIDDFR', 25429, 'non_standard_modification', True, 'Missed'), ('MDETGNLTVSSATCHDTIDDFR', 25447, 'non_standard_modification', True, 'Missed'), ('MDETGNLTVSSATCHDTIDDFR', 25404, 'non_standard_modification', True, 'Missed'), ('MDETGNLTVSSATCHDTIDDFR', 25419, 'non_standard_modification', True, 'Missed'), ('MDETGNLTVSSATCHDTIDDFR', 25420, 'non_standard_modification', True, 'Missed'), ('MDETGNLTVSSATCHDTIDDFR', 25397, 'non_standard_modification', True, 'Missed'), ('MDETGNLTVSSATCHDTIDDFR', 25411, 'non_standard_modification', True, 'Missed'), ('MDETGNLTVSSATCHDTIDDFR', 25430, 'non_standard_modification', True, 'Missed'), ('MDETGNLTVSSATCHDTIDDFR', 25399, 'non_standard_modification', True, 'Missed'), ('MDETGNLTVSSATCHDTIDDFR', 25418, 'non_standard_modification', True, 'Missed'), ('MDETGNLTVSSATCHDTIDDFR', 25387, 'non_standard_modification', True, 'Missed'), ('MDETGNLTVSSATCHDTIDDFR', 25376, 'non_standard_modification', True, 'Missed'), ('MDETGNLTVSSATCHDTIDDFR', 25392, 'non_standard_modification', True, 'Missed')] | D11: 7 | E11: 132 | F11: [('MPYHIQRTI', 25511, nan, True, 'Matched'), ('MPYHIQRTI', 25502, nan, True, 'Matched'), ('MPYHIQRTI', 25509, nan, True, 'Matched'), ('MPYHIQRTI', 25517, nan, True, 'Matched'), ('MPYHIQRTI', 25507, nan, True, 'Matched'), ('MPYHIQRTI', 25501, nan, True, 'Matched'), ('MPYHIQRTI', 25500, nan, True, 'Matched'), ('MPYHIQRTI', 25498, nan, True, 'Matched'), ('MPYHIQRTI', 25499, nan, True, 'Matched'), ('MPYHIQRTI', 25497, nan, True, 'Matched'), ('MPYHIQRTI', 25510, nan, True, 'Matched'), ('MPYHIQRTI', 25504, nan, True, 'Matched'), ('MPYHIQRTI', 25516, nan, True, 'Matched'), ('MPYHIQRTI', 25514, nan, True, 'Matched'), ('MPYHIQRTI', 25472, nan, True, 'Matched'), ('MDETGNLTVSSATCHDTIDDFR', 25423, nan, True, 'Matched'), ('MPYHIQRTI', 25523, nan, True, 'Matched'), ('MPYHIQRTI', 25519, nan, True, 'Matched'), ('MPYHIQRTI', 25513, nan, True, 'Matched'), ('MPYHIQRTI', 25462, nan, True, 'Matched'), ('MPYHIQRTI', 25520, nan, True, 'Matched'), ('MPYHIQRTI', 25508, nan, True, 'Matched'), ('MPYHIQRTI', 25506, nan, True, 'Matched'), ('MPYHIQRTI', 25512, nan, True, 'Matched'), ('MPYHIQRTI', 25521, nan, True, 'Matched'), ('MPYHIQRTI', 25496, nan, True, 'Matched'), ('MPYHIQRTI', 25503, nan, True, 'Matched'), ('MPYHIQRTI', 25505, nan, True, 'Matched'), ('MPYHIQRTI', 25477, nan, True, 'Matched'), ('MPYHIQRTI', 25456, nan, True, 'Matched'), ('MPYHIQRTI', 25522, nan, True, 'Matched'), ('MPYHIQRTI', 25469, nan, True, 'Matched'), ('MPYHIQRTI', 25459, nan, True, 'Matched'), ('MPYHIQRTI', 25467, nan, True, 'Matched'), ('MPYHIQRTI', 25518, nan, True, 'Matched'), ('MPYHIQRTI', 25515, nan, True, 'Matched'), ('MPYHIQRTI', 25455, nan, True, 'Matched'), ('MPYHIQRTI', 25464, nan, True, 'Matched'), ('MPYHIQRTI', 25475, nan, True, 'Matched'), ('GIWLFGDFLCR', 25575, nan, True, 'Matched'), ('MPYHIQRTI', 25480, nan, True, 'Matched'), ('MPYHIQRTI', 25463, nan, True, 'Matched'), ('CFEPPQDNQTK', 25547, nan, True, 'Matched'), ('MPYHIQRTI', 25465, nan, True, 'Matched'), ('MPYHIQRTI', 25460, nan, True, 'Matched'), ('MPYHIQRTI', 25457, nan, True, 'Matched'), ('FLHNETKPCDSVLR', 25591, nan, True, 'Matched'), ('MPYHIQRTI', 25458, nan, True, 'Matched'), ('CFEPPQDNQTK', 25550, nan, True, 'Matched'), ('MDETGNLTVSSATCHDTIDDFR', 25424, nan, True, 'Matched'), ('MPYHIQRTI', 25461, nan, True, 'Matched'), ('FLHNETKPCDSVLR', 25592, nan, True, 'Matched'), ('MPYHIQRTI', 25487, nan, True, 'Matched'), ('TIHLHFLHNETKPCDSVLR', 25531, nan, False, 'Matched'), ('CFEPPQDNQTK', 25546, nan, True, 'Matched'), ('MPYHIQRTI', 25454, nan, True, 'Matched'), ('CFEPPQDNQTK', 25548, nan, True, 'Matched'), ('CFEPPQDNQTK', 25549, nan, True, 'Matched'), ('CIAIVFPVQNINLVTQK', 25559, nan, True, 'Matched'), ('MPYHIQRTI', 25524, nan, True, 'Matched'), ('YYVHKGIWLF', 25585, nan, True, 'Matched'), ('TIDDFRNQVYSTLY', 25580, nan, True, 'Matched'), ('YYVHKGIWLF', 25584, nan, True, 'Matched'), ('MPYHIQRTI', 25470, nan, True, 'Matched'), ('TIDDFRNQVYSTLY', 25582, nan, True, 'Matched'), ('TIDDFRNQVYSTLY', 25578, nan, True, 'Matched'), ('FGNGFVLYV', 25571, nan, True, 'Matched'), ('MPYHIQRTI', 25482, nan, True, 'Matched'), ('TIHLHFLHNETKPCDSVLR', 25541, nan, False, 'Matched'), ('FGNGFVLYV', 25567, nan, True, 'Matched'), ('MPYHIQRTI', 25490, nan, True, 'Matched'), ('MPYHIQRTI', 25493, nan, True, 'Matched'), ('FGNGFVLYV', 25570, nan, True, 'Matched'), ('FGNGFVLYV', 25569, nan, True, 'Matched'), ('TIDDFRNQVYSTLY', 25579, nan, True, 'Matched'), ('MPYHIQRTI', 25471, nan, True, 'Matched'), ('CFEPPQDNQTK', 25545, nan, True, 'Matched'), ('FGNGFVLYV', 25568, nan, True, 'Matched'), ('MPYHIQRTI', 25466, nan, True, 'Matched'), ('MPYHIQRTI', 25492, nan, True, 'Matched'), ('MPYHIQRTI', 25468, nan, True, 'Matched'), ('MPYHIQRTI', 25485, nan, True, 'Matched'), ('MPYHIQRTI', 25491, nan, True, 'Matched'), ('MPYHIQRTI', 25476, nan, True, 'Matched'), ('MPYHIQRTI', 25479, nan, True, 'Matched'), ('FGNGFVLYV', 25566, nan, True, 'Matched'), ('MPYHIQRTI', 25495, nan, True, 'Matched'), ('MPYHIQRTI', 25474, nan, True, 'Matched'), ('TIHLHFLHNETKPCDSVLR', 25540, nan, False, 'Matched'), ('MPYHIQRTI', 25489, nan, True, 'Matched'), ('MPYHIQRTI', 25488, nan, True, 'Matched'), ('TIDDFRNQVYSTLY', 25581, nan, True, 'Matched'), ('MPYHIQRTI', 25481, nan, True, 'Matched'), ('DSVLRMQKSVVIT', 25589, nan, True, 'Matched'), ('YYVHKGIWLF', 25587, nan, True, 'Matched'), ('TIDDFRNQVYSTLY', 25583, nan, True, 'Matched'), ('MPYHIQRTI', 25483, nan, True, 'Matched'), ('YYVHKGIWLF', 25586, nan, True, 'Matched'), ('TIHLHFLHNETKPCDSVLR', 25543, nan, False, 'Matched'), ('MPYHIQRTI', 25473, nan, True, 'Matched'), ('MPYHIQRTI', 25484, nan, True, 'Matched'), ('TIHLHFLHNETKPCDSVLR', 25535, nan, False, 'Matched'), ('MPYHIQRTI', 25478, nan, True, 'Matched'), ('MPYHIQRTI', 25486, nan, True, 'Matched'), ('CIAIVFPVQNINLVTQK', 25560, nan, True, 'Matched'), ('TIHLHFLHNETKPCDSVLR', 25542, nan, False, 'Matched'), ('FLHNETKPCDSVLR', 25593, nan, True, 'Matched'), ('VTQKKARFV', 25598, nan, True, 'Matched'), ('VTQKKARFV', 25599, nan, True, 'Matched'), ('MPYHIQRTI', 25494, nan, True, 'Matched'), ('CIAIVFPVQNINLVTQK', 25562, nan, True, 'Matched'), ('CIAIVFPVQNINLVTQK', 25558, nan, True, 'Matched'), ('DSVLRMQKSVVIT', 25588, nan, True, 'Matched'), ('DSVLRMQKSVVIT', 25590, nan, True, 'Matched'), ('FRNQVYSTLYSMIS', 25602, nan, False, 'Matched'), ('DSVLRMQKSVVITL', 25600, nan, False, 'Matched'), ('FRNQVYSTLYSMISVV', 25594, nan, False, 'Matched'), ('MDETGNLTVSSATCHDTIDDFR', 25427, nan, True, 'Matched'), ('TIHLHFLHNETKPCDSVLR', 25544, nan, False, 'Matched'), ('FRNQVYSTLYSMISVV', 25595, nan, False, 'Matched'), ('TIHLHFLHNETKPCDSVLR', 25536, nan, False, 'Matched'), ('TIHLHFLHNETKPCDSVLR', 25533, nan, False, 'Matched'), ('MDETGNLTVSSATCHDTIDDFR', 25425, nan, True, 'Matched'), ('TIHLHFLHNETKPCDSVLR', 25534, nan, False, 'Matched'), ('TIHLHFLHNETKPCDSVLR', 25532, nan, False, 'Matched'), ('RNQVYSTLYSMIS', 25603, nan, True, 'Matched'), ('CIAIVFPVQNINLVTQK', 25561, nan, True, 'Matched'), ('MDETGNLTVSSATCHDTIDDFR', 25451, nan, True, 'Matched'), ('RNQVYSTLYSMISVV', 25604, nan, False, 'Matched'), ('MDETGNLTVSSATCHDTIDDFR', 25426, nan, True, 'Matched'), ('MDETGNLTVSSATCHDTIDDFR', 25428, nan, True, 'Matched'), ('MDETGNLTVSSATCHDTIDDFR', 25436, nan, True, 'Matched')] | G11: 12 | H11: [('CFEPPQDNQTK', 25552, 'non_standard_modification', True, 'Missed'), ('GIWLFGDFLCR', 25577, 'non_standard_modification', True, 'Missed'), ('GIWLFGDFLCR', 25576, 'non_standard_modification', True, 'Missed'), ('CFEPPQDNQTK', 25553, 'non_standard_modification', True, 'Missed'), ('CIAIVFPVQNINLVTQK', 25564, 'non_standard_modification', True, 'Missed'), ('CFEPPQDNQTK', 25554, 'non_standard_modification', True, 'Missed'), ('CIAIVFPVQNINLVTQK', 25563, 'non_standard_modification', True, 'Missed'), ('CFEPPQDNQTK', 25556, 'non_standard_modification', True, 'Missed'), ('CFEPPQDNQTK', 25555, 'non_standard_modification', True, 'Missed'), ('CFEPPQDNQTK', 25551, 'non_standard_modification', True, 'Missed'), ('TIHLHFLHNETKPCDSVLR', 25526, 'non_standard_modification', False, 'Missed'), ('CIAIVFPVQNINLVTQK', 25565, 'non_standard_modification', True, 'Missed'), ('TIHLHFLHNETKPCDSVLR', 25528, 'non_standard_modification', False, 'Missed'), ('TIHLHFLHNETKPCDSVLR', 25537, 'non_standard_modification', False, 'Missed'), ('TIHLHFLHNETKPCDSVLR', 25527, 'non_standard_modification', False, 'Missed'), ('TIHLHFLHNETKPCDSVLR', 25529, 'non_standard_modification', False, 'Missed'), ('TIHLHFLHNETKPCDSVLR', 25539, 'non_standard_modification', False, 'Missed'), ('DSVLRMQKSVVITLS', 25601, 'HLA2', False, 'Missed'), ('TIHLHFLHNETKPCDSVLR', 25538, 'non_standard_modification', False, 'Missed'), ('QRTIHLHFL', 25596, 'HLA1', True, 'Missed'), ('CIAIVFPVQNINLVTQK', 25557, 'non_standard_modification', True, 'Missed'), ('TIHLHFLHNETKPCDSVLR', 25530, 'non_standard_modification', False, 'Missed'), ('MDETGNLTVSSATCHDTIDDFR', 25398, 'non_standard_modification', True, 'Missed'), ('MDETGNLTVSSATCHDTIDDFR', 25400, 'non_standard_modification', True, 'Missed'), ('MDETGNLTVSSATCHDTIDDFR', 25406, 'non_standard_modification', True, 'Missed'), ('MDETGNLTVSSATCHDTIDDFR', 25402, 'non_standard_modification', True, 'Missed'), ('MDETGNLTVSSATCHDTIDDFR', 25407, 'non_standard_modification', True, 'Missed'), ('MDETGNLTVSSATCHDTIDDFR', 25396, 'non_standard_modification', True, 'Missed'), ('MDETGNLTVSSATCHDTIDDFR', 25395, 'non_standard_modification', True, 'Missed'), ('MDETGNLTVSSATCHDTIDDFR', 25408, 'non_standard_modification', True, 'Missed'), ('MDETGNLTVSSATCHDTIDDFR', 25443, 'non_standard_modification', True, 'Missed'), ('MDETGNLTVSSATCHDTIDDFR', 25450, 'non_standard_modification', True, 'Missed'), ('MDETGNLTVSSATCHDTIDDFR', 25394, 'non_standard_modification', True, 'Missed'), ('MDETGNLTVSSATCHDTIDDFR', 25422, 'non_standard_modification', True, 'Missed'), ('MDETGNLTVSSATCHDTIDDFR', 25445, 'non_standard_modification', True, 'Missed'), ('MDETGNLTVSSATCHDTIDDFR', 25403, 'non_standard_modification', True, 'Missed'), ('MDETGNLTVSSATCHDTIDDFR', 25401, 'non_standard_modification', True, 'Missed'), ('MDETGNLTVSSATCHDTIDDFR', 25405, 'non_standard_modification', True, 'Missed'), ('MDETGNLTVSSATCHDTIDDFR', 25441, 'non_standard_modification', True, 'Missed'), ('MDETGNLTVSSATCHDTIDDFR', 25410, 'non_standard_modification', True, 'Missed'), ('MDETGNLTVSSATCHDTIDDFR', 25409, 'non_standard_modification', True, 'Missed'), ('MDETGNLTVSSATCHDTIDDFR', 25417, 'non_standard_modification', True, 'Missed'), ('MDETGNLTVSSATCHDTIDDFR', 25453, 'non_standard_modification', True, 'Missed'), ('MDETGNLTVSSATCHDTIDDFR', 25416, 'non_standard_modification', True, 'Missed'), ('MDETGNLTVSSATCHDTIDDFR', 25413, 'non_standard_modification', True, 'Missed'), ('MDETGNLTVSSATCHDTIDDFR', 25412, 'non_standard_modification', True, 'Missed'), ('MDETGNLTVSSATCHDTIDDFR', 25429, 'non_standard_modification', True, 'Missed'), ('MDETGNLTVSSATCHDTIDDFR', 25447, 'non_standard_modification', True, 'Missed'), ('MDETGNLTVSSATCHDTIDDFR', 25404, 'non_standard_modification', True, 'Missed'), ('MDETGNLTVSSATCHDTIDDFR', 25419, 'non_standard_modification', True, 'Missed'), ('MDETGNLTVSSATCHDTIDDFR', 25420, 'non_standard_modification', True, 'Missed'), ('MDETGNLTVSSATCHDTIDDFR', 25397, 'non_standard_modification', True, 'Missed'), ('MDETGNLTVSSATCHDTIDDFR', 25411, 'non_standard_modification', True, 'Missed'), ('MDETGNLTVSSATCHDTIDDFR', 25430, 'non_standard_modification', True, 'Missed'), ('MDETGNLTVSSATCHDTIDDFR', 25399, 'non_standard_modification', True, 'Missed'), ('MDETGNLTVSSATCHDTIDDFR', 25418, 'non_standard_modification', True, 'Missed'), ('MDETGNLTVSSATCHDTIDDFR', 25387, 'non_standard_modification', True, 'Missed'), ('MDETGNLTVSSATCHDTIDDFR', 25376, 'non_standard_modification', True, 'Missed'), ('MDETGNLTVSSATCHDTIDDFR', 25392, 'non_standard_modification', True, 'Missed'), ('MPYHIQRTI', 25511, nan, True, 'Matched'), ('MPYHIQRTI', 25502, nan, True, 'Matched'), ('MPYHIQRTI', 25509, nan, True, 'Matched'), ('MPYHIQRTI', 25517, nan, True, 'Matched'), ('MPYHIQRTI', 25507, nan, True, 'Matched'), ('MPYHIQRTI', 25501, nan, True, 'Matched'), ('MPYHIQRTI', 25500, nan, True, 'Matched'), ('MPYHIQRTI', 25498, nan, True, 'Matched'), ('MPYHIQRTI', 25499, nan, True, 'Matched'), ('MPYHIQRTI', 25497, nan, True, 'Matched'), ('MPYHIQRTI', 25510, nan, True, 'Matched'), ('MPYHIQRTI', 25504, nan, True, 'Matched'), ('MPYHIQRTI', 25516, nan, True, 'Matched'), ('MPYHIQRTI', 25514, nan, True, 'Matched'), ('MPYHIQRTI', 25472, nan, True, 'Matched'), ('MDETGNLTVSSATCHDTIDDFR', 25423, nan, True, 'Matched'), ('MPYHIQRTI', 25523, nan, True, 'Matched'), ('MPYHIQRTI', 25519, nan, True, 'Matched'), ('MPYHIQRTI', 25513, nan, True, 'Matched'), ('MPYHIQRTI', 25462, nan, True, 'Matched'), ('MPYHIQRTI', 25520, nan, True, 'Matched'), ('MPYHIQRTI', 25508, nan, True, 'Matched'), ('MPYHIQRTI', 25506, nan, True, 'Matched'), ('MPYHIQRTI', 25512, nan, True, 'Matched'), ('MPYHIQRTI', 25521, nan, True, 'Matched'), ('MPYHIQRTI', 25496, nan, True, 'Matched'), ('MPYHIQRTI', 25503, nan, True, 'Matched'), ('MPYHIQRTI', 25505, nan, True, 'Matched'), ('MPYHIQRTI', 25477, nan, True, 'Matched'), ('MPYHIQRTI', 25456, nan, True, 'Matched'), ('MPYHIQRTI', 25522, nan, True, 'Matched'), ('MPYHIQRTI', 25469, nan, True, 'Matched'), ('MPYHIQRTI', 25459, nan, True, 'Matched'), ('MPYHIQRTI', 25467, nan, True, 'Matched'), ('MPYHIQRTI', 25518, nan, True, 'Matched'), ('MPYHIQRTI', 25515, nan, True, 'Matched'), ('MPYHIQRTI', 25455, nan, True, 'Matched'), ('MPYHIQRTI', 25464, nan, True, 'Matched'), ('MPYHIQRTI', 25475, nan, True, 'Matched'), ('GIWLFGDFLCR', 25575, nan, True, 'Matched'), ('MPYHIQRTI', 25480, nan, True, 'Matched'), ('MPYHIQRTI', 25463, nan, True, 'Matched'), ('CFEPPQDNQTK', 25547, nan, True, 'Matched'), ('MPYHIQRTI', 25465, nan, True, 'Matched'), ('MPYHIQRTI', 25460, nan, True, 'Matched'), ('MPYHIQRTI', 25457, nan, True, 'Matched'), ('FLHNETKPCDSVLR', 25591, nan, True, 'Matched'), ('MPYHIQRTI', 25458, nan, True, 'Matched'), ('CFEPPQDNQTK', 25550, nan, True, 'Matched'), ('MDETGNLTVSSATCHDTIDDFR', 25424, nan, True, 'Matched'), ('MPYHIQRTI', 25461, nan, True, 'Matched'), ('FLHNETKPCDSVLR', 25592, nan, True, 'Matched'), ('MPYHIQRTI', 25487, nan, True, 'Matched'), ('TIHLHFLHNETKPCDSVLR', 25531, nan, False, 'Matched'), ('CFEPPQDNQTK', 25546, nan, True, 'Matched'), ('MPYHIQRTI', 25454, nan, True, 'Matched'), ('CFEPPQDNQTK', 25548, nan, True, 'Matched'), ('CFEPPQDNQTK', 25549, nan, True, 'Matched'), ('CIAIVFPVQNINLVTQK', 25559, nan, True, 'Matched'), ('MPYHIQRTI', 25524, nan, True, 'Matched'), ('YYVHKGIWLF', 25585, nan, True, 'Matched'), ('TIDDFRNQVYSTLY', 25580, nan, True, 'Matched'), ('YYVHKGIWLF', 25584, nan, True, 'Matched'), ('MPYHIQRTI', 25470, nan, True, 'Matched'), ('TIDDFRNQVYSTLY', 25582, nan, True, 'Matched'), ('TIDDFRNQVYSTLY', 25578, nan, True, 'Matched'), ('FGNGFVLYV', 25571, nan, True, 'Matched'), ('MPYHIQRTI', 25482, nan, True, 'Matched'), ('TIHLHFLHNETKPCDSVLR', 25541, nan, False, 'Matched'), ('FGNGFVLYV', 25567, nan, True, 'Matched'), ('MPYHIQRTI', 25490, nan, True, 'Matched'), ('MPYHIQRTI', 25493, nan, True, 'Matched'), ('FGNGFVLYV', 25570, nan, True, 'Matched'), ('FGNGFVLYV', 25569, nan, True, 'Matched'), ('TIDDFRNQVYSTLY', 25579, nan, True, 'Matched'), ('MPYHIQRTI', 25471, nan, True, 'Matched'), ('CFEPPQDNQTK', 25545, nan, True, 'Matched'), ('FGNGFVLYV', 25568, nan, True, 'Matched'), ('MPYHIQRTI', 25466, nan, True, 'Matched'), ('MPYHIQRTI', 25492, nan, True, 'Matched'), ('MPYHIQRTI', 25468, nan, True, 'Matched'), ('MPYHIQRTI', 25485, nan, True, 'Matched'), ('MPYHIQRTI', 25491, nan, True, 'Matched'), ('MPYHIQRTI', 25476, nan, True, 'Matched'), ('MPYHIQRTI', 25479, nan, True, 'Matched'), ('FGNGFVLYV', 25566, nan, True, 'Matched'), ('MPYHIQRTI', 25495, nan, True, 'Matched'), ('MPYHIQRTI', 25474, nan, True, 'Matched'), ('TIHLHFLHNETKPCDSVLR', 25540, nan, False, 'Matched'), ('MPYHIQRTI', 25489, nan, True, 'Matched'), ('MPYHIQRTI', 25488, nan, True, 'Matched'), ('TIDDFRNQVYSTLY', 25581, nan, True, 'Matched'), ('MPYHIQRTI', 25481, nan, True, 'Matched'), ('DSVLRMQKSVVIT', 25589, nan, True, 'Matched'), ('YYVHKGIWLF', 25587, nan, True, 'Matched'), ('TIDDFRNQVYSTLY', 25583, nan, True, 'Matched'), ('MPYHIQRTI', 25483, nan, True, 'Matched'), ('YYVHKGIWLF', 25586, nan, True, 'Matched'), ('TIHLHFLHNETKPCDSVLR', 25543, nan, False, 'Matched'), ('MPYHIQRTI', 25473, nan, True, 'Matched'), ('MPYHIQRTI', 25484, nan, True, 'Matched'), ('TIHLHFLHNETKPCDSVLR', 25535, nan, False, 'Matched'), ('MPYHIQRTI', 25478, nan, True, 'Matched'), ('MPYHIQRTI', 25486, nan, True, 'Matched'), ('CIAIVFPVQNINLVTQK', 25560, nan, True, 'Matched'), ('TIHLHFLHNETKPCDSVLR', 25542, nan, False, 'Matched'), ('FLHNETKPCDSVLR', 25593, nan, True, 'Matched'), ('VTQKKARFV', 25598, nan, True, 'Matched'), ('VTQKKARFV', 25599, nan, True, 'Matched'), ('MPYHIQRTI', 25494, nan, True, 'Matched'), ('CIAIVFPVQNINLVTQK', 25562, nan, True, 'Matched'), ('CIAIVFPVQNINLVTQK', 25558, nan, True, 'Matched'), ('DSVLRMQKSVVIT', 25588, nan, True, 'Matched'), ('DSVLRMQKSVVIT', 25590, nan, True, 'Matched'), ('FRNQVYSTLYSMIS', 25602, nan, False, 'Matched'), ('DSVLRMQKSVVITL', 25600, nan, False, 'Matched'), ('FRNQVYSTLYSMISVV', 25594, nan, False, 'Matched'), ('MDETGNLTVSSATCHDTIDDFR', 25427, nan, True, 'Matched'), ('TIHLHFLHNETKPCDSVLR', 25544, nan, False, 'Matched'), ('FRNQVYSTLYSMISVV', 25595, nan, False, 'Matched'), ('TIHLHFLHNETKPCDSVLR', 25536, nan, False, 'Matched'), ('TIHLHFLHNETKPCDSVLR', 25533, nan, False, 'Matched'), ('MDETGNLTVSSATCHDTIDDFR', 25425, nan, True, 'Matched'), ('TIHLHFLHNETKPCDSVLR', 25534, nan, False, 'Matched'), ('TIHLHFLHNETKPCDSVLR', 25532, nan, False, 'Matched'), ('RNQVYSTLYSMIS', 25603, nan, True, 'Matched'), ('CIAIVFPVQNINLVTQK', 25561, nan, True, 'Matched'), ('MDETGNLTVSSATCHDTIDDFR', 25451, nan, True, 'Matched'), ('RNQVYSTLYSMISVV', 25604, nan, False, 'Matched'), ('MDETGNLTVSSATCHDTIDDFR', 25426, nan, True, 'Matched'), ('MDETGNLTVSSATCHDTIDDFR', 25428, nan, True, 'Matched'), ('MDETGNLTVSSATCHDTIDDFR', 25436, nan, True, 'Matched')] | I11: 13 | J11: =IFERROR(VLOOKUP(A11,dbg_proteins!$A$2:$A$20161,1,FALSE)," ---") -> Q9Y271
